Workbook

Sheet Timeline Feb'26

Sheet Overview
A1: ="Overall Company KPI Achievement "&TEXT(TODAY()-29,"MMM-YY") -> Overall Company KPI Achievement Mar-26
A2: Company Measurement
B3: Month | E3: Accumulate
B4: Total | C4: Achieved | D4: Unachieved | E4: Total | F4: Achieved | G4: Unachieved
A5: 1. Safety | B5: 3 | C5: 3 | D5: 0 | E5: 4 | F5: 3 | G5: 3
B6: 5 | C6: 4 | D6: 1 | E6: 5 | F6: 1 | G6: 4
A7: 2. Quality | B7: 7 | C7: =SUMIF(Summary_SDM!C7:C110,Overview!#REF!,Summary_SDM!Z7:Z109) -> 0 | D7: =SUMIF(Summary_SDM!D7:D110,Overview!#REF!,Summary_SDM!AA7:AA107) -> 0 | E7: 7 | F7: =SUMIF(Summary_SDM!F7:F110,Overview!#REF!,Summary_SDM!AC7:AC107) -> 0 | G7: =SUMIF(Summary_SDM!G7:G110,Overview!#REF!,Summary_SDM!AD7:AD107) -> 0
B8: 2 | C8: =SUMIF(Summary_SDM!C8:C111,Overview!#REF!,Summary_SDM!Z8:Z110) -> 0 | D8: =SUMIF(Summary_SDM!D8:D111,Overview!#REF!,Summary_SDM!AA8:AA108) -> 0 | E8: 2 | F8: =SUMIF(Summary_SDM!F8:F111,Overview!#REF!,Summary_SDM!AC8:AC108) -> 0 | G8: =SUMIF(Summary_SDM!G8:G111,Overview!#REF!,Summary_SDM!AD8:AD108) -> 0
A9: 3. Delivery | B9: 2 | C9: 2 | D9: =SUMIF(Summary_SDM!D9:D112,Overview!#REF!,Summary_SDM!AA9:AA109) -> 0 | E9: 2 | F9: 2 | G9: 0
B10: 2 | C10: 2 | D10: =SUMIF(Summary_SDM!D10:D113,Overview!#REF!,Summary_SDM!AA10:AA110) -> 0 | E10: 2 | F10: 2 | G10: 0
B11: 1 | C11: 1 | D11: =SUMIF(Summary_SDM!D11:D114,Overview!#REF!,Summary_SDM!AA11:AA111) -> 0 | E11: 1 | F11: 1 | G11: 0
A12: 4. Compliance | B12: 18 | E12: 6
A13: 5. HR | B13: - | C13: - | D13: - | E13: 5 | F13: 5 | G13: 0
A14: 6. Attractive | B14: 3 | C14: 2 | D14: 1 | E14: 3 | F14: 2 | G14: 1
A15: 7.Envi. | B15: 7 | C15: 6 | D15: 1 | E15: 8 | F15: 7 | G15: 1
A16: 8. Cost | B16: 7 | C16: 5 | D16: 2 | E16: 7 | F16: 6 | G16: 1
B17: =SUM(B5:B16) -> 57 | E17: =SUM(E5:E16) -> 52

Sheet Summary_SDM
B2: ="Overall Company KPI Achievement "&TEXT(O2,"MMM-YY") -> Overall Company KPI Achievement Feb-26 | O2: 46054
B3: Company Measurement | F3: Freq. | G3: Unit | H3: FY25 Target | I3: Target | J3: Result | K3: Judge | L3: Accu. Target | M3: Accu. Result | N3: Accu. Judge | O3: President award | P3: Explain Item ●：Need ○：No Need | S3: Key of problem | T3: Explain item/No. | V3: Overview result | Y3: Acc | Z3: Month
P4: Monthly | Q4: Accu. | R4: C/S
B5: 1. Safety | C5: worksite | D5: 1 | E5: 1-Grade accident | F5: 1/M | G5: Case | H5: 0 | I5: =SUMIFS(SDM_Data!$J$2:$J$1348,SDM_Data!$B$2:$B$1348,C5,SDM_Data!$D$2:$D$1348,E5,SDM_Data!$E$2:$E$1348,G5,SDM_Data!$I$2:$I$1348,$O$2) -> 0 | J5: =SUMIFS(SDM_Data!$K$2:$K$1348,SDM_Data!$B$2:$B$1348,C5,SDM_Data!$D$2:$D$1348,E5,SDM_Data!$E$2:$E$1348,G5,SDM_Data!$I$2:$I$1348,$O$2) -> 0 | K5: =IF(J5>I5,"X","O") -> O | L5: =SUMIFS(SDM_Data!$L$2:$L$1348,SDM_Data!$B$2:$B$1348,C5,SDM_Data!$D$2:$D$1348,E5,SDM_Data!$E$2:$E$1348,G5,SDM_Data!$I$2:$I$1348,$O$2) -> 0 | M5: =SUMIFS(SDM_Data!$M$2:$M$1348,SDM_Data!$B$2:$B$1348,C5,SDM_Data!$D$2:$D$1348,E5,SDM_Data!$E$2:$E$1348,G5,SDM_Data!$I$2:$I$1348,$O$2) -> 0 | N5: =IF(M5>L5,"X","O") -> O | O5: =IF(N5="O","15/15","0/15") -> 15/15 | P5: =IF(K5="X","l","") | Q5: =IF(N5="X","¡","") | S5: =Safety!B20 -> 1.Man : Authorized person Not follow regulation 2.System : Not have regulation to specific the Type of truck in each operation. | T5: SHE Monthly /19-Mar | V5: Monthly result | Y5: =IF(N5="O",1,0) -> 1 | Z5: =IF(K5="O",1,0) -> 1
C6: worksite | D6: =D5+1 -> 2 | E6: Reoccurrence | F6: 1/M | G6: Case | H6: 0 | I6: =SUMIFS(SDM_Data!$J$2:$J$1348,SDM_Data!$B$2:$B$1348,C6,SDM_Data!$D$2:$D$1348,E6,SDM_Data!$E$2:$E$1348,G6,SDM_Data!$I$2:$I$1348,$O$2) -> 0 | J6: =SUMIFS(SDM_Data!$K$2:$K$1348,SDM_Data!$B$2:$B$1348,C6,SDM_Data!$D$2:$D$1348,E6,SDM_Data!$E$2:$E$1348,G6,SDM_Data!$I$2:$I$1348,$O$2) -> 1 | K6: =IF(J6>I6,"X","O") -> X | L6: =SUMIFS(SDM_Data!$L$2:$L$1348,SDM_Data!$B$2:$B$1348,C6,SDM_Data!$D$2:$D$1348,E6,SDM_Data!$E$2:$E$1348,G6,SDM_Data!$I$2:$I$1348,$O$2) -> 0 | M6: =SUMIFS(SDM_Data!$M$2:$M$1348,SDM_Data!$B$2:$B$1348,C6,SDM_Data!$D$2:$D$1348,E6,SDM_Data!$E$2:$E$1348,G6,SDM_Data!$I$2:$I$1348,$O$2) -> 4 | N6: =IF(M6>L6,"X","O") -> X | O6: - | P6: =IF(K6="X","l","") -> l | Q6: =IF(N6="X","¡","") -> ¡ | T6: Report by | V6: Achieved | W6: Unachieved | X6: Total | Y6: =IF(N6="O",1,0) -> 0 | Z6: =IF(K6="O",1,0) -> 0
C7: Worksite | D7: 3 | E7: Near miss | F7: 1/M | G7: Case | H7: 4 | I7: =SUMIFS(SDM_Data!$J$2:$J$1348,SDM_Data!$B$2:$B$1348,C7,SDM_Data!$D$2:$D$1348,E7,SDM_Data!$E$2:$E$1348,G7,SDM_Data!$I$2:$I$1348,$O$2) -> 0 | J7: =SUMIFS(SDM_Data!$K$2:$K$1348,SDM_Data!$B$2:$B$1348,C7,SDM_Data!$D$2:$D$1348,E7,SDM_Data!$E$2:$E$1348,G7,SDM_Data!$I$2:$I$1348,$O$2) -> 0 | K7: =IF(J7>I7,"X","O") -> O | L7: =SUMIFS(SDM_Data!$L$2:$L$1348,SDM_Data!$B$2:$B$1348,C7,SDM_Data!$D$2:$D$1348,E7,SDM_Data!$E$2:$E$1348,G7,SDM_Data!$I$2:$I$1348,$O$2) -> 3 | M7: =SUMIFS(SDM_Data!$M$2:$M$1348,SDM_Data!$B$2:$B$1348,C7,SDM_Data!$D$2:$D$1348,E7,SDM_Data!$E$2:$E$1348,G7,SDM_Data!$I$2:$I$1348,$O$2) -> 3 | N7: =IF(M7>L7,"X","O") -> O | O7: - | P7: =IF(K7="X","l","") | Q7: =IF(N7="X","¡","") | R7: s | T7: K.Wannapa MGR | V7: =SUM(Z5:Z107) -> 36 | W7: =X7-V7 -> 18 | X7: =COUNT(Z5:Z107) -> 54 | Y7: =IF(N7="O",1,0) -> 1 | Z7: =IF(K7="O",1,0) -> 1
C8: worksite | D8: 4 | E8: 8-High risk audit (New) | F8: 1/Y | G8: Case | H8: 4 | I8: - | J8: - | K8: - | L8: 4 | M8: 5 | N8: =IF(M8>L8,"X","O") -> X | O8: - | P8: =IF(K8="X","l","") | Q8: =IF(N8="X","¡","") -> ¡ | T8: Result Oct'25 | Y8: =IF(N8="O",1,0) -> 0
C9: worksite | E9: 8-High risk audit (Reccourance) | F9: 1/Y | G9: Case | H9: 0 | I9: - | J9: - | K9: - | L9: =SUMIFS(SDM_Data!$L$2:$L$1348,SDM_Data!$B$2:$B$1348,C9,SDM_Data!$D$2:$D$1348,E9,SDM_Data!$E$2:$E$1348,G9,SDM_Data!$I$2:$I$1348,$O$2) -> 0 | M9: =SUMIFS(SDM_Data!$M$2:$M$1348,SDM_Data!$B$2:$B$1348,C9,SDM_Data!$D$2:$D$1348,E9,SDM_Data!$E$2:$E$1348,G9,SDM_Data!$I$2:$I$1348,$O$2) -> 0 | N9: =IF(M9>L9,"X","O") -> O | O9: - | P9: =IF(K9="X","l","") | Q9: =IF(N9="X","¡","") | V9: =V7/X7 -> 0.66666667
C10: Traffic | D10: 5 | E10: Fatal | F10: 1/M | G10: Case | H10: 0 | I10: =SUMIFS(SDM_Data!$J$2:$J$1348,SDM_Data!$B$2:$B$1348,C10,SDM_Data!$D$2:$D$1348,E10,SDM_Data!$E$2:$E$1348,G10,SDM_Data!$I$2:$I$1348,$O$2) -> 0 | J10: =SUMIFS(SDM_Data!$K$2:$K$1348,SDM_Data!$B$2:$B$1348,C10,SDM_Data!$D$2:$D$1348,E10,SDM_Data!$E$2:$E$1348,G10,SDM_Data!$I$2:$I$1348,$O$2) -> 0 | K10: =IF(J10>I10,"X","O") -> O | L10: =SUMIFS(SDM_Data!$L$2:$L$1348,SDM_Data!$B$2:$B$1348,C10,SDM_Data!$D$2:$D$1348,E10,SDM_Data!$E$2:$E$1348,G10,SDM_Data!$I$2:$I$1348,$O$2) -> 0 | M10: =SUMIFS(SDM_Data!$M$2:$M$1348,SDM_Data!$B$2:$B$1348,C10,SDM_Data!$D$2:$D$1348,E10,SDM_Data!$E$2:$E$1348,G10,SDM_Data!$I$2:$I$1348,$O$2) -> 1 | N10: =IF(M10>L10,"X","O") -> X | O10: - | P10: =IF(K10="X","l","") | Q10: =IF(N10="X","¡","") -> ¡ | R10: c | S10: - | T10: SHE Monthly /19-Mar | Y10: =IF(N10="O",1,0) -> 0 | Z10: =IF(K10="O",1,0) -> 1
C11: Traffic | D11: 6 | E11: Injury | F11: 1/M | G11: Case | H11: 0 | I11: =SUMIFS(SDM_Data!$J$2:$J$1348,SDM_Data!$B$2:$B$1348,C11,SDM_Data!$D$2:$D$1348,E11,SDM_Data!$E$2:$E$1348,G11,SDM_Data!$I$2:$I$1348,$O$2) -> 0 | J11: =SUMIFS(SDM_Data!$K$2:$K$1348,SDM_Data!$B$2:$B$1348,C11,SDM_Data!$D$2:$D$1348,E11,SDM_Data!$E$2:$E$1348,G11,SDM_Data!$I$2:$I$1348,$O$2) -> 0 | K11: =IF(J11>I11,"X","O") -> O | L11: =SUMIFS(SDM_Data!$L$2:$L$1348,SDM_Data!$B$2:$B$1348,C11,SDM_Data!$D$2:$D$1348,E11,SDM_Data!$E$2:$E$1348,G11,SDM_Data!$I$2:$I$1348,$O$2) -> 0 | M11: =SUMIFS(SDM_Data!$M$2:$M$1348,SDM_Data!$B$2:$B$1348,C11,SDM_Data!$D$2:$D$1348,E11,SDM_Data!$E$2:$E$1348,G11,SDM_Data!$I$2:$I$1348,$O$2) -> 2 | N11: =IF(M11>L11,"X","O") -> X | O11: - | P11: =IF(K11="X","¡","") | Q11: =IF(N11="X","¡","") -> ¡ | T11: Report by | Y11: =IF(N11="O",1,0) -> 0 | Z11: =IF(K11="O",1,0) -> 1
C12: Traffic | D12: 7 | E12: Illegal & dangerous driving | F12: 1/M | G12: Case | H12: 0 | I12: =SUMIFS(SDM_Data!$J$2:$J$1348,SDM_Data!$B$2:$B$1348,C12,SDM_Data!$D$2:$D$1348,E12,SDM_Data!$E$2:$E$1348,G12,SDM_Data!$I$2:$I$1348,$O$2) -> 0 | J12: =SUMIFS(SDM_Data!$K$2:$K$1348,SDM_Data!$B$2:$B$1348,C12,SDM_Data!$D$2:$D$1348,E12,SDM_Data!$E$2:$E$1348,G12,SDM_Data!$I$2:$I$1348,$O$2) -> 0 | K12: =IF(J12>I12,"X","O") -> O | L12: =SUMIFS(SDM_Data!$L$2:$L$1348,SDM_Data!$B$2:$B$1348,C12,SDM_Data!$D$2:$D$1348,E12,SDM_Data!$E$2:$E$1348,G12,SDM_Data!$I$2:$I$1348,$O$2) -> 0 | M12: =SUMIFS(SDM_Data!$M$2:$M$1348,SDM_Data!$B$2:$B$1348,C12,SDM_Data!$D$2:$D$1348,E12,SDM_Data!$E$2:$E$1348,G12,SDM_Data!$I$2:$I$1348,$O$2) -> 2 | N12: =IF(M12>L12,"X","O") -> X | O12: - | P12: =IF(K12="X","l","") | Q12: =IF(N12="X","¡","") -> ¡ | T12: K.Tharathip MGR | V12: Accumulate result | Y12: =IF(N12="O",1,0) -> 0 | Z12: =IF(K12="O",1,0) -> 1
C13: Traffic | D13: 8 | E13: Hit | F13: 1/M | G13: Case | H13: 0 | I13: =SUMIFS(SDM_Data!$J$2:$J$1348,SDM_Data!$B$2:$B$1348,C13,SDM_Data!$D$2:$D$1348,E13,SDM_Data!$E$2:$E$1348,G13,SDM_Data!$I$2:$I$1348,$O$2) -> 0 | J13: =SUMIFS(SDM_Data!$K$2:$K$1348,SDM_Data!$B$2:$B$1348,C13,SDM_Data!$D$2:$D$1348,E13,SDM_Data!$E$2:$E$1348,G13,SDM_Data!$I$2:$I$1348,$O$2) -> 0 | K13: =IF(J13>I13,"X","O") -> O | L13: =SUMIFS(SDM_Data!$L$2:$L$1348,SDM_Data!$B$2:$B$1348,C13,SDM_Data!$D$2:$D$1348,E13,SDM_Data!$E$2:$E$1348,G13,SDM_Data!$I$2:$I$1348,$O$2) -> 0 | M13: =SUMIFS(SDM_Data!$M$2:$M$1348,SDM_Data!$B$2:$B$1348,C13,SDM_Data!$D$2:$D$1348,E13,SDM_Data!$E$2:$E$1348,G13,SDM_Data!$I$2:$I$1348,$O$2) -> 1 | N13: =IF(M13>L13,"X","O") -> X | O13: =IF(N13="O","10/10","0/10") -> 0/10 | P13: =IF(K13="X","¡","") | Q13: =IF(N13="X","¡","") -> ¡ | V13: Achieved | W13: Unachieved | X13: Total | Y13: =IF(N13="O",1,0) -> 0 | Z13: =IF(K13="O",1,0) -> 1
C14: Traffic | D14: 9 | E14: Hit something | F14: 1/M | G14: Case | H14: 3 | I14: =SUMIFS(SDM_Data!$J$2:$J$1348,SDM_Data!$B$2:$B$1348,C14,SDM_Data!$D$2:$D$1348,E14,SDM_Data!$E$2:$E$1348,G14,SDM_Data!$I$2:$I$1348,$O$2) -> 0 | J14: =SUMIFS(SDM_Data!$K$2:$K$1348,SDM_Data!$B$2:$B$1348,C14,SDM_Data!$D$2:$D$1348,E14,SDM_Data!$E$2:$E$1348,G14,SDM_Data!$I$2:$I$1348,$O$2) -> 0 | K14: =IF(J14>I14,"X","O") -> O | L14: =SUMIFS(SDM_Data!$L$2:$L$1348,SDM_Data!$B$2:$B$1348,C14,SDM_Data!$D$2:$D$1348,E14,SDM_Data!$E$2:$E$1348,G14,SDM_Data!$I$2:$I$1348,$O$2) -> 3 | M14: =SUMIFS(SDM_Data!$M$2:$M$1348,SDM_Data!$B$2:$B$1348,C14,SDM_Data!$D$2:$D$1348,E14,SDM_Data!$E$2:$E$1348,G14,SDM_Data!$I$2:$I$1348,$O$2) -> 2 | N14: =IF(M14>L14,"X","O") -> O | O14: - | P14: =IF(K14="X","l","") | Q14: =IF(N14="X","¡","") | R14: c | V14: =SUM(Y5:Y107) -> 43 | W14: =X14-V14 -> 28 | X14: =COUNT(Y5:Y107) -> 71 | Y14: =IF(N14="O",1,0) -> 1 | Z14: =IF(K14="O",1,0) -> 1
B15: 2. Quality | C15: Claim | D15: =D14+1 -> 10 | E15: Critical claim | F15: 1/M | G15: Case | H15: 0 | I15: =SUMIFS(SDM_Data!$J$2:$J$1348,SDM_Data!$B$2:$B$1348,C15,SDM_Data!$D$2:$D$1348,E15,SDM_Data!$E$2:$E$1348,G15,SDM_Data!$I$2:$I$1348,$O$2) -> 0 | J15: =SUMIFS(SDM_Data!$K$2:$K$1348,SDM_Data!$B$2:$B$1348,C15,SDM_Data!$D$2:$D$1348,E15,SDM_Data!$E$2:$E$1348,G15,SDM_Data!$I$2:$I$1348,$O$2) -> 0 | K15: =IF(J15>I15,"X","O") -> O | L15: =SUMIFS(SDM_Data!$L$2:$L$1348,SDM_Data!$B$2:$B$1348,C15,SDM_Data!$D$2:$D$1348,E15,SDM_Data!$E$2:$E$1348,G15,SDM_Data!$I$2:$I$1348,$O$2) -> 0 | M15: =SUMIFS(SDM_Data!$M$2:$M$1348,SDM_Data!$B$2:$B$1348,C15,SDM_Data!$D$2:$D$1348,E15,SDM_Data!$E$2:$E$1348,G15,SDM_Data!$I$2:$I$1348,$O$2) -> 0 | N15: =IF(M15>L15,"X","O") -> O | O15: =IF(N15="O","15/15","0/15") -> 15/15 | P15: =IF(K15="X","l","") | Q15: =IF(N15="X","¡","") | Y15: =IF(N15="O",1,0) -> 1 | Z15: =IF(K15="O",1,0) -> 1
C16: Claim | D16: =D15+1 -> 11 | E16: 0-km claim (Official) | F16: 1/M | G16: Case | H16: 4 | I16: =SUMIFS(SDM_Data!$J$2:$J$1348,SDM_Data!$B$2:$B$1348,C16,SDM_Data!$D$2:$D$1348,E16,SDM_Data!$E$2:$E$1348,G16,SDM_Data!$I$2:$I$1348,$O$2) -> 0 | J16: =SUMIFS(SDM_Data!$K$2:$K$1348,SDM_Data!$B$2:$B$1348,C16,SDM_Data!$D$2:$D$1348,E16,SDM_Data!$E$2:$E$1348,G16,SDM_Data!$I$2:$I$1348,$O$2) -> 1 | K16: =IF(J16>I16,"X","O") -> X | L16: =SUMIFS(SDM_Data!$L$2:$L$1348,SDM_Data!$B$2:$B$1348,C16,SDM_Data!$D$2:$D$1348,E16,SDM_Data!$E$2:$E$1348,G16,SDM_Data!$I$2:$I$1348,$O$2) -> 4 | M16: =SUMIFS(SDM_Data!$M$2:$M$1348,SDM_Data!$B$2:$B$1348,C16,SDM_Data!$D$2:$D$1348,E16,SDM_Data!$E$2:$E$1348,G16,SDM_Data!$I$2:$I$1348,$O$2) -> 4 | N16: =IF(M16>L16,"X","O") -> O | O16: =IF(N16="O","10/10","0/10") -> 10/10 | P16: =IF(K16="X","l","") -> l | Q16: =IF(N16="X","¡","") | S16: 1. STM HP5S Engine cannot start (F/M Glue) Cause: Glue from jig ball air leak test at cylinder grinding process | T16: Quality monthly 11-Mar Report by Suphatcha MGR | V16: =V14/X14 -> 0.6056338 | Y16: =IF(N16="O",1,0) -> 1 | Z16: =IF(K16="O",1,0) -> 0
C17: Claim | D17: =D16+1 -> 12 | E17: 0-km claim (All DN response) | F17: 1/M | G17: Case | H17: 9 | I17: =SUMIFS(SDM_Data!$J$2:$J$1348,SDM_Data!$B$2:$B$1348,C17,SDM_Data!$D$2:$D$1348,E17,SDM_Data!$E$2:$E$1348,G17,SDM_Data!$I$2:$I$1348,$O$2) -> 1 | J17: =SUMIFS(SDM_Data!$K$2:$K$1348,SDM_Data!$B$2:$B$1348,C17,SDM_Data!$D$2:$D$1348,E17,SDM_Data!$E$2:$E$1348,G17,SDM_Data!$I$2:$I$1348,$O$2) -> 1 | K17: =IF(J17>I17,"X","O") -> O | L17: =SUMIFS(SDM_Data!$L$2:$L$1348,SDM_Data!$B$2:$B$1348,C17,SDM_Data!$D$2:$D$1348,E17,SDM_Data!$E$2:$E$1348,G17,SDM_Data!$I$2:$I$1348,$O$2) -> 9 | M17: =SUMIFS(SDM_Data!$M$2:$M$1348,SDM_Data!$B$2:$B$1348,C17,SDM_Data!$D$2:$D$1348,E17,SDM_Data!$E$2:$E$1348,G17,SDM_Data!$I$2:$I$1348,$O$2) -> 10 | N17: =IF(M17>L17,"X","O") -> X | O17: - | P17: =IF(K17="X","l","") | Q17: =IF(N17="X","¡","") -> ¡ | R17: c | Y17: =IF(N17="O",1,0) -> 0 | Z17: =IF(K17="O",1,0) -> 1
C18: Claim | D18: =D17+1 -> 13 | E18: Market claim | F18: 1/M | G18: Case | H18: - | I18: =SUMIFS(SDM_Data!$J$2:$J$1348,SDM_Data!$B$2:$B$1348,C18,SDM_Data!$D$2:$D$1348,E18,SDM_Data!$E$2:$E$1348,G18,SDM_Data!$I$2:$I$1348,$O$2) -> 0 | J18: =SUMIFS(SDM_Data!$K$2:$K$1348,SDM_Data!$B$2:$B$1348,C18,SDM_Data!$D$2:$D$1348,E18,SDM_Data!$E$2:$E$1348,G18,SDM_Data!$I$2:$I$1348,$O$2) -> 0 | K18: =IF(J18>I18,"X","O") -> O | L18: =SUMIFS(SDM_Data!$L$2:$L$1348,SDM_Data!$B$2:$B$1348,C18,SDM_Data!$D$2:$D$1348,E18,SDM_Data!$E$2:$E$1348,G18,SDM_Data!$I$2:$I$1348,$O$2) -> 0 | M18: =SUMIFS(SDM_Data!$M$2:$M$1348,SDM_Data!$B$2:$B$1348,C18,SDM_Data!$D$2:$D$1348,E18,SDM_Data!$E$2:$E$1348,G18,SDM_Data!$I$2:$I$1348,$O$2) -> 1 | N18: X | O18: - | P18: =IF(K18="X","l","") | Q18: =IF(N18="X","¡","") -> ¡ | R18: c | Y18: =IF(N18="O",1,0) -> 0 | Z18: =IF(K18="O",1,0) -> 1
C19: Claim | D19: =D18+1 -> 14 | E19: OGC claim | F19: 1/M | G19: Case | H19: 6 | I19: =SUMIFS(SDM_Data!$J$2:$J$1348,SDM_Data!$B$2:$B$1348,C19,SDM_Data!$D$2:$D$1348,E19,SDM_Data!$E$2:$E$1348,G19,SDM_Data!$I$2:$I$1348,$O$2) -> 0 | J19: =SUMIFS(SDM_Data!$K$2:$K$1348,SDM_Data!$B$2:$B$1348,C19,SDM_Data!$D$2:$D$1348,E19,SDM_Data!$E$2:$E$1348,G19,SDM_Data!$I$2:$I$1348,$O$2) -> 1 | K19: =IF(J19>I19,"X","O") -> X | L19: =SUMIFS(SDM_Data!$L$2:$L$1348,SDM_Data!$B$2:$B$1348,C19,SDM_Data!$D$2:$D$1348,E19,SDM_Data!$E$2:$E$1348,G19,SDM_Data!$I$2:$I$1348,$O$2) -> 5 | M19: =SUMIFS(SDM_Data!$M$2:$M$1348,SDM_Data!$B$2:$B$1348,C19,SDM_Data!$D$2:$D$1348,E19,SDM_Data!$E$2:$E$1348,G19,SDM_Data!$I$2:$I$1348,$O$2) -> 17 | N19: =IF(M19>L19,"X","O") -> X | O19: - | P19: =IF(K19="X","l","") -> l | Q19: =IF(N19="X","¡","") -> ¡ | R19: c | V19: President award result | Y19: =IF(N19="O",1,0) -> 0 | Z19: =IF(K19="O",1,0) -> 0
C20: Claim | D20: =D19+1 -> 15 | E20: Supplier NCR | F20: 1/M | G20: Case | H20: 6 | I20: =SUMIFS(SDM_Data!$J$2:$J$1348,SDM_Data!$B$2:$B$1348,C20,SDM_Data!$D$2:$D$1348,E20,SDM_Data!$E$2:$E$1348,G20,SDM_Data!$I$2:$I$1348,$O$2) -> 0 | J20: =SUMIFS(SDM_Data!$K$2:$K$1348,SDM_Data!$B$2:$B$1348,C20,SDM_Data!$D$2:$D$1348,E20,SDM_Data!$E$2:$E$1348,G20,SDM_Data!$I$2:$I$1348,$O$2) -> 2 | K20: =IF(J20>I20,"X","O") -> X | L20: =SUMIFS(SDM_Data!$L$2:$L$1348,SDM_Data!$B$2:$B$1348,C20,SDM_Data!$D$2:$D$1348,E20,SDM_Data!$E$2:$E$1348,G20,SDM_Data!$I$2:$I$1348,$O$2) -> 5 | M20: =SUMIFS(SDM_Data!$M$2:$M$1348,SDM_Data!$B$2:$B$1348,C20,SDM_Data!$D$2:$D$1348,E20,SDM_Data!$E$2:$E$1348,G20,SDM_Data!$I$2:$I$1348,$O$2) -> 16 | N20: =IF(M20>L20,"X","O") -> X | O20: - | P20: =IF(K20="X","l","") -> l | Q20: =IF(N20="X","¡","") -> ¡ | R20: c | S20: =Q_Claim!$K$39 -> 1. DMHU Plug rail Coating peeling Cause: Under invesitgate with supplier & DIAT 2. G3S Inlet connector missing ball Cause: Under investigation | V20: =SUM(RIGHT(O5,2)+RIGHT(O13,2)+RIGHT(O15,2)+RIGHT(O16,2)+RIGHT(O22,2)+RIGHT(O88,1)+RIGHT(O99,1)+RIGHT(O101,2)+RIGHT(O102,2))&"/100" -> 100/100 | Y20: =IF(N20="O",1,0) -> 0 | Z20: =IF(K20="O",1,0) -> 0
C21: Claim | D21: =D20+1 -> 16 | E21: Internal NCR | F21: 1/M | G21: Case | H21: 5 | I21: =SUMIFS(SDM_Data!$J$2:$J$1348,SDM_Data!$B$2:$B$1348,C21,SDM_Data!$D$2:$D$1348,E21,SDM_Data!$E$2:$E$1348,G21,SDM_Data!$I$2:$I$1348,$O$2) -> 1 | J21: =SUMIFS(SDM_Data!$K$2:$K$1348,SDM_Data!$B$2:$B$1348,C21,SDM_Data!$D$2:$D$1348,E21,SDM_Data!$E$2:$E$1348,G21,SDM_Data!$I$2:$I$1348,$O$2) -> 2 | K21: =IF(J21>I21,"X","O") -> X | L21: =SUMIFS(SDM_Data!$L$2:$L$1348,SDM_Data!$B$2:$B$1348,C21,SDM_Data!$D$2:$D$1348,E21,SDM_Data!$E$2:$E$1348,G21,SDM_Data!$I$2:$I$1348,$O$2) -> 5 | M21: =SUMIFS(SDM_Data!$M$2:$M$1348,SDM_Data!$B$2:$B$1348,C21,SDM_Data!$D$2:$D$1348,E21,SDM_Data!$E$2:$E$1348,G21,SDM_Data!$I$2:$I$1348,$O$2) -> 3 | N21: =IF(M21>L21,"X","O") -> O | O21: - | P21: =IF(K21="X","l","") -> l | Q21: =IF(N21="X","¡","") | S21: =Q_Claim!$F$39 -> 1. Rail Cap pipe fuel return Broken Cause: Under invesitgation 2. G3S Inlet connector missing ball Cause: Under investigation | T21: Quality monthly 11-Mar Report by Suphatcha MGR | Y21: =IF(N21="O",1,0) -> 1 | Z21: =IF(K21="O",1,0) -> 0
C22: Loss | D22: =D21+1 -> 17 | E22: Cost of spoilage | F22: 1/M | G22: % | H22: 0.0056 | I22: =SUMIFS(SDM_Data!$J$2:$J$1348,SDM_Data!$B$2:$B$1348,C22,SDM_Data!$D$2:$D$1348,E22,SDM_Data!$E$2:$E$1348,G22,SDM_Data!$I$2:$I$1348,$O$2) -> 0.0057988396 | J22: =SUMIFS(SDM_Data!$K$2:$K$1348,SDM_Data!$B$2:$B$1348,C22,SDM_Data!$D$2:$D$1348,E22,SDM_Data!$E$2:$E$1348,G22,SDM_Data!$I$2:$I$1348,$O$2) -> 0.0060065472 | K22: =IF(J22>I22,"X","O") -> X | L22: =SUMIFS(SDM_Data!$L$2:$L$1348,SDM_Data!$B$2:$B$1348,C22,SDM_Data!$D$2:$D$1348,E22,SDM_Data!$E$2:$E$1348,G22,SDM_Data!$I$2:$I$1348,$O$2) -> 0.00564 | M22: =SUMIFS(SDM_Data!$M$2:$M$1348,SDM_Data!$B$2:$B$1348,C22,SDM_Data!$D$2:$D$1348,E22,SDM_Data!$E$2:$E$1348,G22,SDM_Data!$I$2:$I$1348,$O$2) -> 0.0052878596 | N22: =IF(M22>L22,"X","O") -> O | O22: =IF(N22="O","10/10","0/10") -> 10/10 | P22: =IF(K22="X","l","") -> l | Q22: =IF(N22="X","¡","") | S22: GDP +1.24MB :P/L NG 1,146pcs [Plan 0.24%/Act 0.73%/Diff +0.49%] 1) Occure material DNTH cutting 601 run-out NG forecast end of Mar'26 (Forecast Mar'26 Over +1.2MB) 2) Occure in SDM process Relief seat grd. CPK 1.33 improvement M/C & Jig accuracy | Y22: =IF(N22="O",1,0) -> 1 | Z22: =IF(K22="O",1,0) -> 0
C23: Loss | E23: Cost of spoilage | F23: 1/M | G23: MB | H23: 162.9 | I23: =SUMIFS(SDM_Data!$J$2:$J$1348,SDM_Data!$B$2:$B$1348,C23,SDM_Data!$D$2:$D$1348,E23,SDM_Data!$E$2:$E$1348,G23,SDM_Data!$I$2:$I$1348,$O$2) -> 16.232374 | J23: =SUMIFS(SDM_Data!$K$2:$K$1348,SDM_Data!$B$2:$B$1348,C23,SDM_Data!$D$2:$D$1348,E23,SDM_Data!$E$2:$E$1348,G23,SDM_Data!$I$2:$I$1348,$O$2) -> 16.813799 | K23: =IF(J23>I23,"X","O") -> X | L23: =SUMIFS(SDM_Data!$L$2:$L$1348,SDM_Data!$B$2:$B$1348,C23,SDM_Data!$D$2:$D$1348,E23,SDM_Data!$E$2:$E$1348,G23,SDM_Data!$I$2:$I$1348,$O$2) -> 159.61695 | M23: =SUMIFS(SDM_Data!$M$2:$M$1348,SDM_Data!$B$2:$B$1348,C23,SDM_Data!$D$2:$D$1348,E23,SDM_Data!$E$2:$E$1348,G23,SDM_Data!$I$2:$I$1348,$O$2) -> 154.62741 | N23: =IF(M23>L23,"X","O") -> O | O23: - | Q23: =IF(N23="X","¡","")
C24: Loss | D24: =D22+1 -> 18 | E24: Quality loss | F24: 1/M | G24: MB | H24: 70.1 | I24: =SUMIFS(SDM_Data!$J$2:$J$1348,SDM_Data!$B$2:$B$1348,C24,SDM_Data!$D$2:$D$1348,E24,SDM_Data!$E$2:$E$1348,G24,SDM_Data!$I$2:$I$1348,$O$2) -> 4.48 | J24: =SUMIFS(SDM_Data!$K$2:$K$1348,SDM_Data!$B$2:$B$1348,C24,SDM_Data!$D$2:$D$1348,E24,SDM_Data!$E$2:$E$1348,G24,SDM_Data!$I$2:$I$1348,$O$2) -> 14.69 | K24: =IF(J24>I24,"X","O") -> X | L24: =SUMIFS(SDM_Data!$L$2:$L$1348,SDM_Data!$B$2:$B$1348,C24,SDM_Data!$D$2:$D$1348,E24,SDM_Data!$E$2:$E$1348,G24,SDM_Data!$I$2:$I$1348,$O$2) -> 65.97 | M24: =SUMIFS(SDM_Data!$M$2:$M$1348,SDM_Data!$B$2:$B$1348,C24,SDM_Data!$D$2:$D$1348,E24,SDM_Data!$E$2:$E$1348,G24,SDM_Data!$I$2:$I$1348,$O$2) -> 118.01 | N24: =IF(M24>L24,"X","O") -> X | O24: - | P24: =IF(K24="X","l","") -> l | Q24: =IF(N24="X","¡","") -> ¡ | R24: s | Y24: =IF(N24="O",1,0) -> 0 | Z24: =IF(K24="O",1,0) -> 0
B25: 3. Delivery | C25: Long BM >3 hr | D25: =D24+1 -> 19 | E25: Priority shipment line > 3hr | F25: 1/M | G25: Case | H25: 180 | I25: =SUMIFS(SDM_Data!$J$2:$J$1348,SDM_Data!$B$2:$B$1348,C25,SDM_Data!$D$2:$D$1348,E25,SDM_Data!$E$2:$E$1348,G25,SDM_Data!$I$2:$I$1348,$O$2) -> 26 | J25: =SUMIFS(SDM_Data!$K$2:$K$1348,SDM_Data!$B$2:$B$1348,C25,SDM_Data!$D$2:$D$1348,E25,SDM_Data!$E$2:$E$1348,G25,SDM_Data!$I$2:$I$1348,$O$2) -> 15 | K25: =IF(J25>I25,"X","O") -> O | L25: =SUMIFS(SDM_Data!$L$2:$L$1348,SDM_Data!$B$2:$B$1348,C25,SDM_Data!$D$2:$D$1348,E25,SDM_Data!$E$2:$E$1348,G25,SDM_Data!$I$2:$I$1348,$O$2) -> 296 | M25: =SUMIFS(SDM_Data!$M$2:$M$1348,SDM_Data!$B$2:$B$1348,C25,SDM_Data!$D$2:$D$1348,E25,SDM_Data!$E$2:$E$1348,G25,SDM_Data!$I$2:$I$1348,$O$2) -> 130 | N25: =IF(M25>L25,"X","O") -> O | O25: - | P25: =IF(K25="X","l","") | Q25: =IF(N25="X","¡","") | Y25: =IF(N25="O",1,0) -> 1 | Z25: =IF(K25="O",1,0) -> 1
C26: Unplanned holiday working | D26: 20 | E26: OT unplanned recovery from m/c BM | F26: 1/M | G26: Day | H26: 0 | I26: =SUMIFS(SDM_Data!$J$2:$J$1348,SDM_Data!$B$2:$B$1348,C26,SDM_Data!$D$2:$D$1348,E26,SDM_Data!$E$2:$E$1348,G26,SDM_Data!$I$2:$I$1348,$O$2) -> 0 | J26: =SUMIFS(SDM_Data!$K$2:$K$1348,SDM_Data!$B$2:$B$1348,C26,SDM_Data!$D$2:$D$1348,E26,SDM_Data!$E$2:$E$1348,G26,SDM_Data!$I$2:$I$1348,$O$2) -> 6 | K26: =IF(J26>I26,"X","O") -> X | L26: - | M26: - | N26: - | O26: - | P26: =IF(K26="X","l","") -> l | Q26: =IF(N26="X","¡","") | Y26: =IF(N27="O",1,0) -> 1 | Z26: =IF(K27="O",1,0) -> 1
C27: On plan delivery | D27: =D26+1 -> 21 | E27: - | F27: 1/M | G27: % | H27: 1 | I27: =SUMIFS(SDM_Data!$J$2:$J$1348,SDM_Data!$B$2:$B$1348,C27,SDM_Data!$D$2:$D$1348,E27,SDM_Data!$E$2:$E$1348,G27,SDM_Data!$I$2:$I$1348,$O$2) -> 1 | J27: =SUMIFS(SDM_Data!$K$2:$K$1348,SDM_Data!$B$2:$B$1348,C27,SDM_Data!$D$2:$D$1348,E27,SDM_Data!$E$2:$E$1348,G27,SDM_Data!$I$2:$I$1348,$O$2) -> 1 | K27: =IF(J27>I27,"X","O") -> O | L27: =SUMIFS(SDM_Data!$L$2:$L$1348,SDM_Data!$B$2:$B$1348,C27,SDM_Data!$D$2:$D$1348,E27,SDM_Data!$E$2:$E$1348,G27,SDM_Data!$I$2:$I$1348,$O$2) -> 1 | M27: =SUMIFS(SDM_Data!$M$2:$M$1348,SDM_Data!$B$2:$B$1348,C27,SDM_Data!$D$2:$D$1348,E27,SDM_Data!$E$2:$E$1348,G27,SDM_Data!$I$2:$I$1348,$O$2) -> 1 | N27: =IF(M27>L27,"X","O") -> O | O27: - | P27: =IF(K27="X","l","") | Q27: =IF(N27="X","¡","") | Y27: =IF(N28="O",1,0) -> 1 | Z27: =IF(K28="O",1,0) -> 1
C28: Nearmiss deliviery delay > 30 mins | D28: =D27+1 -> 22 | E28: - | F28: 1/M | G28: Case | H28: 0 | I28: =SUMIFS(SDM_Data!$J$2:$J$1348,SDM_Data!$B$2:$B$1348,C28,SDM_Data!$D$2:$D$1348,E28,SDM_Data!$E$2:$E$1348,G28,SDM_Data!$I$2:$I$1348,$O$2) -> 0 | J28: =SUMIFS(SDM_Data!$K$2:$K$1348,SDM_Data!$B$2:$B$1348,C28,SDM_Data!$D$2:$D$1348,E28,SDM_Data!$E$2:$E$1348,G28,SDM_Data!$I$2:$I$1348,$O$2) -> 0 | K28: =IF(J28>I28,"X","O") -> O | L28: =SUMIFS(SDM_Data!$L$2:$L$1348,SDM_Data!$B$2:$B$1348,C28,SDM_Data!$D$2:$D$1348,E28,SDM_Data!$E$2:$E$1348,G28,SDM_Data!$I$2:$I$1348,$O$2) -> 0 | M28: =SUMIFS(SDM_Data!$M$2:$M$1348,SDM_Data!$B$2:$B$1348,C28,SDM_Data!$D$2:$D$1348,E28,SDM_Data!$E$2:$E$1348,G28,SDM_Data!$I$2:$I$1348,$O$2) -> 0 | N28: =IF(M28>L28,"X","O") -> O | O28: - | P28: =IF(K28="X","l","") | Q28: =IF(N28="X","¡","") | Y28: =IF(N29="O",1,0) -> 1 | Z28: =IF(K29="O",1,0) -> 1
C29: Premium/Unplanned freight | D29: =D28+1 -> 23 | E29: - | F29: 1/M | G29: MB | H29: 7.65 | I29: =SUMIFS(SDM_Data!$J$2:$J$1348,SDM_Data!$B$2:$B$1348,C29,SDM_Data!$D$2:$D$1348,E29,SDM_Data!$E$2:$E$1348,G29,SDM_Data!$I$2:$I$1348,$O$2) -> 0.6375 | J29: =SUMIFS(SDM_Data!$K$2:$K$1348,SDM_Data!$B$2:$B$1348,C29,SDM_Data!$D$2:$D$1348,E29,SDM_Data!$E$2:$E$1348,G29,SDM_Data!$I$2:$I$1348,$O$2) -> 0.05 | K29: =IF(J29>I29,"X","O") -> O | L29: =SUMIFS(SDM_Data!$L$2:$L$1348,SDM_Data!$B$2:$B$1348,C29,SDM_Data!$D$2:$D$1348,E29,SDM_Data!$E$2:$E$1348,G29,SDM_Data!$I$2:$I$1348,$O$2) -> 7.015 | M29: =SUMIFS(SDM_Data!$M$2:$M$1348,SDM_Data!$B$2:$B$1348,C29,SDM_Data!$D$2:$D$1348,E29,SDM_Data!$E$2:$E$1348,G29,SDM_Data!$I$2:$I$1348,$O$2) -> 2.59 | N29: =IF(M29>L29,"X","O") -> O | O29: - | P29: =IF(K29="X","l","") | Q29: =IF(N29="X","¡","") | Y29: =IF(N30="O",1,0) -> 0 | Z29: =IF(K30="O",1,0) -> 1
B30: 4. Compliance | C30: Business compliance | D30: =D29+1 -> 24 | E30: Accident | F30: 1/M | G30: Case | H30: 0 | I30: =SUMIFS(SDM_Data!$J$2:$J$1348,SDM_Data!$B$2:$B$1348,C30,SDM_Data!$D$2:$D$1348,E30,SDM_Data!$E$2:$E$1348,G30,SDM_Data!$I$2:$I$1348,$O$2) -> 0 | J30: =SUMIFS(SDM_Data!$K$2:$K$1348,SDM_Data!$B$2:$B$1348,C30,SDM_Data!$D$2:$D$1348,E30,SDM_Data!$E$2:$E$1348,G30,SDM_Data!$I$2:$I$1348,$O$2) -> 0 | K30: =IF(J30>I30,"X","O") -> O | L30: =SUMIFS(SDM_Data!$L$2:$L$1348,SDM_Data!$B$2:$B$1348,C30,SDM_Data!$D$2:$D$1348,E30,SDM_Data!$E$2:$E$1348,G30,SDM_Data!$I$2:$I$1348,$O$2) -> 0 | M30: =SUMIFS(SDM_Data!$M$2:$M$1348,SDM_Data!$B$2:$B$1348,C30,SDM_Data!$D$2:$D$1348,E30,SDM_Data!$E$2:$E$1348,G30,SDM_Data!$I$2:$I$1348,$O$2) -> 5 | N30: =IF(M30>L30,"X","O") -> X | O30: - | P30: =IF(K30="X","l","") | Q30: =IF(N30="X","¡","") -> ¡ | Y30: =IF(N31="O",1,0) -> 0 | Z30: =IF(K31="O",1,0) -> 1
C31: Business compliance | D31: =D30+1 -> 25 | E31: Nearmiss | F31: 1/M | G31: Case | H31: 0 | I31: =SUMIFS(SDM_Data!$J$2:$J$1348,SDM_Data!$B$2:$B$1348,C31,SDM_Data!$D$2:$D$1348,E31,SDM_Data!$E$2:$E$1348,G31,SDM_Data!$I$2:$I$1348,$O$2) -> 0.75 | J31: =SUMIFS(SDM_Data!$K$2:$K$1348,SDM_Data!$B$2:$B$1348,C31,SDM_Data!$D$2:$D$1348,E31,SDM_Data!$E$2:$E$1348,G31,SDM_Data!$I$2:$I$1348,$O$2) -> 0 | K31: =IF(J31>I31,"X","O") -> O | L31: =SUMIFS(SDM_Data!$L$2:$L$1348,SDM_Data!$B$2:$B$1348,C31,SDM_Data!$D$2:$D$1348,E31,SDM_Data!$E$2:$E$1348,G31,SDM_Data!$I$2:$I$1348,$O$2) -> 0 | M31: =SUMIFS(SDM_Data!$M$2:$M$1348,SDM_Data!$B$2:$B$1348,C31,SDM_Data!$D$2:$D$1348,E31,SDM_Data!$E$2:$E$1348,G31,SDM_Data!$I$2:$I$1348,$O$2) -> 3 | N31: =IF(M31>L31,"X","O") -> X | O31: - | P31: =IF(K31="X","l","") | Q31: =IF(N31="X","¡","") -> ¡ | Y31: =IF(N32="O",1,0) -> 0 | Z31: =IF(K32="O",1,0) -> 1
C32: Business compliance | D32: =D31+1 -> 26 | E32: Incident | F32: 1/M | G32: Case | H32: 0 | I32: =SUMIFS(SDM_Data!$J$2:$J$1348,SDM_Data!$B$2:$B$1348,C32,SDM_Data!$D$2:$D$1348,E32,SDM_Data!$E$2:$E$1348,G32,SDM_Data!$I$2:$I$1348,$O$2) -> 0 | J32: =SUMIFS(SDM_Data!$K$2:$K$1348,SDM_Data!$B$2:$B$1348,C32,SDM_Data!$D$2:$D$1348,E32,SDM_Data!$E$2:$E$1348,G32,SDM_Data!$I$2:$I$1348,$O$2) -> 0 | K32: =IF(J32>I32,"X","O") -> O | L32: =SUMIFS(SDM_Data!$L$2:$L$1348,SDM_Data!$B$2:$B$1348,C32,SDM_Data!$D$2:$D$1348,E32,SDM_Data!$E$2:$E$1348,G32,SDM_Data!$I$2:$I$1348,$O$2) -> 0 | M32: =SUMIFS(SDM_Data!$M$2:$M$1348,SDM_Data!$B$2:$B$1348,C32,SDM_Data!$D$2:$D$1348,E32,SDM_Data!$E$2:$E$1348,G32,SDM_Data!$I$2:$I$1348,$O$2) -> 1 | N32: =IF(M32>L32,"X","O") -> X | O32: - | P32: =IF(K32="X","l","") | Q32: =IF(N32="X","¡","") -> ¡ | R32: c | S32: Result of Nov'25 | Y32: =IF(N33="O",1,0) -> 1 | Z32: =IF(K33="O",1,0) -> 1
C33: Business compliance | D33: =D32+1 -> 27 | E33: Urgent purchasing | F33: 1/M | G33: Case | H33: 281 | I33: =SUMIFS(SDM_Data!$J$2:$J$1348,SDM_Data!$B$2:$B$1348,C33,SDM_Data!$D$2:$D$1348,E33,SDM_Data!$E$2:$E$1348,G33,SDM_Data!$I$2:$I$1348,$O$2) -> 18 | J33: =SUMIFS(SDM_Data!$K$2:$K$1348,SDM_Data!$B$2:$B$1348,C33,SDM_Data!$D$2:$D$1348,E33,SDM_Data!$E$2:$E$1348,G33,SDM_Data!$I$2:$I$1348,$O$2) -> 6 | K33: =IF(J33>I33,"X","O") -> O | L33: =SUMIFS(SDM_Data!$L$2:$L$1348,SDM_Data!$B$2:$B$1348,C33,SDM_Data!$D$2:$D$1348,E33,SDM_Data!$E$2:$E$1348,G33,SDM_Data!$I$2:$I$1348,$O$2) -> 233 | M33: =SUMIFS(SDM_Data!$M$2:$M$1348,SDM_Data!$B$2:$B$1348,C33,SDM_Data!$D$2:$D$1348,E33,SDM_Data!$E$2:$E$1348,G33,SDM_Data!$I$2:$I$1348,$O$2) -> 197 | N33: =IF(M33>L33,"X","O") -> O | O33: - | P33: =IF(K33="X","l","") | Q33: =IF(N33="X","¡","")
C34: Business compliance | E34: Urgent purchasing | F34: 1/M | G34: MB | H34: 117 | I34: =SUMIFS(SDM_Data!$J$2:$J$1348,SDM_Data!$B$2:$B$1348,C34,SDM_Data!$D$2:$D$1348,E34,SDM_Data!$E$2:$E$1348,G34,SDM_Data!$I$2:$I$1348,$O$2) -> 3.95 | J34: =SUMIFS(SDM_Data!$K$2:$K$1348,SDM_Data!$B$2:$B$1348,C34,SDM_Data!$D$2:$D$1348,E34,SDM_Data!$E$2:$E$1348,G34,SDM_Data!$I$2:$I$1348,$O$2) -> 1.327 | K34: =IF(J34>I34,"X","O") -> O | L34: =SUMIFS(SDM_Data!$L$2:$L$1348,SDM_Data!$B$2:$B$1348,C34,SDM_Data!$D$2:$D$1348,E34,SDM_Data!$E$2:$E$1348,G34,SDM_Data!$I$2:$I$1348,$O$2) -> 92.109 | M34: =SUMIFS(SDM_Data!$M$2:$M$1348,SDM_Data!$B$2:$B$1348,C34,SDM_Data!$D$2:$D$1348,E34,SDM_Data!$E$2:$E$1348,G34,SDM_Data!$I$2:$I$1348,$O$2) -> 58.618 | N34: =IF(M34>L34,"X","O") -> O | O34: - | P34: =IF(K34="X","l","") | Q34: =IF(N34="X","¡","") | Y34: =IF(N35="O",1,0) -> 1 | Z34: =IF(K35="O",1,0) -> 0
C35: Business compliance | D35: =D33+1 -> 28 | E35: Urgent purchasing clear within3 Month | F35: 1/M | G35: Case | H35: 0 | I35: - | J35: - | K35: - | L35: =SUMIFS(SDM_Data!$L$2:$L$1348,SDM_Data!$B$2:$B$1348,C35,SDM_Data!$D$2:$D$1348,E35,SDM_Data!$E$2:$E$1348,G35,SDM_Data!$I$2:$I$1348,$O$2) -> 0 | M35: =SUMIFS(SDM_Data!$M$2:$M$1348,SDM_Data!$B$2:$B$1348,C35,SDM_Data!$D$2:$D$1348,E35,SDM_Data!$E$2:$E$1348,G35,SDM_Data!$I$2:$I$1348,$O$2) -> 0 | N35: =IF(M35>L35,"X","O") -> O | O35: - | P35: =IF(K35="X","l","") | Q35: =IF(N35="X","l","")
C36: Business compliance | E36: Urgent purchasing clear within3 Month | F36: 1/M | G36: MB | H36: 0 | I36: - | J36: - | K36: - | L36: =SUMIFS(SDM_Data!$L$2:$L$1348,SDM_Data!$B$2:$B$1348,C36,SDM_Data!$D$2:$D$1348,E36,SDM_Data!$E$2:$E$1348,G36,SDM_Data!$I$2:$I$1348,$O$2) -> 0 | M36: =SUMIFS(SDM_Data!$M$2:$M$1348,SDM_Data!$B$2:$B$1348,C36,SDM_Data!$D$2:$D$1348,E36,SDM_Data!$E$2:$E$1348,G36,SDM_Data!$I$2:$I$1348,$O$2) -> 0 | N36: =IF(M36>L36,"X","O") -> O | O36: - | P36: =IF(K36="X","l","") | Q36: =IF(N36="X","¡","") | Y36: =IF(N37="O",1,0) -> 1 | Z36: =IF(K37="O",1,0) -> 1
C37: Business compliance | D37: =D35+1 -> 29 | E37: Special purchasing | F37: 1/M | G37: Case | H37: 194 | I37: =SUMIFS(SDM_Data!$J$2:$J$1348,SDM_Data!$B$2:$B$1348,C37,SDM_Data!$D$2:$D$1348,E37,SDM_Data!$E$2:$E$1348,G37,SDM_Data!$I$2:$I$1348,$O$2) -> 8 | J37: =SUMIFS(SDM_Data!$K$2:$K$1348,SDM_Data!$B$2:$B$1348,C37,SDM_Data!$D$2:$D$1348,E37,SDM_Data!$E$2:$E$1348,G37,SDM_Data!$I$2:$I$1348,$O$2) -> 8 | K37: =IF(J37>I37,"X","O") -> O | L37: =SUMIFS(SDM_Data!$L$2:$L$1348,SDM_Data!$B$2:$B$1348,C37,SDM_Data!$D$2:$D$1348,E37,SDM_Data!$E$2:$E$1348,G37,SDM_Data!$I$2:$I$1348,$O$2) -> 172 | M37: =SUMIFS(SDM_Data!$M$2:$M$1348,SDM_Data!$B$2:$B$1348,C37,SDM_Data!$D$2:$D$1348,E37,SDM_Data!$E$2:$E$1348,G37,SDM_Data!$I$2:$I$1348,$O$2) -> 72 | N37: =IF(M37>L37,"X","O") -> O | O37: - | P37: =IF(K37="X","l","") | Q37: =IF(N37="X","¡","")
C38: Business compliance | E38: Special purchasing | F38: 1/M | G38: MB | H38: 313.1 | I38: =SUMIFS(SDM_Data!$J$2:$J$1348,SDM_Data!$B$2:$B$1348,C38,SDM_Data!$D$2:$D$1348,E38,SDM_Data!$E$2:$E$1348,G38,SDM_Data!$I$2:$I$1348,$O$2) -> 8.274 | J38: =SUMIFS(SDM_Data!$K$2:$K$1348,SDM_Data!$B$2:$B$1348,C38,SDM_Data!$D$2:$D$1348,E38,SDM_Data!$E$2:$E$1348,G38,SDM_Data!$I$2:$I$1348,$O$2) -> 7.262 | K38: =IF(J38>I38,"X","O") -> O | L38: =SUMIFS(SDM_Data!$L$2:$L$1348,SDM_Data!$B$2:$B$1348,C38,SDM_Data!$D$2:$D$1348,E38,SDM_Data!$E$2:$E$1348,G38,SDM_Data!$I$2:$I$1348,$O$2) -> 281.261 | M38: =SUMIFS(SDM_Data!$M$2:$M$1348,SDM_Data!$B$2:$B$1348,C38,SDM_Data!$D$2:$D$1348,E38,SDM_Data!$E$2:$E$1348,G38,SDM_Data!$I$2:$I$1348,$O$2) -> 69.426 | N38: =IF(M38>L38,"X","O") -> O | O38: - | P38: =IF(K38="X","l","") | Q38: =IF(N38="X","¡","") | Y38: =IF(N39="O",1,0) -> 1 | Z38: =IF(K39="O",1,0) -> 1
C39: Information security | D39: =D37+1 -> 30 | E39: Critical/Incident | F39: 1/M | G39: Case | H39: 0 | I39: =SUMIFS(SDM_Data!$J$2:$J$1348,SDM_Data!$B$2:$B$1348,C39,SDM_Data!$D$2:$D$1348,E39,SDM_Data!$E$2:$E$1348,G39,SDM_Data!$I$2:$I$1348,$O$2) -> 0 | J39: =SUMIFS(SDM_Data!$K$2:$K$1348,SDM_Data!$B$2:$B$1348,C39,SDM_Data!$D$2:$D$1348,E39,SDM_Data!$E$2:$E$1348,G39,SDM_Data!$I$2:$I$1348,$O$2) -> 0 | K39: =IF(J39>I39,"X","O") -> O | L39: =SUMIFS(SDM_Data!$L$2:$L$1348,SDM_Data!$B$2:$B$1348,C39,SDM_Data!$D$2:$D$1348,E39,SDM_Data!$E$2:$E$1348,G39,SDM_Data!$I$2:$I$1348,$O$2) -> 0 | M39: =SUMIFS(SDM_Data!$M$2:$M$1348,SDM_Data!$B$2:$B$1348,C39,SDM_Data!$D$2:$D$1348,E39,SDM_Data!$E$2:$E$1348,G39,SDM_Data!$I$2:$I$1348,$O$2) -> 0 | N39: =IF(M39>L39,"X","O") -> O | O39: - | P39: =IF(K39="X","l","") | Q39: =IF(N39="X","¡","") | Y39: =IF(N40="O",1,0) -> 1 | Z39: =IF(K40="O",1,0) -> 1
C40: Information security | D40: =D39+1 -> 31 | E40: Lead to incident | F40: 1/M | G40: Case | H40: 0 | I40: =SUMIFS(SDM_Data!$J$2:$J$1348,SDM_Data!$B$2:$B$1348,C40,SDM_Data!$D$2:$D$1348,E40,SDM_Data!$E$2:$E$1348,G40,SDM_Data!$I$2:$I$1348,$O$2) -> 0 | J40: =SUMIFS(SDM_Data!$K$2:$K$1348,SDM_Data!$B$2:$B$1348,C40,SDM_Data!$D$2:$D$1348,E40,SDM_Data!$E$2:$E$1348,G40,SDM_Data!$I$2:$I$1348,$O$2) -> 0 | K40: =IF(J40>I40,"X","O") -> O | L40: =SUMIFS(SDM_Data!$L$2:$L$1348,SDM_Data!$B$2:$B$1348,C40,SDM_Data!$D$2:$D$1348,E40,SDM_Data!$E$2:$E$1348,G40,SDM_Data!$I$2:$I$1348,$O$2) -> 0 | M40: =SUMIFS(SDM_Data!$M$2:$M$1348,SDM_Data!$B$2:$B$1348,C40,SDM_Data!$D$2:$D$1348,E40,SDM_Data!$E$2:$E$1348,G40,SDM_Data!$I$2:$I$1348,$O$2) -> 0 | N40: =IF(M40>L40,"X","O") -> O | O40: - | P40: =IF(K40="X","l","") | Q40: =IF(N40="X","¡","") | Y40: =IF(N41="O",1,0) -> 0 | Z40: =IF(K41="O",1,0) -> 1
C41: Information security | D41: =D40+1 -> 32 | E41: Nearmiss | F41: 1/M | G41: Case | H41: 0 | I41: =SUMIFS(SDM_Data!$J$2:$J$1348,SDM_Data!$B$2:$B$1348,C41,SDM_Data!$D$2:$D$1348,E41,SDM_Data!$E$2:$E$1348,G41,SDM_Data!$I$2:$I$1348,$O$2) -> 0 | J41: =SUMIFS(SDM_Data!$K$2:$K$1348,SDM_Data!$B$2:$B$1348,C41,SDM_Data!$D$2:$D$1348,E41,SDM_Data!$E$2:$E$1348,G41,SDM_Data!$I$2:$I$1348,$O$2) -> 0 | K41: =IF(J41>I41,"X","O") -> O | L41: =SUMIFS(SDM_Data!$L$2:$L$1348,SDM_Data!$B$2:$B$1348,C41,SDM_Data!$D$2:$D$1348,E41,SDM_Data!$E$2:$E$1348,G41,SDM_Data!$I$2:$I$1348,$O$2) -> 0 | M41: =SUMIFS(SDM_Data!$M$2:$M$1348,SDM_Data!$B$2:$B$1348,C41,SDM_Data!$D$2:$D$1348,E41,SDM_Data!$E$2:$E$1348,G41,SDM_Data!$I$2:$I$1348,$O$2) -> 5 | N41: =IF(M41>L41,"X","O") -> X | O41: - | P41: =IF(K41="X","l","") | Q41: =IF(N41="X","¡","") -> ¡ | R41: c | Y41: =IF(N42="O",1,0) -> 1 | Z41: =IF(K42="O",1,0) -> 1
C42: Information security | D42: =D41+1 -> 33 | E42: E-mail traing result | F42: 1/3M | G42: Case | H42: 5 | I42: =SUMIFS(SDM_Data!$J$2:$J$1348,SDM_Data!$B$2:$B$1348,C42,SDM_Data!$D$2:$D$1348,E42,SDM_Data!$E$2:$E$1348,G42,SDM_Data!$I$2:$I$1348,$O$2) -> 0 | J42: =SUMIFS(SDM_Data!$K$2:$K$1348,SDM_Data!$B$2:$B$1348,C42,SDM_Data!$D$2:$D$1348,E42,SDM_Data!$E$2:$E$1348,G42,SDM_Data!$I$2:$I$1348,$O$2) -> 0 | K42: =IF(J42>I42,"X","O") -> O | L42: =SUMIFS(SDM_Data!$L$2:$L$1348,SDM_Data!$B$2:$B$1348,C42,SDM_Data!$D$2:$D$1348,E42,SDM_Data!$E$2:$E$1348,G42,SDM_Data!$I$2:$I$1348,$O$2) -> 3 | M42: =SUMIFS(SDM_Data!$M$2:$M$1348,SDM_Data!$B$2:$B$1348,C42,SDM_Data!$D$2:$D$1348,E42,SDM_Data!$E$2:$E$1348,G42,SDM_Data!$I$2:$I$1348,$O$2) -> 3 | N42: =IF(M42>L42,"X","O") -> O | O42: - | P42: =IF(K42="X","l","") | Q42: =IF(N42="X","¡","") | Y42: =IF(N43="O",1,0) -> 1 | Z42: =IF(K43="O",1,0) -> 1
C43: Human compliance | D43: =D42+1 -> 34 | E43: Accident | F43: 1/M | G43: Case | H43: 0 | I43: =SUMIFS(SDM_Data!$J$2:$J$1348,SDM_Data!$B$2:$B$1348,C43,SDM_Data!$D$2:$D$1348,E43,SDM_Data!$E$2:$E$1348,G43,SDM_Data!$I$2:$I$1348,$O$2) -> 0 | J43: =SUMIFS(SDM_Data!$K$2:$K$1348,SDM_Data!$B$2:$B$1348,C43,SDM_Data!$D$2:$D$1348,E43,SDM_Data!$E$2:$E$1348,G43,SDM_Data!$I$2:$I$1348,$O$2) -> 0 | K43: =IF(J43>I43,"X","O") -> O | L43: =SUMIFS(SDM_Data!$L$2:$L$1348,SDM_Data!$B$2:$B$1348,C43,SDM_Data!$D$2:$D$1348,E43,SDM_Data!$E$2:$E$1348,G43,SDM_Data!$I$2:$I$1348,$O$2) -> 0 | M43: =SUMIFS(SDM_Data!$M$2:$M$1348,SDM_Data!$B$2:$B$1348,C43,SDM_Data!$D$2:$D$1348,E43,SDM_Data!$E$2:$E$1348,G43,SDM_Data!$I$2:$I$1348,$O$2) -> 0 | N43: =IF(M43>L43,"X","O") -> O | O43: - | P43: =IF(K43="X","l","") | Q43: =IF(N43="X","¡","") | Y43: =IF(N44="O",1,0) -> 0 | Z43: =IF(K44="O",1,0) -> 1
C44: Human compliance | D44: =D43+1 -> 35 | E44: Nearmiss | F44: 1/M | G44: Case | H44: 0 | I44: =SUMIFS(SDM_Data!$J$2:$J$1348,SDM_Data!$B$2:$B$1348,C44,SDM_Data!$D$2:$D$1348,E44,SDM_Data!$E$2:$E$1348,G44,SDM_Data!$I$2:$I$1348,$O$2) -> 2.5 | J44: =SUMIFS(SDM_Data!$K$2:$K$1348,SDM_Data!$B$2:$B$1348,C44,SDM_Data!$D$2:$D$1348,E44,SDM_Data!$E$2:$E$1348,G44,SDM_Data!$I$2:$I$1348,$O$2) -> 1 | K44: =IF(J44>I44,"X","O") -> O | L44: =SUMIFS(SDM_Data!$L$2:$L$1348,SDM_Data!$B$2:$B$1348,C44,SDM_Data!$D$2:$D$1348,E44,SDM_Data!$E$2:$E$1348,G44,SDM_Data!$I$2:$I$1348,$O$2) -> 25 | M44: =SUMIFS(SDM_Data!$M$2:$M$1348,SDM_Data!$B$2:$B$1348,C44,SDM_Data!$D$2:$D$1348,E44,SDM_Data!$E$2:$E$1348,G44,SDM_Data!$I$2:$I$1348,$O$2) -> 28 | N44: =IF(M44>L44,"X","O") -> X | O44: - | P44: =IF(K44="X","l","") | Q44: =IF(N44="X","¡","") -> ¡ | Y44: =IF(N45="O",1,0) -> 0 | Z44: =IF(K45="O",1,0) -> 1
C45: Human compliance | D45: =D44+1 -> 36 | E45: Incident | F45: 1/M | G45: Case | H45: 0 | I45: =SUMIFS(SDM_Data!$J$2:$J$1348,SDM_Data!$B$2:$B$1348,C45,SDM_Data!$D$2:$D$1348,E45,SDM_Data!$E$2:$E$1348,G45,SDM_Data!$I$2:$I$1348,$O$2) -> 0 | J45: =SUMIFS(SDM_Data!$K$2:$K$1348,SDM_Data!$B$2:$B$1348,C45,SDM_Data!$D$2:$D$1348,E45,SDM_Data!$E$2:$E$1348,G45,SDM_Data!$I$2:$I$1348,$O$2) -> 0 | K45: =IF(J45>I45,"X","O") -> O | L45: =SUMIFS(SDM_Data!$L$2:$L$1348,SDM_Data!$B$2:$B$1348,C45,SDM_Data!$D$2:$D$1348,E45,SDM_Data!$E$2:$E$1348,G45,SDM_Data!$I$2:$I$1348,$O$2) -> 0 | M45: =SUMIFS(SDM_Data!$M$2:$M$1348,SDM_Data!$B$2:$B$1348,C45,SDM_Data!$D$2:$D$1348,E45,SDM_Data!$E$2:$E$1348,G45,SDM_Data!$I$2:$I$1348,$O$2) -> 1 | N45: =IF(M45>L45,"X","O") -> X | O45: - | P45: =IF(K45="X","l","") | Q45: =IF(N45="X","¡","") -> ¡ | Y45: =IF(N46="O",1,0) -> 1 | Z45: =IF(K46="O",1,0) -> 1
C46: Asset control | D46: =D45+1 -> 37 | E46: Fixed asset loss | F46: 1/M | G46: Case | H46: 0 | I46: =SUMIFS(SDM_Data!$J$2:$J$1348,SDM_Data!$B$2:$B$1348,C46,SDM_Data!$D$2:$D$1348,E46,SDM_Data!$E$2:$E$1348,G46,SDM_Data!$I$2:$I$1348,$O$2) -> 0 | J46: =SUMIFS(SDM_Data!$K$2:$K$1348,SDM_Data!$B$2:$B$1348,C46,SDM_Data!$D$2:$D$1348,E46,SDM_Data!$E$2:$E$1348,G46,SDM_Data!$I$2:$I$1348,$O$2) -> 0 | K46: =IF(J46>I46,"X","O") -> O | L46: =SUMIFS(SDM_Data!$L$2:$L$1348,SDM_Data!$B$2:$B$1348,C46,SDM_Data!$D$2:$D$1348,E46,SDM_Data!$E$2:$E$1348,G46,SDM_Data!$I$2:$I$1348,$O$2) -> 0 | M46: =SUMIFS(SDM_Data!$M$2:$M$1348,SDM_Data!$B$2:$B$1348,C46,SDM_Data!$D$2:$D$1348,E46,SDM_Data!$E$2:$E$1348,G46,SDM_Data!$I$2:$I$1348,$O$2) -> 0 | N46: =IF(M46>L46,"X","O") -> O | O46: - | P46: =IF(K46="X","l","") | Q46: =IF(N46="X","¡","")
C47: Asset control | E47: Fixed asset loss | F47: 1/M | G47: MB | H47: 0 | I47: =SUMIFS(SDM_Data!$J$2:$J$1348,SDM_Data!$B$2:$B$1348,C47,SDM_Data!$D$2:$D$1348,E47,SDM_Data!$E$2:$E$1348,G47,SDM_Data!$I$2:$I$1348,$O$2) -> 0 | J47: =SUMIFS(SDM_Data!$K$2:$K$1348,SDM_Data!$B$2:$B$1348,C47,SDM_Data!$D$2:$D$1348,E47,SDM_Data!$E$2:$E$1348,G47,SDM_Data!$I$2:$I$1348,$O$2) -> 0 | K47: =IF(J47>I47,"X","O") -> O | L47: =SUMIFS(SDM_Data!$L$2:$L$1348,SDM_Data!$B$2:$B$1348,C47,SDM_Data!$D$2:$D$1348,E47,SDM_Data!$E$2:$E$1348,G47,SDM_Data!$I$2:$I$1348,$O$2) -> 0 | M47: =SUMIFS(SDM_Data!$M$2:$M$1348,SDM_Data!$B$2:$B$1348,C47,SDM_Data!$D$2:$D$1348,E47,SDM_Data!$E$2:$E$1348,G47,SDM_Data!$I$2:$I$1348,$O$2) -> 0 | N47: =IF(M47>L47,"X","O") -> O | O47: - | P47: =IF(K47="X","l","") | Q47: =IF(N47="X","¡","")
C48: Asset control | D48: =D46+1 -> 38 | E48: Idle Fixed Assets | F48: 1/M | G48: Case | H48: - | I48: - | J48: - | K48: - | L48: - | M48: =SUMIFS(SDM_Data!$M$2:$M$1348,SDM_Data!$B$2:$B$1348,C48,SDM_Data!$D$2:$D$1348,E48,SDM_Data!$E$2:$E$1348,G48,SDM_Data!$I$2:$I$1348,$O$2) -> 40 | N48: - | O48: - | P48: =IF(K48="X","l","") | Q48: =IF(N48="X","¡","")
C49: Asset control | E49: Idle Fixed Assets | F49: 1/M | G49: MB | H49: - | I49: - | J49: - | K49: - | L49: - | M49: =SUMIFS(SDM_Data!$M$2:$M$1348,SDM_Data!$B$2:$B$1348,C49,SDM_Data!$D$2:$D$1348,E49,SDM_Data!$E$2:$E$1348,G49,SDM_Data!$I$2:$I$1348,$O$2) -> 11.58 | N49: - | O49: - | P49: =IF(K49="X","l","") | Q49: =IF(N49="X","¡","")
C50: Asset control | D50: =D48+1 -> 39 | E50: CIP (No using date) | F50: 1/M | G50: Case | H50: - | I50: - | J50: - | K50: - | L50: - | M50: =SUMIFS(SDM_Data!$M$2:$M$1348,SDM_Data!$B$2:$B$1348,C50,SDM_Data!$D$2:$D$1348,E50,SDM_Data!$E$2:$E$1348,G50,SDM_Data!$I$2:$I$1348,$O$2) -> 134 | N50: - | O50: - | P50: =IF(K50="X","l","") | Q50: =IF(N50="X","¡","") | S50: CIP (No using date) : PE 76.5 MB. SE 8.78MB PD 4.93 MB. INN 3.03 MB FAC 1.9 MB. MT 1.44 MB. | T50: Report in TMM 31/Mar By ACC/PE GM
C51: Asset control | E51: CIP (No using date) | F51: 1/M | G51: MB | H51: - | I51: - | J51: - | K51: - | L51: - | M51: =SUMIFS(SDM_Data!$M$2:$M$1348,SDM_Data!$B$2:$B$1348,C51,SDM_Data!$D$2:$D$1348,E51,SDM_Data!$E$2:$E$1348,G51,SDM_Data!$I$2:$I$1348,$O$2) -> 97.2 | N51: - | O51: - | P51: =IF(K51="X","l","") | Q51: =IF(N51="X","¡","")
C52: Asset control | D52: =D50+1 -> 40 | E52: CIP (Document not complete) | F52: 1/M | G52: Case | H52: - | I52: - | J52: - | K52: - | L52: - | M52: =SUMIFS(SDM_Data!$M$2:$M$1348,SDM_Data!$B$2:$B$1348,C52,SDM_Data!$D$2:$D$1348,E52,SDM_Data!$E$2:$E$1348,G52,SDM_Data!$I$2:$I$1348,$O$2) -> 188 | N52: - | O52: - | P52: =IF(K52="X","l","") | Q52: =IF(N52="X","¡","") | S52: CIP (Document not complete) PE 86.24MB, FAC 5.29MB, PD 4.49 MB. | T52: Report in TMM 31/Mar By ACC/PE GM
C53: Asset control | E53: CIP (Document not complete) | F53: 1/M | G53: MB | H53: - | I53: - | J53: - | K53: - | L53: - | M53: =SUMIFS(SDM_Data!$M$2:$M$1348,SDM_Data!$B$2:$B$1348,C53,SDM_Data!$D$2:$D$1348,E53,SDM_Data!$E$2:$E$1348,G53,SDM_Data!$I$2:$I$1348,$O$2) -> 96.2 | N53: - | O53: - | P53: =IF(K53="X","l","") | Q53: =IF(N53="X","¡","") | Y53: =IF(N54="O",1,0) -> 1 | Z53: =IF(K54="O",1,0) -> 0
C54: Asset control | D54: =D52+1 -> 41 | E54: CIP > 12 Month | F54: 1/M | G54: Case | H54: - | I54: =SUMIFS(SDM_Data!$J$2:$J$1348,SDM_Data!$B$2:$B$1348,C54,SDM_Data!$D$2:$D$1348,E54,SDM_Data!$E$2:$E$1348,G54,SDM_Data!$I$2:$I$1348,$O$2) -> 19 | J54: =SUMIFS(SDM_Data!$K$2:$K$1348,SDM_Data!$B$2:$B$1348,C54,SDM_Data!$D$2:$D$1348,E54,SDM_Data!$E$2:$E$1348,G54,SDM_Data!$I$2:$I$1348,$O$2) -> 4 | K54: =IF(J54>I54,"O","x") -> x | L54: =SUMIFS(SDM_Data!$L$2:$L$1348,SDM_Data!$B$2:$B$1348,C54,SDM_Data!$D$2:$D$1348,E54,SDM_Data!$E$2:$E$1348,G54,SDM_Data!$I$2:$I$1348,$O$2) -> 4 | M54: =SUMIFS(SDM_Data!$M$2:$M$1348,SDM_Data!$B$2:$B$1348,C54,SDM_Data!$D$2:$D$1348,E54,SDM_Data!$E$2:$E$1348,G54,SDM_Data!$I$2:$I$1348,$O$2) -> 3 | N54: =IF(M54>L54,"X","O") -> O | O54: - | Q54: =IF(N54="X","¡","") | S54: =SDM_Data!O857 -> Plan Jan'26 = 4case Complet until Jan'26 = 15 case Complete until Jan'26 = 1 case(plan Mar'26) Remark: Target FY26 = 4case Transfer in Jun'26= 2 case 0.41 MB. Addition transfer in Jun'26 = 2case 6.94 MB.
C55: Asset control | E55: CIP > 12 Month | F55: 1/M | G55: MB | H55: - | I55: =SUMIFS(SDM_Data!$J$2:$J$1348,SDM_Data!$B$2:$B$1348,C55,SDM_Data!$D$2:$D$1348,E55,SDM_Data!$E$2:$E$1348,G55,SDM_Data!$I$2:$I$1348,$O$2) -> 32.53 | J55: =SUMIFS(SDM_Data!$K$2:$K$1348,SDM_Data!$B$2:$B$1348,C55,SDM_Data!$D$2:$D$1348,E55,SDM_Data!$E$2:$E$1348,G55,SDM_Data!$I$2:$I$1348,$O$2) -> 5.7 | K55: =IF(J55>I55,"O","x") -> x | L55: =SUMIFS(SDM_Data!$L$2:$L$1348,SDM_Data!$B$2:$B$1348,C55,SDM_Data!$D$2:$D$1348,E55,SDM_Data!$E$2:$E$1348,G55,SDM_Data!$I$2:$I$1348,$O$2) -> 1.12 | M55: =SUMIFS(SDM_Data!$M$2:$M$1348,SDM_Data!$B$2:$B$1348,C55,SDM_Data!$D$2:$D$1348,E55,SDM_Data!$E$2:$E$1348,G55,SDM_Data!$I$2:$I$1348,$O$2) -> 0.6 | N55: =IF(M55>L55,"X","O") -> O | O55: - | Q55: =IF(N55="X","¡","") | Y55: =IF(N56="O",1,0) -> 1 | Z55: =IF(K56="O",1,0) -> 0
C56: Asset control | D56: =D54+1 -> 42 | E56: CIP > 18 Month | F56: 1/M | G56: Case | H56: - | I56: =SUMIFS(SDM_Data!$J$2:$J$1348,SDM_Data!$B$2:$B$1348,C56,SDM_Data!$D$2:$D$1348,E56,SDM_Data!$E$2:$E$1348,G56,SDM_Data!$I$2:$I$1348,$O$2) -> 1 | J56: =SUMIFS(SDM_Data!$K$2:$K$1348,SDM_Data!$B$2:$B$1348,C56,SDM_Data!$D$2:$D$1348,E56,SDM_Data!$E$2:$E$1348,G56,SDM_Data!$I$2:$I$1348,$O$2) -> 0 | K56: =IF(J56>=I56,"O","x") -> x | L56: =SUMIFS(SDM_Data!$L$2:$L$1348,SDM_Data!$B$2:$B$1348,C56,SDM_Data!$D$2:$D$1348,E56,SDM_Data!$E$2:$E$1348,G56,SDM_Data!$I$2:$I$1348,$O$2) -> 2 | M56: =SUMIFS(SDM_Data!$M$2:$M$1348,SDM_Data!$B$2:$B$1348,C56,SDM_Data!$D$2:$D$1348,E56,SDM_Data!$E$2:$E$1348,G56,SDM_Data!$I$2:$I$1348,$O$2) -> 0 | N56: =IF(M56>L56,"X","O") -> O | O56: - | Q56: =IF(N56="X","¡","") | S56: Completed in Jan'26 = plan 1 case Target FY26 Transfer in May'26= 6case (7.68 MB) Transfer in Apr'26= 1case (0.43 MB)
C57: Asset control | E57: CIP > 18 Month | F57: 1/M | G57: MB | H57: - | I57: =SUMIFS(SDM_Data!$J$2:$J$1348,SDM_Data!$B$2:$B$1348,C57,SDM_Data!$D$2:$D$1348,E57,SDM_Data!$E$2:$E$1348,G57,SDM_Data!$I$2:$I$1348,$O$2) -> 1.35 | J57: =SUMIFS(SDM_Data!$K$2:$K$1348,SDM_Data!$B$2:$B$1348,C57,SDM_Data!$D$2:$D$1348,E57,SDM_Data!$E$2:$E$1348,G57,SDM_Data!$I$2:$I$1348,$O$2) -> 0 | K57: =IF(J57>=I57,"O","x") -> x | L57: =SUMIFS(SDM_Data!$L$2:$L$1348,SDM_Data!$B$2:$B$1348,C57,SDM_Data!$D$2:$D$1348,E57,SDM_Data!$E$2:$E$1348,G57,SDM_Data!$I$2:$I$1348,$O$2) -> 0.33 | M57: =SUMIFS(SDM_Data!$M$2:$M$1348,SDM_Data!$B$2:$B$1348,C57,SDM_Data!$D$2:$D$1348,E57,SDM_Data!$E$2:$E$1348,G57,SDM_Data!$I$2:$I$1348,$O$2) -> 0 | N57: =IF(M57>L57,"X","O") -> O | O57: - | Q57: =IF(N57="X","¡","") | Y57: =IF(N58="O",1,0) -> 0
C58: Asset control | D58: =D56+1 -> 43 | E58: Un-received Order >12 [expense] | F58: 1/M | G58: Case | H58: - | I58: - | J58: - | K58: - | L58: =SUMIFS(SDM_Data!$L$2:$L$1348,SDM_Data!$B$2:$B$1348,C58,SDM_Data!$D$2:$D$1348,E58,SDM_Data!$E$2:$E$1348,G58,SDM_Data!$I$2:$I$1348,$O$2) -> 0 | M58: =SUMIFS(SDM_Data!$M$2:$M$1348,SDM_Data!$B$2:$B$1348,C58,SDM_Data!$D$2:$D$1348,E58,SDM_Data!$E$2:$E$1348,G58,SDM_Data!$I$2:$I$1348,$O$2) -> 137 | N58: =IF(M58>L58,"X","O") -> X | O58: - | P58: =IF(K58="X","l","") | Q58: =IF(N58="X","¡","") -> ¡ | S58: =SDM_Data!O861 -> Expense >12M SDM-MT&FAC : 65 cases / 4.597 MB.:Job Stock Spare part,Oil) SDM-SPD&PD : 30 case / 3.149 Mb.: Job.Kaizen MC. & Cutting Tool SDM-PC : 14 cases / 0.354 MB.:Job Rent for Forklift SDM-Admin : 14 case / 1.057 MB.:Job Repair | T58: Report in TMM 24-Feb Report by Pruek /GM
C59: Asset control | E59: Un-received Order >12 [expense] | F59: 1/M | G59: MB | H59: - | I59: - | J59: - | K59: - | L59: =SUMIFS(SDM_Data!$L$2:$L$1348,SDM_Data!$B$2:$B$1348,C59,SDM_Data!$D$2:$D$1348,E59,SDM_Data!$E$2:$E$1348,G59,SDM_Data!$I$2:$I$1348,$O$2) -> 0 | M59: =SUMIFS(SDM_Data!$M$2:$M$1348,SDM_Data!$B$2:$B$1348,C59,SDM_Data!$D$2:$D$1348,E59,SDM_Data!$E$2:$E$1348,G59,SDM_Data!$I$2:$I$1348,$O$2) -> 12.128 | N59: =IF(M59>L59,"X","O") -> X | O59: - | P59: =IF(K59="X","l","") | Q59: =IF(N59="X","¡","") -> ¡ | T59: Report in TMM 10-Mar By each Dept. | Y59: =IF(N60="O",1,0) -> 0
C60: Asset control | D60: =D58+1 -> 44 | E60: Un-received Order >18 [Investment] | F60: 1/M | G60: Case | H60: - | I60: - | J60: - | K60: - | L60: =SUMIFS(SDM_Data!$L$2:$L$1348,SDM_Data!$B$2:$B$1348,C60,SDM_Data!$D$2:$D$1348,E60,SDM_Data!$E$2:$E$1348,G60,SDM_Data!$I$2:$I$1348,$O$2) -> 0 | M60: =SUMIFS(SDM_Data!$M$2:$M$1348,SDM_Data!$B$2:$B$1348,C60,SDM_Data!$D$2:$D$1348,E60,SDM_Data!$E$2:$E$1348,G60,SDM_Data!$I$2:$I$1348,$O$2) -> 98 | N60: =IF(M60>L60,"X","O") -> X | O60: - | P60: =IF(K60="X","l","") | Q60: =IF(N60="X","¡","") -> ¡ | S60: =SDM_Data!O863 -> Investment >18M SDM-PE : 70 case / 42.549 MB.:Job Modify MC SDM-SPD&PE : 15 case / 7.374 Mb.: Job Kaizen MC.
C61: Asset control | E61: Un-received Order >18 [Investment] | F61: 1/M | G61: MB | H61: - | I61: - | J61: - | K61: - | L61: =SUMIFS(SDM_Data!$L$2:$L$1348,SDM_Data!$B$2:$B$1348,C61,SDM_Data!$D$2:$D$1348,E61,SDM_Data!$E$2:$E$1348,G61,SDM_Data!$I$2:$I$1348,$O$2) -> 0 | M61: =SUMIFS(SDM_Data!$M$2:$M$1348,SDM_Data!$B$2:$B$1348,C61,SDM_Data!$D$2:$D$1348,E61,SDM_Data!$E$2:$E$1348,G61,SDM_Data!$I$2:$I$1348,$O$2) -> 62.738 | N61: =IF(M61>L61,"X","O") -> X | O61: - | P61: =IF(K61="X","l","") | Q61: =IF(N61="X","¡","") -> ¡ | Y61: =IF(N62="O",1,0) -> 0
C62: Asset control | D62: =D60+1 -> 45 | E62: Inventory variance | F62: 1/6M | G62: % | H62: +/-0.5% | I62: - | J62: - | K62: - | L62: =SUMIFS(SDM_Data!$L$2:$L$1348,SDM_Data!$B$2:$B$1348,C62,SDM_Data!$D$2:$D$1348,E62,SDM_Data!$E$2:$E$1348,G62,SDM_Data!$I$2:$I$1348,$O$2) -> -0.005 | M62: =SUMIFS(SDM_Data!$M$2:$M$1348,SDM_Data!$B$2:$B$1348,C62,SDM_Data!$D$2:$D$1348,E62,SDM_Data!$E$2:$E$1348,G62,SDM_Data!$I$2:$I$1348,$O$2) -> -0.00574 | N62: =IF(M62<L62,"X","O") -> X | O62: - | P62: =IF(K62="X","l","") | Q62: =IF(N62="X","¡","") -> ¡ | T62: Result of 1st time (Sep)
C63: Asset control | E63: Inventory variance | F63: 1/6M | G63: MB | H63: - | I63: - | J63: - | K63: - | L63: =SUMIFS(SDM_Data!$L$2:$L$1348,SDM_Data!$B$2:$B$1348,C63,SDM_Data!$D$2:$D$1348,E63,SDM_Data!$E$2:$E$1348,G63,SDM_Data!$I$2:$I$1348,$O$2) -> 0 | M63: =SUMIFS(SDM_Data!$M$2:$M$1348,SDM_Data!$B$2:$B$1348,C63,SDM_Data!$D$2:$D$1348,E63,SDM_Data!$E$2:$E$1348,G63,SDM_Data!$I$2:$I$1348,$O$2) -> -9.2 | N63: - | O63: - | P63: =IF(K63="X","l","") | Q63: =IF(N63="X","¡","") | Y63: =IF(N64="O",1,0) -> 1 | Z63: =IF(K64="O",1,0) -> 1
C64: Asset control | D64: =D62+1 -> 46 | E64: Spare part inventory | F64: 1/M | G64: % | H64: 0.035 | I64: =SUMIFS(SDM_Data!$J$2:$J$1348,SDM_Data!$B$2:$B$1348,C64,SDM_Data!$D$2:$D$1348,E64,SDM_Data!$E$2:$E$1348,G64,SDM_Data!$I$2:$I$1348,$O$2) -> 0.0351 | J64: =SUMIFS(SDM_Data!$K$2:$K$1348,SDM_Data!$B$2:$B$1348,C64,SDM_Data!$D$2:$D$1348,E64,SDM_Data!$E$2:$E$1348,G64,SDM_Data!$I$2:$I$1348,$O$2) -> 0.0305 | K64: =IF(J64>I64,"X","O") -> O | L64: =SUMIFS(SDM_Data!$L$2:$L$1348,SDM_Data!$B$2:$B$1348,C64,SDM_Data!$D$2:$D$1348,E64,SDM_Data!$E$2:$E$1348,G64,SDM_Data!$I$2:$I$1348,$O$2) -> 0.0351 | M64: =SUMIFS(SDM_Data!$M$2:$M$1348,SDM_Data!$B$2:$B$1348,C64,SDM_Data!$D$2:$D$1348,E64,SDM_Data!$E$2:$E$1348,G64,SDM_Data!$I$2:$I$1348,$O$2) -> 0.0305 | N64: =IF(M64>L64,"X","O") -> O | O64: - | P64: =IF(K64="X","l","") | Q64: =IF(N64="X","¡","")
C65: Asset control | E65: Spare part inventory | F65: 1/M | G65: MB | H65: - | I65: =SUMIFS(SDM_Data!$J$2:$J$1348,SDM_Data!$B$2:$B$1348,C65,SDM_Data!$D$2:$D$1348,E65,SDM_Data!$E$2:$E$1348,G65,SDM_Data!$I$2:$I$1348,$O$2) -> 643.91 | J65: =SUMIFS(SDM_Data!$K$2:$K$1348,SDM_Data!$B$2:$B$1348,C65,SDM_Data!$D$2:$D$1348,E65,SDM_Data!$E$2:$E$1348,G65,SDM_Data!$I$2:$I$1348,$O$2) -> 583.28 | K65: =IF(J65>I65,"X","O") -> O | L65: =SUMIFS(SDM_Data!$L$2:$L$1348,SDM_Data!$B$2:$B$1348,C65,SDM_Data!$D$2:$D$1348,E65,SDM_Data!$E$2:$E$1348,G65,SDM_Data!$I$2:$I$1348,$O$2) -> 643.91 | M65: =SUMIFS(SDM_Data!$M$2:$M$1348,SDM_Data!$B$2:$B$1348,C65,SDM_Data!$D$2:$D$1348,E65,SDM_Data!$E$2:$E$1348,G65,SDM_Data!$I$2:$I$1348,$O$2) -> 583.28 | N65: =IF(M65>L65,"X","O") -> O | O65: - | P65: =IF(K65="X","l","") | Q65: =IF(N65="X","¡","")
C66: Asset control | D66: =D64+1 -> 47 | E66: Holding part | F66: 1/M | G66: Case | I66: =SUMIFS(SDM_Data!$J$2:$J$1348,SDM_Data!$B$2:$B$1348,C66,SDM_Data!$D$2:$D$1348,E66,SDM_Data!$E$2:$E$1348,G66,SDM_Data!$I$2:$I$1348,$O$2) -> 0 | J66: =SUMIFS(SDM_Data!$K$2:$K$1348,SDM_Data!$B$2:$B$1348,C66,SDM_Data!$D$2:$D$1348,E66,SDM_Data!$E$2:$E$1348,G66,SDM_Data!$I$2:$I$1348,$O$2) -> 0 | K66: - | L66: =SUMIFS(SDM_Data!$L$2:$L$1348,SDM_Data!$B$2:$B$1348,C66,SDM_Data!$D$2:$D$1348,E66,SDM_Data!$E$2:$E$1348,G66,SDM_Data!$I$2:$I$1348,$O$2) -> 0 | M66: =SUMIFS(SDM_Data!$M$2:$M$1348,SDM_Data!$B$2:$B$1348,C66,SDM_Data!$D$2:$D$1348,E66,SDM_Data!$E$2:$E$1348,G66,SDM_Data!$I$2:$I$1348,$O$2) -> 0 | N66: - | O66: - | P66: =IF(K66="X","l","") | Q66: =IF(N66="X","¡","") | Y66: =IF(N67="O",1,0) -> 0 | Z66: =IF(K67="O",1,0) -> 0
C67: Asset control | E67: Holding part | F67: 1/M | G67: MB | I67: =SUMIFS(SDM_Data!$J$2:$J$1348,SDM_Data!$B$2:$B$1348,C67,SDM_Data!$D$2:$D$1348,E67,SDM_Data!$E$2:$E$1348,G67,SDM_Data!$I$2:$I$1348,$O$2) -> 2.2729146 | J67: =SUMIFS(SDM_Data!$K$2:$K$1348,SDM_Data!$B$2:$B$1348,C67,SDM_Data!$D$2:$D$1348,E67,SDM_Data!$E$2:$E$1348,G67,SDM_Data!$I$2:$I$1348,$O$2) -> 6.5564866 | K67: =IF(J67>I67,"X","O") -> X | L67: =SUMIFS(SDM_Data!$L$2:$L$1348,SDM_Data!$B$2:$B$1348,C67,SDM_Data!$D$2:$D$1348,E67,SDM_Data!$E$2:$E$1348,G67,SDM_Data!$I$2:$I$1348,$O$2) -> 82.305811 | M67: =SUMIFS(SDM_Data!$M$2:$M$1348,SDM_Data!$B$2:$B$1348,C67,SDM_Data!$D$2:$D$1348,E67,SDM_Data!$E$2:$E$1348,G67,SDM_Data!$I$2:$I$1348,$O$2) -> 89.404456 | N67: =IF(M67>L67,"X","O") -> X | O67: - | P67: =IF(K67="X","l","") -> l | Q67: =IF(N67="X","¡","") -> ¡ | S67: Housing porosity, GDP head no plating and Shoe stain. (Continue) | T67: Quality monthly 11-Mar Report by Suphatcha MGR | Y67: =IF(N68="O",1,0) -> 1
C68: Asset control | D68: =D66+1 -> 48 | E68: Slow moving of FG | F68: 1/3M | G68: MB | H68: 3.17 | I68: - | J68: - | K68: - | L68: =SUMIFS(SDM_Data!$L$2:$L$1348,SDM_Data!$B$2:$B$1348,C68,SDM_Data!$D$2:$D$1348,E68,SDM_Data!$E$2:$E$1348,G68,SDM_Data!$I$2:$I$1348,$O$2) -> 3.17 | M68: =SUMIFS(SDM_Data!$M$2:$M$1348,SDM_Data!$B$2:$B$1348,C68,SDM_Data!$D$2:$D$1348,E68,SDM_Data!$E$2:$E$1348,G68,SDM_Data!$I$2:$I$1348,$O$2) -> 0.77 | N68: =IF(M68>L68,"X","O") -> O | O68: - | P68: =IF(K68="X","l","") | Q68: =IF(N68="X","¡","") | Y68: =IF(N69="O",1,0) -> 1
C69: Asset control | D69: =D68+1 -> 49 | E69: Slow moving of Parts&RM | F69: 1/3M | G69: MB | H69: 5.84 | I69: - | J69: - | K69: - | L69: =SUMIFS(SDM_Data!$L$2:$L$1348,SDM_Data!$B$2:$B$1348,C69,SDM_Data!$D$2:$D$1348,E69,SDM_Data!$E$2:$E$1348,G69,SDM_Data!$I$2:$I$1348,$O$2) -> 5.84 | M69: =SUMIFS(SDM_Data!$M$2:$M$1348,SDM_Data!$B$2:$B$1348,C69,SDM_Data!$D$2:$D$1348,E69,SDM_Data!$E$2:$E$1348,G69,SDM_Data!$I$2:$I$1348,$O$2) -> 5.25 | N69: =IF(M69>L69,"X","O") -> O | O69: - | P69: =IF(K69="X","l","") | Q69: =IF(N69="X","¡","") | T69: Result of Dec'25 | Y69: =IF(N70="O",1,0) -> 1
C70: Asset control | D70: =D69+1 -> 50 | E70: Slow moving of Spare Parts | F70: 1/3M | G70: MB | H70: - | I70: - | J70: - | K70: - | L70: =SUMIFS(SDM_Data!$L$2:$L$1348,SDM_Data!$B$2:$B$1348,C70,SDM_Data!$D$2:$D$1348,E70,SDM_Data!$E$2:$E$1348,G70,SDM_Data!$I$2:$I$1348,$O$2) -> 160.61 | M70: =SUMIFS(SDM_Data!$M$2:$M$1348,SDM_Data!$B$2:$B$1348,C70,SDM_Data!$D$2:$D$1348,E70,SDM_Data!$E$2:$E$1348,G70,SDM_Data!$I$2:$I$1348,$O$2) -> 148.7 | N70: =IF(M70>L70,"X","O") -> O | O70: - | P70: =IF(K70="X","l","") | Q70: =IF(N70="X","¡","") | T70: Result of Dec'25
C71: Asset control | D71: =D70+1 -> 51 | E71: Dead stock of FG, PART & RM | F71: 1/Y | G71: MB | H71: 5.4 | I71: - | J71: - | K71: - | L71: - | M71: - | N71: - | O71: - | P71: =IF(K71="X","l","") | Q71: =IF(N71="X","¡","")
C72: Asset control | D72: =D71+1 -> 52 | E72: Dead stock of Spare parts | F72: 1/Y | G72: MB | H72: 3 | I72: - | J72: - | K72: - | L72: - | M72: - | N72: - | O72: - | P72: =IF(K72="X","l","") | Q72: =IF(N72="X","¡","")
C73: Compliance survey score | D73: =D72+1 -> 53 | E73: All topics score < 1.20 points | F73: 1/Y | G73: Socre | H73: 1.2 | I73: - | J73: - | K73: - | L73: =SUMIFS(SDM_Data!$L$2:$L$1348,SDM_Data!$B$2:$B$1348,C73,SDM_Data!$D$2:$D$1348,E73,SDM_Data!$E$2:$E$1348,G73,SDM_Data!$I$2:$I$1348,$O$2) -> 1.2 | M73: =SUMIFS(SDM_Data!$M$2:$M$1348,SDM_Data!$B$2:$B$1348,C73,SDM_Data!$D$2:$D$1348,E73,SDM_Data!$E$2:$E$1348,G73,SDM_Data!$I$2:$I$1348,$O$2) -> 1.46 | N73: =IF(M73>L73,"X","O") -> X | O73: - | P73: =IF(K73="X","l","") | Q73: =IF(N73="X","l","") -> l | T73: Report in TMM /31-Mar Report by Kobsook/GM | Y73: =IF(N74="O",1,0) -> 0
C74: J-SOX audit score | D74: =D73+1 -> 54 | E74: Deficiency | F74: 1/Y | G74: Socre | H74: 5 | I74: - | J74: - | K74: - | L74: =SUMIFS(SDM_Data!$L$2:$L$1348,SDM_Data!$B$2:$B$1348,C74,SDM_Data!$D$2:$D$1348,E74,SDM_Data!$E$2:$E$1348,G74,SDM_Data!$I$2:$I$1348,$O$2) -> 0 | M74: =SUMIFS(SDM_Data!$M$2:$M$1348,SDM_Data!$B$2:$B$1348,C74,SDM_Data!$D$2:$D$1348,E74,SDM_Data!$E$2:$E$1348,G74,SDM_Data!$I$2:$I$1348,$O$2) -> 4.71 | N74: =IF(M74>L74,"X","O") -> X | O74: - | P74: =IF(K74="X","l","") | Q74: =IF(N74="X","¡","") -> ¡ | T74: Result of Sep (J-Sox report) | Y74: =IF(N75="O",1,0) -> 1
C75: Information security audit score | D75: =D74+1 -> 55 | E75: Deficiency | F75: 1/Y | G75: Case | H75: 0 | I75: - | J75: - | K75: - | L75: =SUMIFS(SDM_Data!$L$2:$L$1348,SDM_Data!$B$2:$B$1348,C75,SDM_Data!$D$2:$D$1348,E75,SDM_Data!$E$2:$E$1348,G75,SDM_Data!$I$2:$I$1348,$O$2) -> 0 | M75: =SUMIFS(SDM_Data!$M$2:$M$1348,SDM_Data!$B$2:$B$1348,C75,SDM_Data!$D$2:$D$1348,E75,SDM_Data!$E$2:$E$1348,G75,SDM_Data!$I$2:$I$1348,$O$2) -> 0 | N75: =IF(M75>L75,"X","O") -> O | O75: - | P75: =IF(K75="X","l","") | Q75: =IF(N75="X","¡","")
C76: Voice of employee (Bad News First) | D76: =D75+1 -> 56 | E76: - | F76: 1/M | G76: Case | H76: - | I76: =SUMIFS(SDM_Data!$J$2:$J$1348,SDM_Data!$B$2:$B$1348,C76,SDM_Data!$D$2:$D$1348,E76,SDM_Data!$E$2:$E$1348,G76,SDM_Data!$I$2:$I$1348,$O$2) -> 30 | J76: =SUMIFS(SDM_Data!$K$2:$K$1348,SDM_Data!$B$2:$B$1348,C76,SDM_Data!$D$2:$D$1348,E76,SDM_Data!$E$2:$E$1348,G76,SDM_Data!$I$2:$I$1348,$O$2) -> 25 | K76: - | L76: =SUMIFS(SDM_Data!$L$2:$L$1348,SDM_Data!$B$2:$B$1348,C76,SDM_Data!$D$2:$D$1348,E76,SDM_Data!$E$2:$E$1348,G76,SDM_Data!$I$2:$I$1348,$O$2) -> 271 | M76: =SUMIFS(SDM_Data!$M$2:$M$1348,SDM_Data!$B$2:$B$1348,C76,SDM_Data!$D$2:$D$1348,E76,SDM_Data!$E$2:$E$1348,G76,SDM_Data!$I$2:$I$1348,$O$2) -> 223 | N76: - | O76: - | P76: =IF(K76="X","l","") | Q76: =IF(N76="X","¡","") | Y76: =IF(N77="O",1,0) -> 1
B77: 5. HR | C77: Annual compulsory training | D77: =D76+1 -> 57 | E77: HR training | F77: 1/6M | G77: Curriculum/% | H77: Complete 100% | I77: - | J77: - | K77: - | L77: =SUMIFS(SDM_Data!$L$2:$L$1348,SDM_Data!$B$2:$B$1348,C77,SDM_Data!$D$2:$D$1348,E77,SDM_Data!$E$2:$E$1348,G77,SDM_Data!$I$2:$I$1348,$O$2) -> 1 | M77: =SUMIFS(SDM_Data!$M$2:$M$1348,SDM_Data!$B$2:$B$1348,C77,SDM_Data!$D$2:$D$1348,E77,SDM_Data!$E$2:$E$1348,G77,SDM_Data!$I$2:$I$1348,$O$2) -> 1 | N77: =IF(M77>L77,"X","O") -> O | O77: - | P77: =IF(K77="X","l","") | Q77: =IF(N77="X","¡","") | Y77: =IF(N78="O",1,0) -> 1
C78: Annual compulsory training | D78: =D77+1 -> 58 | E78: Dept. Training | F78: 1/6M | G78: Persons/% | H78: 1 | I78: - | J78: - | K78: - | L78: =SUMIFS(SDM_Data!$L$2:$L$1348,SDM_Data!$B$2:$B$1348,C78,SDM_Data!$D$2:$D$1348,E78,SDM_Data!$E$2:$E$1348,G78,SDM_Data!$I$2:$I$1348,$O$2) -> 1 | M78: =SUMIFS(SDM_Data!$M$2:$M$1348,SDM_Data!$B$2:$B$1348,C78,SDM_Data!$D$2:$D$1348,E78,SDM_Data!$E$2:$E$1348,G78,SDM_Data!$I$2:$I$1348,$O$2) -> 1 | N78: =IF(M78>L78,"X","O") -> O | O78: - | P78: =IF(K78="X","l","") | Q78: =IF(N78="X","¡","") | Y78: =IF(N79="O",1,0) -> 1
C79: Annual compulsory training | D79: =D78+1 -> 59 | E79: Mgmt. Training | F79: 1/Y | G79: Person/ ability level | H79: - Complete project - LIFO rank up | I79: - | J79: - | K79: - | L79: =SUMIFS(SDM_Data!$L$2:$L$1348,SDM_Data!$B$2:$B$1348,C79,SDM_Data!$D$2:$D$1348,E79,SDM_Data!$E$2:$E$1348,G79,SDM_Data!$I$2:$I$1348,$O$2) -> 12 | M79: =SUMIFS(SDM_Data!$M$2:$M$1348,SDM_Data!$B$2:$B$1348,C79,SDM_Data!$D$2:$D$1348,E79,SDM_Data!$E$2:$E$1348,G79,SDM_Data!$I$2:$I$1348,$O$2) -> 12 | N79: =IF(M79>L79,"X","O") -> O | O79: - | P79: =IF(K79="X","l","") | Q79: =IF(N79="X","¡","") | Y79: =IF(N80="O",1,0) -> 1
C80: Annual compulsory training | D80: =D79+1 -> 60 | E80: Pre boarding promotion | F80: 1/Y | G80: system | H80: Complete functional 60% | I80: - | J80: - | K80: - | L80: =SUMIFS(SDM_Data!$L$2:$L$1348,SDM_Data!$B$2:$B$1348,C80,SDM_Data!$D$2:$D$1348,E80,SDM_Data!$E$2:$E$1348,G80,SDM_Data!$I$2:$I$1348,$O$2) -> 0.4 | M80: =SUMIFS(SDM_Data!$M$2:$M$1348,SDM_Data!$B$2:$B$1348,C80,SDM_Data!$D$2:$D$1348,E80,SDM_Data!$E$2:$E$1348,G80,SDM_Data!$I$2:$I$1348,$O$2) -> 0.4 | N80: =IF(M80>L80,"X","O") -> O | O80: - | P80: =IF(K80="X","l","") | Q80: =IF(N80="X","¡","") | Y80: =IF(N81="O",1,0) -> 1
C81: Annual compulsory training | D81: =D80+1 -> 61 | E81: Post boarding promotion | F81: 1/Y | G81: system | H81: Complete functional 60% | I81: - | J81: - | K81: - | L81: =SUMIFS(SDM_Data!$L$2:$L$1348,SDM_Data!$B$2:$B$1348,C81,SDM_Data!$D$2:$D$1348,E81,SDM_Data!$E$2:$E$1348,G81,SDM_Data!$I$2:$I$1348,$O$2) -> 0.4 | M81: =SUMIFS(SDM_Data!$M$2:$M$1348,SDM_Data!$B$2:$B$1348,C81,SDM_Data!$D$2:$D$1348,E81,SDM_Data!$E$2:$E$1348,G81,SDM_Data!$I$2:$I$1348,$O$2) -> 0.4 | N81: =IF(M81>L81,"X","O") -> O | O81: - | P81: =IF(K81="X","l","") | Q81: =IF(N81="X","¡","")
C82: MSS+e score | D82: =D81+1 -> 62 | E82: - | F82: 1/Y | G82: Case | H82: 3.95 | I82: - | J82: - | K82: - | L82: - | M82: - | N82: - | O82: - | P82: =IF(K82="X","l","") | Q82: =IF(N82="X","¡","")
C83: Engagement | D83: =D82+1 -> 63 | E83: - | F83: 1/Y | G83: Case | H83: 3.2 | I83: - | J83: - | K83: - | L83: - | M83: - | N83: - | O83: - | P83: =IF(K83="X","l","") | Q83: =IF(N83="X","¡","") | Y83: =IF(N84="O",1,0) -> 0 | Z83: =IF(K84="O",1,0) -> 0
B84: 6. Attractive | C84: Non-value work reduction | D84: =D83+1 -> 64 | E84: Direct | F84: 1/M | G84: Hrs/Month | H84: 3,500 (33%) | I84: =SUMIFS(SDM_Data!$J$2:$J$1348,SDM_Data!$B$2:$B$1348,C84,SDM_Data!$D$2:$D$1348,E84,SDM_Data!$E$2:$E$1348,G84,SDM_Data!$I$2:$I$1348,$O$2) -> 1122.77 | J84: =SUMIFS(SDM_Data!$K$2:$K$1348,SDM_Data!$B$2:$B$1348,C84,SDM_Data!$D$2:$D$1348,E84,SDM_Data!$E$2:$E$1348,G84,SDM_Data!$I$2:$I$1348,$O$2) -> 401.33 | K84: =IF(J84<I84,"X","O") -> X | L84: =SUMIFS(SDM_Data!$L$2:$L$1348,SDM_Data!$B$2:$B$1348,C84,SDM_Data!$D$2:$D$1348,E84,SDM_Data!$E$2:$E$1348,G84,SDM_Data!$I$2:$I$1348,$O$2) -> 3029.12 | M84: =SUMIFS(SDM_Data!$M$2:$M$1348,SDM_Data!$B$2:$B$1348,C84,SDM_Data!$D$2:$D$1348,E84,SDM_Data!$E$2:$E$1348,G84,SDM_Data!$I$2:$I$1348,$O$2) -> 2308.23 | N84: =IF(M84<L84,"X","O") -> X | O84: - | P84: =IF(K84="X","l","") -> l | Q84: =IF(N84="X","¡","") -> ¡ | Y84: =IF(N85="O",1,0) -> 0 | Z84: =IF(K85="O",1,0) -> 0
C85: Non-value work reduction | E85: Indirect | F85: 1/M | G85: Hrs | H85: 42,350 Hrs.(10%) | I85: =SUMIFS(SDM_Data!$J$2:$J$1348,SDM_Data!$B$2:$B$1348,C85,SDM_Data!$D$2:$D$1348,E85,SDM_Data!$E$2:$E$1348,G85,SDM_Data!$I$2:$I$1348,$O$2) -> 6500 | J85: =SUMIFS(SDM_Data!$K$2:$K$1348,SDM_Data!$B$2:$B$1348,C85,SDM_Data!$D$2:$D$1348,E85,SDM_Data!$E$2:$E$1348,G85,SDM_Data!$I$2:$I$1348,$O$2) -> 6320 | K85: =IF(J85<I85,"X","O") -> X | L85: =SUMIFS(SDM_Data!$L$2:$L$1348,SDM_Data!$B$2:$B$1348,C85,SDM_Data!$D$2:$D$1348,E85,SDM_Data!$E$2:$E$1348,G85,SDM_Data!$I$2:$I$1348,$O$2) -> 35350 | M85: =SUMIFS(SDM_Data!$M$2:$M$1348,SDM_Data!$B$2:$B$1348,C85,SDM_Data!$D$2:$D$1348,E85,SDM_Data!$E$2:$E$1348,G85,SDM_Data!$I$2:$I$1348,$O$2) -> 25282 | N85: =IF(M85<L85,"X","O") -> X | O85: - | P85: =IF(K85="X","l","") -> l | Q85: =IF(N85="X","¡","") -> ¡ | R85: s | S85: Safety DX Project delay from waiting PO approval and workflow analysis MT waiting start GO-Live Periodic system in FY26 (New data) | Y85: =IF(N86="O",1,0) -> 1 | Z85: =IF(K86="O",1,0) -> 1
C86: Projects with Universities | D86: =D84+1 -> 65 | E86: - | F86: 1/6M | G86: Project | H86: 70 | I86: =SUMIFS(SDM_Data!$J$2:$J$1348,SDM_Data!$B$2:$B$1348,C86,SDM_Data!$D$2:$D$1348,E86,SDM_Data!$E$2:$E$1348,G86,SDM_Data!$I$2:$I$1348,$O$2) -> 7 | J86: =SUMIFS(SDM_Data!$K$2:$K$1348,SDM_Data!$B$2:$B$1348,C86,SDM_Data!$D$2:$D$1348,E86,SDM_Data!$E$2:$E$1348,G86,SDM_Data!$I$2:$I$1348,$O$2) -> 7 | K86: =IF(J86<I86,"X","O") -> O | L86: =SUMIFS(SDM_Data!$L$2:$L$1348,SDM_Data!$B$2:$B$1348,C86,SDM_Data!$D$2:$D$1348,E86,SDM_Data!$E$2:$E$1348,G86,SDM_Data!$I$2:$I$1348,$O$2) -> 63 | M86: =SUMIFS(SDM_Data!$M$2:$M$1348,SDM_Data!$B$2:$B$1348,C86,SDM_Data!$D$2:$D$1348,E86,SDM_Data!$E$2:$E$1348,G86,SDM_Data!$I$2:$I$1348,$O$2) -> 63 | N86: =IF(M86<L86,"X","O") -> O | O86: - | P86: =IF(K86="X","l","") | Q86: =IF(N86="X","¡","") | Y86: =IF(N87="O",1,0) -> 0 | Z86: =IF(K87="O",1,0) -> 0
B87: 7.Environment | C87: Energy | D87: =D86+1 -> 66 | E87: CO2 emission | F87: 1/M | G87: ton | H87: 40244 | I87: =SUMIFS(SDM_Data!$J$2:$J$1348,SDM_Data!$B$2:$B$1348,C87,SDM_Data!$D$2:$D$1348,E87,SDM_Data!$E$2:$E$1348,G87,SDM_Data!$I$2:$I$1348,$O$2) -> 3171 | J87: =SUMIFS(SDM_Data!$K$2:$K$1348,SDM_Data!$B$2:$B$1348,C87,SDM_Data!$D$2:$D$1348,E87,SDM_Data!$E$2:$E$1348,G87,SDM_Data!$I$2:$I$1348,$O$2) -> 3598 | K87: =IF(J87>I87,"X","O") -> X | L87: =SUMIFS(SDM_Data!$L$2:$L$1348,SDM_Data!$B$2:$B$1348,C87,SDM_Data!$D$2:$D$1348,E87,SDM_Data!$E$2:$E$1348,G87,SDM_Data!$I$2:$I$1348,$O$2) -> 36635 | M87: =SUMIFS(SDM_Data!$M$2:$M$1348,SDM_Data!$B$2:$B$1348,C87,SDM_Data!$D$2:$D$1348,E87,SDM_Data!$E$2:$E$1348,G87,SDM_Data!$I$2:$I$1348,$O$2) -> 37494 | N87: =IF(M87>L87,"X","O") -> X | P87: =IF(K87="X","¡","") -> ¡ | Q87: =IF(N87="X","¡","") -> ¡ | R87: s | T87: SHE Monthly, Pinnaree PAM ( (19-Mar) Approve by P/MD/EVP
C88: Energy | E88: CO2 basic unit | F88: 1/M | G88: ton/VAP-MB | H88: -0.02 | I88: - | J88: - | K88: - | L88: =SUMIFS(SDM_Data!$L$2:$L$1348,SDM_Data!$B$2:$B$1348,C88,SDM_Data!$D$2:$D$1348,E88,SDM_Data!$E$2:$E$1348,G88,SDM_Data!$I$2:$I$1348,$O$2) -> 0 | M88: =SUMIFS(SDM_Data!$M$2:$M$1348,SDM_Data!$B$2:$B$1348,C88,SDM_Data!$D$2:$D$1348,E88,SDM_Data!$E$2:$E$1348,G88,SDM_Data!$I$2:$I$1348,$O$2) -> 0 | N88: =IF(M88>L88,"X","O") -> O | O88: =IF(N88="O","5/5","0/5") -> 5/5 | P88: =IF(K88="X","l","") | Q88: =IF(N88="X","¡","") | Y88: =IF(N89="O",1,0) -> 1 | Z88: =IF(K89="O",1,0) -> 1
C89: Energy | D89: =D87+1 -> 67 | E89: Energy saving | F89: 1/M | G89: % | H89: -0.07 | I89: =SUMIFS(SDM_Data!$J$2:$J$1348,SDM_Data!$B$2:$B$1348,C89,SDM_Data!$D$2:$D$1348,E89,SDM_Data!$E$2:$E$1348,G89,SDM_Data!$I$2:$I$1348,$O$2) -> -0.0071 | J89: =SUMIFS(SDM_Data!$K$2:$K$1348,SDM_Data!$B$2:$B$1348,C89,SDM_Data!$D$2:$D$1348,E89,SDM_Data!$E$2:$E$1348,G89,SDM_Data!$I$2:$I$1348,$O$2) -> -0.0073 | K89: =IF(J89>I89,"X","O") -> O | L89: =SUMIFS(SDM_Data!$L$2:$L$1348,SDM_Data!$B$2:$B$1348,C89,SDM_Data!$D$2:$D$1348,E89,SDM_Data!$E$2:$E$1348,G89,SDM_Data!$I$2:$I$1348,$O$2) -> -0.0644 | M89: =SUMIFS(SDM_Data!$M$2:$M$1348,SDM_Data!$B$2:$B$1348,C89,SDM_Data!$D$2:$D$1348,E89,SDM_Data!$E$2:$E$1348,G89,SDM_Data!$I$2:$I$1348,$O$2) -> -0.0672 | N89: =IF(M89>L89,"X","O") -> O | P89: =IF(K89="X","l","") | Q89: =IF(N89="X","¡","")
C90: Energy | E90: Energy saving | F90: 1/M | G90: ton | H90: -3020 | I90: =SUMIFS(SDM_Data!$J$2:$J$1348,SDM_Data!$B$2:$B$1348,C90,SDM_Data!$D$2:$D$1348,E90,SDM_Data!$E$2:$E$1348,G90,SDM_Data!$I$2:$I$1348,$O$2) -> -290 | J90: =SUMIFS(SDM_Data!$K$2:$K$1348,SDM_Data!$B$2:$B$1348,C90,SDM_Data!$D$2:$D$1348,E90,SDM_Data!$E$2:$E$1348,G90,SDM_Data!$I$2:$I$1348,$O$2) -> -299.48 | K90: =IF(J90>I90,"X","O") -> O | L90: =SUMIFS(SDM_Data!$L$2:$L$1348,SDM_Data!$B$2:$B$1348,C90,SDM_Data!$D$2:$D$1348,E90,SDM_Data!$E$2:$E$1348,G90,SDM_Data!$I$2:$I$1348,$O$2) -> -2643.3 | M90: =SUMIFS(SDM_Data!$M$2:$M$1348,SDM_Data!$B$2:$B$1348,C90,SDM_Data!$D$2:$D$1348,E90,SDM_Data!$E$2:$E$1348,G90,SDM_Data!$I$2:$I$1348,$O$2) -> -2749.26 | N90: =IF(M90>L90,"X","O") -> O | P90: =IF(K90="X","l","") | Q90: =IF(N90="X","¡","") | Y90: =IF(N91="O",1,0) -> 0 | Z90: =IF(K91="O",1,0) -> 1
C91: Energy | D91: =D89+1 -> 68 | E91: Energy saving day | F91: 1/M | G91: Day | H91: 39 | I91: =SUMIFS(SDM_Data!$J$2:$J$1348,SDM_Data!$B$2:$B$1348,C91,SDM_Data!$D$2:$D$1348,E91,SDM_Data!$E$2:$E$1348,G91,SDM_Data!$I$2:$I$1348,$O$2) -> 2 | J91: =SUMIFS(SDM_Data!$K$2:$K$1348,SDM_Data!$B$2:$B$1348,C91,SDM_Data!$D$2:$D$1348,E91,SDM_Data!$E$2:$E$1348,G91,SDM_Data!$I$2:$I$1348,$O$2) -> 2 | K91: =IF(J91>=I91,"O","X") -> O | L91: =SUMIFS(SDM_Data!$L$2:$L$1348,SDM_Data!$B$2:$B$1348,C91,SDM_Data!$D$2:$D$1348,E91,SDM_Data!$E$2:$E$1348,G91,SDM_Data!$I$2:$I$1348,$O$2) -> 37 | M91: =SUMIFS(SDM_Data!$M$2:$M$1348,SDM_Data!$B$2:$B$1348,C91,SDM_Data!$D$2:$D$1348,E91,SDM_Data!$E$2:$E$1348,G91,SDM_Data!$I$2:$I$1348,$O$2) -> 23 | N91: =IF(M91>L91,"O","X") -> X | P91: =IF(K91="X","l","") | Q91: =IF(N91="X","¡","") -> ¡ | T91: Oct'25 result | Y91: =IF(N92="O",1,0) -> 1 | Z91: =IF(K92="O",1,0) -> 1
C92: Energy | D92: =D91+1 -> 69 | E92: Energy cost (Electricity + Natural gas +N2) | F92: 1/M | G92: MB | H92: 251.99 | I92: =SUMIFS(SDM_Data!$J$2:$J$1348,SDM_Data!$B$2:$B$1348,C92,SDM_Data!$D$2:$D$1348,E92,SDM_Data!$E$2:$E$1348,G92,SDM_Data!$I$2:$I$1348,$O$2) -> 20.885 | J92: =SUMIFS(SDM_Data!$K$2:$K$1348,SDM_Data!$B$2:$B$1348,C92,SDM_Data!$D$2:$D$1348,E92,SDM_Data!$E$2:$E$1348,G92,SDM_Data!$I$2:$I$1348,$O$2) -> 20.795 | K92: =IF(J92>I92,"X","O") -> O | L92: =SUMIFS(SDM_Data!$L$2:$L$1348,SDM_Data!$B$2:$B$1348,C92,SDM_Data!$D$2:$D$1348,E92,SDM_Data!$E$2:$E$1348,G92,SDM_Data!$I$2:$I$1348,$O$2) -> 238.033 | M92: =SUMIFS(SDM_Data!$M$2:$M$1348,SDM_Data!$B$2:$B$1348,C92,SDM_Data!$D$2:$D$1348,E92,SDM_Data!$E$2:$E$1348,G92,SDM_Data!$I$2:$I$1348,$O$2) -> 226.151 | N92: =IF(M92>L92,"X","O") -> O | P92: =IF(K92="X","l","") | Q92: =IF(N92="X","¡","") | Y92: =IF(N93="O",1,0) -> 1 | Z92: =IF(K93="O",1,0) -> 0
C93: Water | D93: =D92+1 -> 70 | E93: Water usage | F93: 1/M | G93: m3 | H93: 292915 | I93: =SUMIFS(SDM_Data!$J$2:$J$1348,SDM_Data!$B$2:$B$1348,C93,SDM_Data!$D$2:$D$1348,E93,SDM_Data!$E$2:$E$1348,G93,SDM_Data!$I$2:$I$1348,$O$2) -> 25286 | J93: =SUMIFS(SDM_Data!$K$2:$K$1348,SDM_Data!$B$2:$B$1348,C93,SDM_Data!$D$2:$D$1348,E93,SDM_Data!$E$2:$E$1348,G93,SDM_Data!$I$2:$I$1348,$O$2) -> 28677 | K93: =IF(J93>I93,"X","O") -> X | L93: =SUMIFS(SDM_Data!$L$2:$L$1348,SDM_Data!$B$2:$B$1348,C93,SDM_Data!$D$2:$D$1348,E93,SDM_Data!$E$2:$E$1348,G93,SDM_Data!$I$2:$I$1348,$O$2) -> 276245 | M93: =SUMIFS(SDM_Data!$M$2:$M$1348,SDM_Data!$B$2:$B$1348,C93,SDM_Data!$D$2:$D$1348,E93,SDM_Data!$E$2:$E$1348,G93,SDM_Data!$I$2:$I$1348,$O$2) -> 269799 | N93: =IF(M93>L93,"X","O") -> O | P93: =IF(K93="X","¡","") -> ¡ | Q93: =IF(N93="X","¡","") | R93: s | Y93: =IF(N94="O",1,0) -> 1
C94: Water | D94: =D93+1 -> 71 | E94: Water reduciton | F94: 1/M | G94: % | H94: -0.01 | I94: - | J94: - | K94: - | L94: =SUMIFS(SDM_Data!$L$2:$L$1348,SDM_Data!$B$2:$B$1348,C94,SDM_Data!$D$2:$D$1348,E94,SDM_Data!$E$2:$E$1348,G94,SDM_Data!$I$2:$I$1348,$O$2) -> -0.009163 | M94: =SUMIFS(SDM_Data!$M$2:$M$1348,SDM_Data!$B$2:$B$1348,C94,SDM_Data!$D$2:$D$1348,E94,SDM_Data!$E$2:$E$1348,G94,SDM_Data!$I$2:$I$1348,$O$2) -> -0.0684 | N94: =IF(M94>L94,"X","O") -> O | P94: =IF(K94="X","l","") | Q94: =IF(N94="X","¡","") | Y94: =IF(N95="O",1,0) -> 0 | Z94: =IF(K95="O",1,0) -> 0
C95: Water | D95: =D94+1 -> 72 | E95: Water cost (Water treatment + Wastewater) | F95: 1/M | G95: MB | H95: 8.84 | I95: =SUMIFS(SDM_Data!$J$2:$J$1348,SDM_Data!$B$2:$B$1348,C95,SDM_Data!$D$2:$D$1348,E95,SDM_Data!$E$2:$E$1348,G95,SDM_Data!$I$2:$I$1348,$O$2) -> 0.893 | J95: =SUMIFS(SDM_Data!$K$2:$K$1348,SDM_Data!$B$2:$B$1348,C95,SDM_Data!$D$2:$D$1348,E95,SDM_Data!$E$2:$E$1348,G95,SDM_Data!$I$2:$I$1348,$O$2) -> 1.049 | K95: =IF(J95>I95,"X","O") -> X | L95: =SUMIFS(SDM_Data!$L$2:$L$1348,SDM_Data!$B$2:$B$1348,C95,SDM_Data!$D$2:$D$1348,E95,SDM_Data!$E$2:$E$1348,G95,SDM_Data!$I$2:$I$1348,$O$2) -> 9.349364 | M95: =SUMIFS(SDM_Data!$M$2:$M$1348,SDM_Data!$B$2:$B$1348,C95,SDM_Data!$D$2:$D$1348,E95,SDM_Data!$E$2:$E$1348,G95,SDM_Data!$I$2:$I$1348,$O$2) -> 9.447 | N95: =IF(M95>L95,"X","O") -> X | P95: =IF(K95="X","¡","") -> ¡ | Q95: =IF(N95="X","¡","") -> ¡ | Y95: =IF(N96="O",1,0) -> 1 | Z95: =IF(K96="O",1,0) -> 1
C96: Waste | D96: =D95+1 -> 73 | E96: Waste reduction (Ton/VAP-MB ) | F96: 1/M | G96: Ton/VAP-MB | H96: 0.192 | I96: =SUMIFS(SDM_Data!$J$2:$J$1348,SDM_Data!$B$2:$B$1348,C96,SDM_Data!$D$2:$D$1348,E96,SDM_Data!$E$2:$E$1348,G96,SDM_Data!$I$2:$I$1348,$O$2) -> 0.1922 | J96: =SUMIFS(SDM_Data!$K$2:$K$1348,SDM_Data!$B$2:$B$1348,C96,SDM_Data!$D$2:$D$1348,E96,SDM_Data!$E$2:$E$1348,G96,SDM_Data!$I$2:$I$1348,$O$2) -> 0.1708 | K96: =IF(J96>I96,"X","O") -> O | L96: =SUMIFS(SDM_Data!$L$2:$L$1348,SDM_Data!$B$2:$B$1348,C96,SDM_Data!$D$2:$D$1348,E96,SDM_Data!$E$2:$E$1348,G96,SDM_Data!$I$2:$I$1348,$O$2) -> 0.1922 | M96: =SUMIFS(SDM_Data!$M$2:$M$1348,SDM_Data!$B$2:$B$1348,C96,SDM_Data!$D$2:$D$1348,E96,SDM_Data!$E$2:$E$1348,G96,SDM_Data!$I$2:$I$1348,$O$2) -> 0.1737 | N96: =IF(M96>L96,"X","O") -> O | P96: =IF(K96="X","l","") | Q96: =IF(N96="X","¡","")
C97: Waste | E97: Waste reduction | F97: 1/M | G97: Ton | H97: 3298 | I97: =SUMIFS(SDM_Data!$J$2:$J$1348,SDM_Data!$B$2:$B$1348,C97,SDM_Data!$D$2:$D$1348,E97,SDM_Data!$E$2:$E$1348,G97,SDM_Data!$I$2:$I$1348,$O$2) -> 263 | J97: =SUMIFS(SDM_Data!$K$2:$K$1348,SDM_Data!$B$2:$B$1348,C97,SDM_Data!$D$2:$D$1348,E97,SDM_Data!$E$2:$E$1348,G97,SDM_Data!$I$2:$I$1348,$O$2) -> 267.27 | K97: =IF(J97>I97,"X","O") -> X | L97: =SUMIFS(SDM_Data!$L$2:$L$1348,SDM_Data!$B$2:$B$1348,C97,SDM_Data!$D$2:$D$1348,E97,SDM_Data!$E$2:$E$1348,G97,SDM_Data!$I$2:$I$1348,$O$2) -> 3013 | M97: =SUMIFS(SDM_Data!$M$2:$M$1348,SDM_Data!$B$2:$B$1348,C97,SDM_Data!$D$2:$D$1348,E97,SDM_Data!$E$2:$E$1348,G97,SDM_Data!$I$2:$I$1348,$O$2) -> 2922.02 | N97: =IF(M97>L97,"X","O") -> O | P97: =IF(K97="X","¡","") -> ¡ | Q97: =IF(N97="X","¡","") | Y97: =IF(N98="O",1,0) -> 1 | Z97: =IF(K98="O",1,0) -> 1
B98: 8. Cost | C98: Sales | D98: =D96+1 -> 74 | E98: Sales | F98: 1/M | G98: MB | H98: 31108 | I98: =SUMIFS(SDM_Data!$J$2:$J$1348,SDM_Data!$B$2:$B$1348,C98,SDM_Data!$D$2:$D$1348,E98,SDM_Data!$E$2:$E$1348,G98,SDM_Data!$I$2:$I$1348,$O$2) -> 0 | J98: =SUMIFS(SDM_Data!$K$2:$K$1348,SDM_Data!$B$2:$B$1348,C98,SDM_Data!$D$2:$D$1348,E98,SDM_Data!$E$2:$E$1348,G98,SDM_Data!$I$2:$I$1348,$O$2) -> 0 | K98: =IF(J98<I98,"X","O") -> O | L98: =SUMIFS(SDM_Data!$L$2:$L$1348,SDM_Data!$B$2:$B$1348,C98,SDM_Data!$D$2:$D$1348,E98,SDM_Data!$E$2:$E$1348,G98,SDM_Data!$I$2:$I$1348,$O$2) -> 0 | M98: =SUMIFS(SDM_Data!$M$2:$M$1348,SDM_Data!$B$2:$B$1348,C98,SDM_Data!$D$2:$D$1348,E98,SDM_Data!$E$2:$E$1348,G98,SDM_Data!$I$2:$I$1348,$O$2) -> 0 | N98: =IF(M98<L98,"X","O") -> O | P98: =IF(K98="X","l","") | Q98: =IF(N98="X","¡","") | Y98: =IF(N99="O",1,0) -> 1 | Z98: =IF(K99="O",1,0) -> 1
C99: Profit | D99: =D98+1 -> 75 | E99: Amount | F99: 1/M | G99: MB | H99: 3713 | I99: =SUMIFS(SDM_Data!$J$2:$J$1348,SDM_Data!$B$2:$B$1348,C99,SDM_Data!$D$2:$D$1348,E99,SDM_Data!$E$2:$E$1348,G99,SDM_Data!$I$2:$I$1348,$O$2) -> 279.08515 | J99: =SUMIFS(SDM_Data!$K$2:$K$1348,SDM_Data!$B$2:$B$1348,C99,SDM_Data!$D$2:$D$1348,E99,SDM_Data!$E$2:$E$1348,G99,SDM_Data!$I$2:$I$1348,$O$2) -> 350.75365 | K99: =IF(J99>I99,"O","X") -> O | L99: =SUMIFS(SDM_Data!$L$2:$L$1348,SDM_Data!$B$2:$B$1348,C99,SDM_Data!$D$2:$D$1348,E99,SDM_Data!$E$2:$E$1348,G99,SDM_Data!$I$2:$I$1348,$O$2) -> 3273.7487 | M99: =SUMIFS(SDM_Data!$M$2:$M$1348,SDM_Data!$B$2:$B$1348,C99,SDM_Data!$D$2:$D$1348,E99,SDM_Data!$E$2:$E$1348,G99,SDM_Data!$I$2:$I$1348,$O$2) -> 4258.139 | N99: =IF(M99>L99,"O","X") -> O | O99: =IF(N99="O","15/15","0/15") -> 15/15 | P99: =IF(K99="X","l","") | Q99: =IF(N99="X","¡","")
C100: Profit | E100: Ratio | F100: 1/M | G100: % | H100: 0.119 | I100: =SUMIFS(SDM_Data!$J$2:$J$1348,SDM_Data!$B$2:$B$1348,C100,SDM_Data!$D$2:$D$1348,E100,SDM_Data!$E$2:$E$1348,G100,SDM_Data!$I$2:$I$1348,$O$2) -> 0.11257979 | J100: =SUMIFS(SDM_Data!$K$2:$K$1348,SDM_Data!$B$2:$B$1348,C100,SDM_Data!$D$2:$D$1348,E100,SDM_Data!$E$2:$E$1348,G100,SDM_Data!$I$2:$I$1348,$O$2) -> 0.13073215 | K100: =IF(J100>I100,"O","X") -> O | L100: =SUMIFS(SDM_Data!$L$2:$L$1348,SDM_Data!$B$2:$B$1348,C100,SDM_Data!$D$2:$D$1348,E100,SDM_Data!$E$2:$E$1348,G100,SDM_Data!$I$2:$I$1348,$O$2) -> 0.11559383 | M100: =SUMIFS(SDM_Data!$M$2:$M$1348,SDM_Data!$B$2:$B$1348,C100,SDM_Data!$D$2:$D$1348,E100,SDM_Data!$E$2:$E$1348,G100,SDM_Data!$I$2:$I$1348,$O$2) -> 0.13858208 | N100: =IF(M100>L100,"O","X") -> O | P100: =IF(K100="X","l","") | Q100: =IF(N100="X","¡","") | Y100: =IF(N101="O",1,0) -> 1
C101: BEP | D101: =D99+1 -> 76 | E101: - | F101: 1/M | G101: % | H101: 0.4545 | I101: - | J101: - | K101: - | L101: =SUMIFS(SDM_Data!$L$2:$L$1348,SDM_Data!$B$2:$B$1348,C101,SDM_Data!$D$2:$D$1348,E101,SDM_Data!$E$2:$E$1348,G101,SDM_Data!$I$2:$I$1348,$O$2) -> 0.4625 | M101: =SUMIFS(SDM_Data!$M$2:$M$1348,SDM_Data!$B$2:$B$1348,C101,SDM_Data!$D$2:$D$1348,E101,SDM_Data!$E$2:$E$1348,G101,SDM_Data!$I$2:$I$1348,$O$2) -> 0.37185846 | N101: =IF(M101>L101,"X","O") -> O | O101: =IF(N101="O","15/15","0/10") -> 15/15 | P101: =IF(K101="X","l","") | Q101: =IF(N101="X","¡","") | Y101: =IF(N102="O",1,0) -> 1
...

Sheet Summary_SKD
B2: ="Overall Company KPI Achievement "&TEXT((TODAY()-29),"MMM-YY") -> Overall Company KPI Achievement Mar-26 | N2: 46054
B3: Company Measurement | F3: Frequency | G3: Unit | H3: FY25 Target | I3: Target | J3: Result | K3: Judge | L3: Accu. Target | M3: Accu. Result | N3: Accu. Judge | O3: Explain Item in PMM ●：Need ○：No Need | Q3: Key of problem | R3: Explain item/No. | T3: Overview result | Z3: Acc | AA3: Month
O4: Monthly | P4: Accu.
B5: 2. Quality | C5: Claim | D5: 1 | E5: Critical claim | F5: 1/M | G5: Case | H5: 0 | I5: =SUMIFS(SKD_data!$J$2:$J$584,Quality[Month],Summary_SKD!$N$2,Quality[measurment],Summary_SKD!E5,Quality[Unit],Summary_SKD!G5) -> 0 | J5: =SUMIFS(SKD_data!$K$2:$K$584,Quality[Month],Summary_SKD!$N$2,Quality[measurment],Summary_SKD!E5,Quality[Unit],Summary_SKD!G5) -> 0 | K5: =IF(J5>I5,"X","O") -> O | L5: =SUMIFS(SKD_data!$L$2:$L$584,Quality[Month],Summary_SKD!$N$2,Quality[measurment],Summary_SKD!E5,Quality[Unit],Summary_SKD!G5) -> 0 | M5: =SUMIFS(SKD_data!$M$2:$M$584,Quality[Month],Summary_SKD!$N$2,Quality[measurment],Summary_SKD!E5,Quality[Unit],Summary_SKD!G5) -> 0 | N5: =IF(M5>L5,"X","O") -> O | O5: =IF(K5="X","l","") | P5: =IF(N5="X","¡","") | Z5: =IF(N5="O",1,0) -> 1 | AA5: =IF(K5="O",1,0) -> 1
D6: 2 | E6: 0-km claim (Official) | F6: 1/M | G6: Case | H6: 1 | I6: =SUMIFS(SKD_data!$J$2:$J$584,Quality[Month],Summary_SKD!$N$2,Quality[measurment],Summary_SKD!E6,Quality[Unit],Summary_SKD!G6) -> 0 | J6: =SUMIFS(SKD_data!$K$2:$K$584,Quality[Month],Summary_SKD!$N$2,Quality[measurment],Summary_SKD!E6,Quality[Unit],Summary_SKD!G6) -> 0 | K6: =IF(J6>I6,"X","O") -> O | L6: =SUMIFS(SKD_data!$L$2:$L$584,Quality[Month],Summary_SKD!$N$2,Quality[measurment],Summary_SKD!E6,Quality[Unit],Summary_SKD!G6) -> 1 | M6: =SUMIFS(SKD_data!$M$2:$M$584,Quality[Month],Summary_SKD!$N$2,Quality[measurment],Summary_SKD!E6,Quality[Unit],Summary_SKD!G6) -> 0 | N6: =IF(M6>L6,"X","O") -> O | O6: =IF(K6="X","l","") | P6: =IF(N6="X","¡","") | T6: Monthly result | Z6: =IF(N6="O",1,0) -> 1 | AA6: =IF(K6="O",1,0) -> 1
D7: 3 | E7: 0-km claim (All DN response) | F7: 1/M | G7: Case | H7: 1 | I7: =SUMIFS(SKD_data!$J$2:$J$584,Quality[Month],Summary_SKD!$N$2,Quality[measurment],Summary_SKD!E7,Quality[Unit],Summary_SKD!G7) -> 0 | J7: =SUMIFS(SKD_data!$K$2:$K$584,Quality[Month],Summary_SKD!$N$2,Quality[measurment],Summary_SKD!E7,Quality[Unit],Summary_SKD!G7) -> 0 | K7: =IF(J7>I7,"X","O") -> O | L7: =SUMIFS(SKD_data!$L$2:$L$584,Quality[Month],Summary_SKD!$N$2,Quality[measurment],Summary_SKD!E7,Quality[Unit],Summary_SKD!G7) -> 1 | M7: =SUMIFS(SKD_data!$M$2:$M$584,Quality[Month],Summary_SKD!$N$2,Quality[measurment],Summary_SKD!E7,Quality[Unit],Summary_SKD!G7) -> 0 | N7: =IF(M7>L7,"X","O") -> O | O7: =IF(K7="X","l","") | P7: =IF(N7="X","¡","") | T7: Achieved | U7: Unachieved | V7: Total | Z7: =IF(N7="O",1,0) -> 1 | AA7: =IF(K7="O",1,0) -> 1
C8: Loss | D8: 4 | E8: Cost of spoilage | F8: 1/M | G8: % | H8: 0.0049 | I8: =SUMIFS(SKD_data!$J$2:$J$584,Quality[Month],Summary_SKD!$N$2,Quality[measurment],Summary_SKD!E8,Quality[Unit],Summary_SKD!G8) -> 0.0047233271 | J8: =SUMIFS(SKD_data!$K$2:$K$584,Quality[Month],Summary_SKD!$N$2,Quality[measurment],Summary_SKD!E8,Quality[Unit],Summary_SKD!G8) -> 0.00532 | K8: =IF(J8>I8,"X","O") -> X | L8: =SUMIFS(SKD_data!$L$2:$L$584,Quality[Month],Summary_SKD!$N$2,Quality[measurment],Summary_SKD!E8,Quality[Unit],Summary_SKD!G8) -> 0.0049055796 | M8: =SUMIFS(SKD_data!$M$2:$M$584,Quality[Month],Summary_SKD!$N$2,Quality[measurment],Summary_SKD!E8,Quality[Unit],Summary_SKD!G8) -> 0.00501 | N8: =IF(M8>L8,"X","O") -> X | O8: =IF(K8="X","l","") -> l | P8: =IF(N8="X","¡","") -> ¡ | Q8: 1.[One Times] SCV Kakou delay scrap NG (Keep Body Valve yellow stain for analysis root cause) 2.[Cont.] DF2 NG alarm over judge M/C - NG alarm sealing leak , part cap Fuel fiter NG No.0100 NG 1.8% | T8: =SUM(AA6:AA111) -> 12 | U8: =V8-T8 -> 7 | V8: =COUNT(AA6:AA111) -> 19
E9: Cost of spoilage | F9: 1/M | G9: MB | H9: 40.87MB | I9: =SUMIFS(SKD_data!$J$2:$J$584,Quality[Month],Summary_SKD!$N$2,Quality[measurment],Summary_SKD!E9,Quality[Unit],Summary_SKD!G9) -> 3.1303189 | J9: =SUMIFS(SKD_data!$K$2:$K$584,Quality[Month],Summary_SKD!$N$2,Quality[measurment],Summary_SKD!E9,Quality[Unit],Summary_SKD!G9) -> 3.8 | K9: =IF(J9>I9,"X","O") -> X | L9: =SUMIFS(SKD_data!$L$2:$L$584,Quality[Month],Summary_SKD!$N$2,Quality[measurment],Summary_SKD!E9,Quality[Unit],Summary_SKD!G9) -> 41.67 | M9: =SUMIFS(SKD_data!$M$2:$M$584,Quality[Month],Summary_SKD!$N$2,Quality[measurment],Summary_SKD!E9,Quality[Unit],Summary_SKD!G9) -> 41.2 | N9: =IF(M9>L9,"X","O") -> O | O9: =IF(K9="X","l","") -> l | P9: =IF(N9="X","¡","") | Z9: =IF(N9="O",1,0) -> 1 | AA9: =IF(K9="O",1,0) -> 0
B10: 4. Compliance | C10: Business compliance | E10: Urgent purchasing | F10: 1/M | G10: Case | H10: 73 | I10: =SUMIFS(SKD_data!$J$2:$J$584,Quality[Month],Summary_SKD!$N$2,Quality[measurment],Summary_SKD!E10,Quality[Unit],Summary_SKD!G10) -> 19 | J10: =SUMIFS(SKD_data!$K$2:$K$584,Quality[Month],Summary_SKD!$N$2,Quality[measurment],Summary_SKD!E10,Quality[Unit],Summary_SKD!G10) -> 8 | K10: =IF(J10>I10,"X","O") -> O | L10: =SUMIFS(SKD_data!$L$2:$L$584,Quality[Month],Summary_SKD!$N$2,Quality[measurment],Summary_SKD!E10,Quality[Unit],Summary_SKD!G10) -> 66 | M10: =SUMIFS(SKD_data!$M$2:$M$584,Quality[Month],Summary_SKD!$N$2,Quality[measurment],Summary_SKD!E10,Quality[Unit],Summary_SKD!G10) -> 41 | N10: =IF(M10>L10,"X","O") -> O | O10: =IF(K10="X","l","") | P10: =IF(N10="X","¡","") | T10: =T8/V8 -> 0.63157895
E11: Urgent purchasing | F11: 1/M | G11: MB | H11: 32.4 | I11: =SUMIFS(SKD_data!$J$2:$J$584,Quality[Month],Summary_SKD!$N$2,Quality[measurment],Summary_SKD!E11,Quality[Unit],Summary_SKD!G11) -> 13.639 | J11: =SUMIFS(SKD_data!$K$2:$K$584,Quality[Month],Summary_SKD!$N$2,Quality[measurment],Summary_SKD!E11,Quality[Unit],Summary_SKD!G11) -> 3.384 | K11: =IF(J11>I11,"X","O") -> O | L11: =SUMIFS(SKD_data!$L$2:$L$584,Quality[Month],Summary_SKD!$N$2,Quality[measurment],Summary_SKD!E11,Quality[Unit],Summary_SKD!G11) -> 30.95819 | M11: =SUMIFS(SKD_data!$M$2:$M$584,Quality[Month],Summary_SKD!$N$2,Quality[measurment],Summary_SKD!E11,Quality[Unit],Summary_SKD!G11) -> 10.865638 | N11: =IF(M11>L11,"X","O") -> O | O11: =IF(K11="X","l","") | P11: =IF(N11="X","¡","") | Z11: =IF(N11="O",1,0) -> 1 | AA11: =IF(K11="O",1,0) -> 1
E12: Urgent purchasing clear within3 Month | F12: 1/M | G12: Case | H12: 0 | I12: =SUMIFS(SKD_data!$J$2:$J$584,Quality[Month],Summary_SKD!$N$2,Quality[measurment],Summary_SKD!E12,Quality[Unit],Summary_SKD!G12) -> 0 | J12: =SUMIFS(SKD_data!$K$2:$K$584,Quality[Month],Summary_SKD!$N$2,Quality[measurment],Summary_SKD!E12,Quality[Unit],Summary_SKD!G12) -> 0 | K12: =IF(J12>I12,"X","O") -> O | L12: =SUMIFS(SKD_data!$L$2:$L$584,Quality[Month],Summary_SKD!$N$2,Quality[measurment],Summary_SKD!E12,Quality[Unit],Summary_SKD!G12) -> 0 | M12: =SUMIFS(SKD_data!$M$2:$M$584,Quality[Month],Summary_SKD!$N$2,Quality[measurment],Summary_SKD!E12,Quality[Unit],Summary_SKD!G12) -> 0 | N12: =IF(M12>L12,"X","O") -> O | O12: =IF(K12="X","l","") | P12: =IF(N12="X","¡","") | T12: Accumulate result
E13: Urgent purchasing clear within3 Month | F13: 1/M | G13: MB | H13: 0 | I13: =SUMIFS(SKD_data!$J$2:$J$584,Quality[Month],Summary_SKD!$N$2,Quality[measurment],Summary_SKD!E13,Quality[Unit],Summary_SKD!G13) -> 0 | J13: =SUMIFS(SKD_data!$K$2:$K$584,Quality[Month],Summary_SKD!$N$2,Quality[measurment],Summary_SKD!E13,Quality[Unit],Summary_SKD!G13) -> 0 | K13: =IF(J13>I13,"X","O") -> O | L13: =SUMIFS(SKD_data!$L$2:$L$584,Quality[Month],Summary_SKD!$N$2,Quality[measurment],Summary_SKD!E13,Quality[Unit],Summary_SKD!G13) -> 0 | M13: =SUMIFS(SKD_data!$M$2:$M$584,Quality[Month],Summary_SKD!$N$2,Quality[measurment],Summary_SKD!E13,Quality[Unit],Summary_SKD!G13) -> 0 | N13: =IF(M13>L13,"X","O") -> O | O13: =IF(K13="X","l","") | P13: =IF(N13="X","¡","") | T13: Achieved | U13: Unachieved | V13: Total | Z13: =IF(N13="O",1,0) -> 1 | AA13: =IF(K13="O",1,0) -> 1
E14: Special purchasing | F14: 1/M | G14: Case | H14: 43 | I14: =SUMIFS(SKD_data!$J$2:$J$584,Quality[Month],Summary_SKD!$N$2,Quality[measurment],Summary_SKD!E14,Quality[Unit],Summary_SKD!G14) -> 10 | J14: =SUMIFS(SKD_data!$K$2:$K$584,Quality[Month],Summary_SKD!$N$2,Quality[measurment],Summary_SKD!E14,Quality[Unit],Summary_SKD!G14) -> 4 | K14: =IF(J14>I14,"X","O") -> O | L14: =SUMIFS(SKD_data!$L$2:$L$584,Quality[Month],Summary_SKD!$N$2,Quality[measurment],Summary_SKD!E14,Quality[Unit],Summary_SKD!G14) -> 40 | M14: =SUMIFS(SKD_data!$M$2:$M$584,Quality[Month],Summary_SKD!$N$2,Quality[measurment],Summary_SKD!E14,Quality[Unit],Summary_SKD!G14) -> 38 | N14: =IF(M14>L14,"X","O") -> O | O14: =IF(K14="X","l","") | P14: =IF(N14="X","¡","") | T14: =SUM(Z6:Z111) -> 15 | U14: =V14-T14 -> 8 | V14: =COUNT(Z6:Z111) -> 23
E15: Special purchasing | F15: 1/M | G15: MB | H15: 78.7 | I15: =SUMIFS(SKD_data!$J$2:$J$584,Quality[Month],Summary_SKD!$N$2,Quality[measurment],Summary_SKD!E15,Quality[Unit],Summary_SKD!G15) -> 14.1 | J15: =SUMIFS(SKD_data!$K$2:$K$584,Quality[Month],Summary_SKD!$N$2,Quality[measurment],Summary_SKD!E15,Quality[Unit],Summary_SKD!G15) -> 1.048 | K15: =IF(J15>I15,"X","O") -> O | L15: =SUMIFS(SKD_data!$L$2:$L$584,Quality[Month],Summary_SKD!$N$2,Quality[measurment],Summary_SKD!E15,Quality[Unit],Summary_SKD!G15) -> 71 | M15: =SUMIFS(SKD_data!$M$2:$M$584,Quality[Month],Summary_SKD!$N$2,Quality[measurment],Summary_SKD!E15,Quality[Unit],Summary_SKD!G15) -> 43.678 | N15: =IF(M15>L15,"X","O") -> O | O15: =IF(K15="X","l","") | P15: =IF(N15="X","¡","") | Z15: =IF(N15="O",1,0) -> 1 | AA15: =IF(K15="O",1,0) -> 1
C16: Asset control | D16: 5 | E16: Idle Fixed Assets | F16: 1/M | G16: Case | H16: - | I16: - | J16: - | K16: - | L16: =SUMIFS(SKD_data!$L$2:$L$584,Quality[Month],Summary_SKD!$N$2,Quality[measurment],Summary_SKD!E16,Quality[Unit],Summary_SKD!G16) -> 0 | M16: =SUMIFS(SKD_data!$M$2:$M$584,Quality[Month],Summary_SKD!$N$2,Quality[measurment],Summary_SKD!E16,Quality[Unit],Summary_SKD!G16) -> 0 | N16: =IF(M16>L16,"X","O") -> O | O16: =IF(K16="X","l","") | P16: =IF(N16="X","¡","") | T16: =T14/V14 -> 0.65217391
E17: Idle Fixed Assets | F17: 1/M | G17: MB | H17: - | I17: - | J17: - | K17: - | L17: =SUMIFS(SKD_data!$L$2:$L$584,Quality[Month],Summary_SKD!$N$2,Quality[measurment],Summary_SKD!E17,Quality[Unit],Summary_SKD!G17) -> 0 | M17: =SUMIFS(SKD_data!$M$2:$M$584,Quality[Month],Summary_SKD!$N$2,Quality[measurment],Summary_SKD!E17,Quality[Unit],Summary_SKD!G17) -> 0 | N17: =IF(M17>L17,"X","O") -> O | O17: =IF(K17="X","l","") | P17: =IF(N17="X","¡","")
D18: 6 | E18: CIP (No using date) | F18: 1/M | G18: Case | H18: - | I18: - | J18: - | K18: - | L18: - | M18: =SUMIFS(SKD_data!$M$2:$M$584,Quality[Month],Summary_SKD!$N$2,Quality[measurment],Summary_SKD!E18,Quality[Unit],Summary_SKD!G18) -> 28 | N18: - | O18: =IF(K18="X","l","") | P18: =IF(N18="X","¡","") | Q18: CIP (No using date) No record INV on system PE : 12 case, 6.86 MB. PU : 12 case, 18.49 MB. PD : 3 case, 3.57 MB. MT : 1 case, 0.04 MB.
E19: CIP (No using date) | F19: 1/M | G19: MB | H19: - | I19: - | J19: - | K19: - | L19: - | M19: =SUMIFS(SKD_data!$M$2:$M$584,Quality[Month],Summary_SKD!$N$2,Quality[measurment],Summary_SKD!E19,Quality[Unit],Summary_SKD!G19) -> 32.49 | N19: - | O19: =IF(K19="X","l","") | P19: =IF(N19="X","¡","")
D20: 7 | E20: CIP (Document not complete) | F20: 1/M | G20: Case | H20: - | I20: - | J20: - | K20: - | L20: - | M20: =SUMIFS(SKD_data!$M$2:$M$584,Quality[Month],Summary_SKD!$N$2,Quality[measurment],Summary_SKD!E20,Quality[Unit],Summary_SKD!G20) -> 19 | N20: - | O20: =IF(K20="X","l","") | P20: =IF(N20="X","¡","") | Q20: CIP (Document not complete) Under process approval & No submit analysis PE : 7 case, 4.6 MB. PU : 3 case, 2.09 MB. PD : 9 case, 8.01 MB.
E21: CIP (Document not complete) | F21: 1/M | G21: MB | H21: - | I21: - | J21: - | K21: - | L21: - | M21: =SUMIFS(SKD_data!$M$2:$M$584,Quality[Month],Summary_SKD!$N$2,Quality[measurment],Summary_SKD!E21,Quality[Unit],Summary_SKD!G21) -> 35.96 | N21: - | O21: =IF(K21="X","l","") | P21: =IF(N21="X","¡","")
D22: 8 | E22: CIP > 12 Month | F22: 1/M | G22: Case | H22: 0 | I22: =SUMIFS(SKD_data!$J$2:$J$584,Quality[Month],Summary_SKD!$N$2,Quality[measurment],Summary_SKD!E22,Quality[Unit],Summary_SKD!G22) -> 3 | J22: =SUMIFS(SKD_data!$K$2:$K$584,Quality[Month],Summary_SKD!$N$2,Quality[measurment],Summary_SKD!E22,Quality[Unit],Summary_SKD!G22) -> 0 | K22: =IF(J22>=I22,"O","X") -> X | L22: =SUMIFS(SKD_data!$L$2:$L$584,Quality[Month],Summary_SKD!$N$2,Quality[measurment],Summary_SKD!E22,Quality[Unit],Summary_SKD!G22) -> 3 | M22: =SUMIFS(SKD_data!$M$2:$M$584,Quality[Month],Summary_SKD!$N$2,Quality[measurment],Summary_SKD!E22,Quality[Unit],Summary_SKD!G22) -> 4 | N22: =IF(M22<L22,"O","X") -> X | O22: =IF(K22="X","¡","") -> ¡ | P22: =IF(N22="X","¡","") -> ¡ | Q22: (CIP >12 M) Complete 2 item 1.7MB trf in Jan.26 Over revise plan : PE : 1 Case 0.94MB (Waiting memo for cancel PO and record to expense) Transfer in FY26 PE : 1case 1.7MB (WASHING SOL 1W (G2G3) MC1 & MC2) | R22: Report in TMM 31/Mar By ACC/PE GM | Z22: =IF(N22="O",1,0) -> 0 | AA22: =IF(K22="O",1,0) -> 0
E23: CIP > 12 Month | F23: 1/M | G23: MB | H23: 0 | I23: =SUMIFS(SKD_data!$J$2:$J$584,Quality[Month],Summary_SKD!$N$2,Quality[measurment],Summary_SKD!E23,Quality[Unit],Summary_SKD!G23) -> 2.64 | J23: =SUMIFS(SKD_data!$K$2:$K$584,Quality[Month],Summary_SKD!$N$2,Quality[measurment],Summary_SKD!E23,Quality[Unit],Summary_SKD!G23) -> 0 | K23: =IF(J23>=I23,"O","X") -> X | L23: =SUMIFS(SKD_data!$L$2:$L$584,Quality[Month],Summary_SKD!$N$2,Quality[measurment],Summary_SKD!E23,Quality[Unit],Summary_SKD!G23) -> 3.5 | M23: =SUMIFS(SKD_data!$M$2:$M$584,Quality[Month],Summary_SKD!$N$2,Quality[measurment],Summary_SKD!E23,Quality[Unit],Summary_SKD!G23) -> 4.5 | N23: =IF(M23<L23,"O","X") -> X | O23: =IF(K23="X","¡","") -> ¡ | P23: =IF(N23="X","¡","") -> ¡
D24: 9 | E24: CIP > 18 Month | F24: 1/M | G24: Case | H24: 0 | I24: =SUMIFS(SKD_data!$J$2:$J$584,Quality[Month],Summary_SKD!$N$2,Quality[measurment],Summary_SKD!E24,Quality[Unit],Summary_SKD!G24) -> 2 | J24: =SUMIFS(SKD_data!$K$2:$K$584,Quality[Month],Summary_SKD!$N$2,Quality[measurment],Summary_SKD!E24,Quality[Unit],Summary_SKD!G24) -> 1 | K24: =IF(J24>=I24,"O","X") -> X | L24: =SUMIFS(SKD_data!$L$2:$L$584,Quality[Month],Summary_SKD!$N$2,Quality[measurment],Summary_SKD!E24,Quality[Unit],Summary_SKD!G24) -> 1 | M24: =SUMIFS(SKD_data!$M$2:$M$584,Quality[Month],Summary_SKD!$N$2,Quality[measurment],Summary_SKD!E24,Quality[Unit],Summary_SKD!G24) -> 3 | N24: =IF(M24<L24,"O","X") -> X | O24: =IF(K24="X","¡","") -> ¡ | P24: =IF(N24="X","¡","") -> ¡ | R24: Report in TMM 31/Mar By ACC/PE GM | Z24: =IF(N24="O",1,0) -> 0 | AA24: =IF(K24="O",1,0) -> 0
E25: CIP > 18 Month | F25: 1/M | G25: MB | H25: 0 | I25: =SUMIFS(SKD_data!$J$2:$J$584,Quality[Month],Summary_SKD!$N$2,Quality[measurment],Summary_SKD!E25,Quality[Unit],Summary_SKD!G25) -> 1.76 | J25: =SUMIFS(SKD_data!$K$2:$K$584,Quality[Month],Summary_SKD!$N$2,Quality[measurment],Summary_SKD!E25,Quality[Unit],Summary_SKD!G25) -> 1.06 | K25: =IF(J25>=I25,"O","X") -> X | L25: =SUMIFS(SKD_data!$L$2:$L$584,Quality[Month],Summary_SKD!$N$2,Quality[measurment],Summary_SKD!E25,Quality[Unit],Summary_SKD!G25) -> 1.55 | M25: =SUMIFS(SKD_data!$M$2:$M$584,Quality[Month],Summary_SKD!$N$2,Quality[measurment],Summary_SKD!E25,Quality[Unit],Summary_SKD!G25) -> 1.76 | N25: =IF(M25<L25,"O","X") -> X | O25: =IF(K25="X","¡","") -> ¡ | P25: =IF(N25="X","¡","") -> ¡
D26: 10 | E26: Un-received Order >12 [expense] | F26: 1/M | G26: Case | H26: - | I26: - | J26: - | K26: - | L26: =SUMIFS(SKD_data!$L$2:$L$584,Quality[Month],Summary_SKD!$N$2,Quality[measurment],Summary_SKD!E26,Quality[Unit],Summary_SKD!G26) -> 0 | M26: =SUMIFS(SKD_data!$M$2:$M$584,Quality[Month],Summary_SKD!$N$2,Quality[measurment],Summary_SKD!E26,Quality[Unit],Summary_SKD!G26) -> 13 | N26: =IF(M26>L26,"X","O") -> X | O26: =IF(K26="X","l","") | P26: =IF(N26="X","¡","") -> ¡ | Q26: SKD expense : PD common : 6 cases = 1.60 MB PUR common : 2 cases = 1.79 MB **Data date of 10 Mar'26** | R26: Report in TMM 24-Feb Report by Pruek /GM
E27: Un-received Order >12 [expense] | F27: 1/M | G27: MB | H27: - | I27: - | J27: - | K27: - | L27: =SUMIFS(SKD_data!$L$2:$L$584,Quality[Month],Summary_SKD!$N$2,Quality[measurment],Summary_SKD!E27,Quality[Unit],Summary_SKD!G27) -> 0 | M27: =SUMIFS(SKD_data!$M$2:$M$584,Quality[Month],Summary_SKD!$N$2,Quality[measurment],Summary_SKD!E27,Quality[Unit],Summary_SKD!G27) -> 3.548 | N27: =IF(M27>L27,"X","O") -> X | O27: =IF(K27="X","l","") | P27: =IF(N27="X","¡","") -> ¡ | R27: Report in TMM 10-Mar By each Dept. | Z27: =IF(N27="O",1,0) -> 0 | AA27: =IF(K27="O",1,0) -> 0
D28: 11 | E28: Un-received Order >18 [Investment] | F28: 1/M | G28: Case | H28: - | I28: - | J28: - | K28: - | L28: =SUMIFS(SKD_data!$L$2:$L$584,Quality[Month],Summary_SKD!$N$2,Quality[measurment],Summary_SKD!E28,Quality[Unit],Summary_SKD!G28) -> 0 | M28: =SUMIFS(SKD_data!$M$2:$M$584,Quality[Month],Summary_SKD!$N$2,Quality[measurment],Summary_SKD!E28,Quality[Unit],Summary_SKD!G28) -> 37 | N28: =IF(M28>L28,"X","O") -> X | O28: =IF(K28="X","l","") | P28: =IF(N28="X","¡","") -> ¡ | Q28: SKD Investment PU common : 18 cases = 25.44 MB PD (Fuel filter) : 7 cases = 0.744 MB PD (Valve) 4 cases = 1.57 MB **Data date of 10 Mar'26** | R28: Report in TMM 24-Feb Report by Pruek /GM
E29: Un-received Order >18 [Investment] | F29: 1/M | G29: MB | H29: - | I29: - | J29: - | K29: - | L29: =SUMIFS(SKD_data!$L$2:$L$584,Quality[Month],Summary_SKD!$N$2,Quality[measurment],Summary_SKD!E29,Quality[Unit],Summary_SKD!G29) -> 0 | M29: =SUMIFS(SKD_data!$M$2:$M$584,Quality[Month],Summary_SKD!$N$2,Quality[measurment],Summary_SKD!E29,Quality[Unit],Summary_SKD!G29) -> 37.111 | N29: =IF(M29>L29,"X","O") -> X | O29: =IF(K29="X","l","") | P29: =IF(N29="X","¡","") -> ¡ | R29: Report in TMM 10-Mar By each Dept. | Z29: =IF(N29="O",1,0) -> 0 | AA29: =IF(K29="O",1,0) -> 0
D30: 12 | E30: Inventory variance | F30: 1/6M | G30: % | H30: - | I30: - | J30: - | K30: - | L30: =SUMIFS(SKD_data!$L$2:$L$584,Quality[Month],Summary_SKD!$N$2,Quality[measurment],Summary_SKD!E30,Quality[Unit],Summary_SKD!G30) -> -0.005 | M30: =SUMIFS(SKD_data!$M$2:$M$584,Quality[Month],Summary_SKD!$N$2,Quality[measurment],Summary_SKD!E30,Quality[Unit],Summary_SKD!G30) -> -0.004 | N30: =IF(M30<L30,"X","O") -> O | O30: =IF(K30="X","l","") | P30: =IF(N30="X","¡","") | Z30: =IF(N30="O",1,0) -> 1 | AA30: =IF(K30="O",1,0) -> 0
E31: Inventory variance | F31: 1/6M | G31: MB | H31: - | I31: - | J31: - | K31: - | L31: =SUMIFS(SKD_data!$L$2:$L$584,Quality[Month],Summary_SKD!$N$2,Quality[measurment],Summary_SKD!E31,Quality[Unit],Summary_SKD!G31) -> 0 | M31: =SUMIFS(SKD_data!$M$2:$M$584,Quality[Month],Summary_SKD!$N$2,Quality[measurment],Summary_SKD!E31,Quality[Unit],Summary_SKD!G31) -> -2.12 | N31: =IF(M31>L31,"X","O") -> O | O31: =IF(K31="X","l","") | P31: =IF(N31="X","¡","")
D32: 13 | E32: Spare part inventory | F32: 1/6M | G32: % | H32: 0.0342 | I32: =SUMIFS(SKD_data!$J$2:$J$584,Quality[Month],Summary_SKD!$N$2,Quality[measurment],Summary_SKD!E32,Quality[Unit],Summary_SKD!G32) -> 0.0298 | J32: =SUMIFS(SKD_data!$K$2:$K$584,Quality[Month],Summary_SKD!$N$2,Quality[measurment],Summary_SKD!E32,Quality[Unit],Summary_SKD!G32) -> 0.0276 | K32: =IF(J32>I32,"X","O") -> O | L32: =SUMIFS(SKD_data!$L$2:$L$584,Quality[Month],Summary_SKD!$N$2,Quality[measurment],Summary_SKD!E32,Quality[Unit],Summary_SKD!G32) -> 0.0298 | M32: =SUMIFS(SKD_data!$M$2:$M$584,Quality[Month],Summary_SKD!$N$2,Quality[measurment],Summary_SKD!E32,Quality[Unit],Summary_SKD!G32) -> 0.0276 | N32: =IF(M32>L32,"X","O") -> O | O32: =IF(K32="X","l","") | P32: =IF(N32="X","¡","") | Z32: =IF(N32="O",1,0) -> 1 | AA32: =IF(K32="O",1,0) -> 1
E33: Spare part inventory | F33: 1/6M | G33: MB | H33: - | I33: =SUMIFS(SKD_data!$J$2:$J$584,Quality[Month],Summary_SKD!$N$2,Quality[measurment],Summary_SKD!E33,Quality[Unit],Summary_SKD!G33) -> 104.35 | J33: =SUMIFS(SKD_data!$K$2:$K$584,Quality[Month],Summary_SKD!$N$2,Quality[measurment],Summary_SKD!E33,Quality[Unit],Summary_SKD!G33) -> 96.09 | K33: =IF(J33>I33,"X","O") -> O | L33: =SUMIFS(SKD_data!$L$2:$L$584,Quality[Month],Summary_SKD!$N$2,Quality[measurment],Summary_SKD!E33,Quality[Unit],Summary_SKD!G33) -> 104.35 | M33: =SUMIFS(SKD_data!$M$2:$M$584,Quality[Month],Summary_SKD!$N$2,Quality[measurment],Summary_SKD!E33,Quality[Unit],Summary_SKD!G33) -> 96.09 | N33: =IF(M33>L33,"X","O") -> O | O33: =IF(K33="X","l","") | P33: =IF(N33="X","¡","")
D34: 14 | E34: Slow moving of FG | F34: 1/3M | G34: MB | H34: 3.17 | I34: - | J34: =SUMIFS(SKD_data!$K$2:$K$584,Quality[Month],Summary_SKD!$N$2,Quality[measurment],Summary_SKD!E34,Quality[Unit],Summary_SKD!G34) -> 0 | K34: - | L34: =SUMIFS(SKD_data!$L$2:$L$584,Quality[Month],Summary_SKD!$N$2,Quality[measurment],Summary_SKD!E34,Quality[Unit],Summary_SKD!G34) -> 0.12 | M34: =SUMIFS(SKD_data!$M$2:$M$584,Quality[Month],Summary_SKD!$N$2,Quality[measurment],Summary_SKD!E34,Quality[Unit],Summary_SKD!G34) -> 0.4 | N34: =IF(M34>L34,"X","O") -> X | O34: =IF(K34="X","l","") | P34: =IF(N34="X","¡","") -> ¡ | R34: Resul of Dec'25 | Z34: =IF(N34="O",1,0) -> 0
D35: 15 | E35: Slow moving of Parts&RM | F35: 1/3M | G35: MB | H35: - | I35: - | J35: - | K35: - | L35: =SUMIFS(SKD_data!$L$2:$L$584,Quality[Month],Summary_SKD!$N$2,Quality[measurment],Summary_SKD!E35,Quality[Unit],Summary_SKD!G35) -> 2 | M35: =SUMIFS(SKD_data!$M$2:$M$584,Quality[Month],Summary_SKD!$N$2,Quality[measurment],Summary_SKD!E35,Quality[Unit],Summary_SKD!G35) -> 0.9 | N35: =IF(M35>L35,"X","O") -> O | O35: =IF(K35="X","l","") | P35: =IF(N35="X","¡","") | Z35: =IF(N35="O",1,0) -> 1
D36: 16 | E36: Slow moving of Spare Parts | F36: 1/3M | G36: MB | H36: - | I36: - | J36: - | K36: - | L36: =SUMIFS(SKD_data!$L$2:$L$584,Quality[Month],Summary_SKD!$N$2,Quality[measurment],Summary_SKD!E36,Quality[Unit],Summary_SKD!G36) -> 30.2 | M36: =SUMIFS(SKD_data!$M$2:$M$584,Quality[Month],Summary_SKD!$N$2,Quality[measurment],Summary_SKD!E36,Quality[Unit],Summary_SKD!G36) -> 31.9 | N36: =IF(M36>L36,"X","O") -> X | O36: =IF(K36="X","l","") | P36: =IF(N36="X","¡","") -> ¡ | R36: Result of Dec'25 | Z36: =IF(N36="O",1,0) -> 0 | AA36: =IF(K36="O",1,0) -> 0
D37: 17 | E37: Dead stock of FG, PART & RM | F37: 1/Y | G37: MB | H37: 5.4 | I37: - | J37: =SUMIFS(SKD_data!$K$2:$K$584,Quality[Month],Summary_SKD!$N$2,Quality[measurment],Summary_SKD!E37,Quality[Unit],Summary_SKD!G37) -> 0 | K37: - | L37: =SUMIFS(SKD_data!$L$2:$L$584,Quality[Month],Summary_SKD!$N$2,Quality[measurment],Summary_SKD!E37,Quality[Unit],Summary_SKD!G37) -> 0 | M37: =SUMIFS(SKD_data!$M$2:$M$584,Quality[Month],Summary_SKD!$N$2,Quality[measurment],Summary_SKD!E37,Quality[Unit],Summary_SKD!G37) -> 0 | N37: - | O37: =IF(K37="X","l","") | P37: =IF(N37="X","¡","")
D38: 18 | E38: Dead stock of Spare parts | F38: 1/Y | G38: MB | H38: 3 | I38: - | J38: =SUMIFS(SKD_data!$K$2:$K$584,Quality[Month],Summary_SKD!$N$2,Quality[measurment],Summary_SKD!E38,Quality[Unit],Summary_SKD!G38) -> 0 | K38: - | L38: =SUMIFS(SKD_data!$L$2:$L$584,Quality[Month],Summary_SKD!$N$2,Quality[measurment],Summary_SKD!E38,Quality[Unit],Summary_SKD!G38) -> 0 | M38: =SUMIFS(SKD_data!$M$2:$M$584,Quality[Month],Summary_SKD!$N$2,Quality[measurment],Summary_SKD!E38,Quality[Unit],Summary_SKD!G38) -> 0 | N38: - | O38: =IF(K38="X","l","") | P38: =IF(N38="X","¡","")
B39: 8. Cost | C39: Sale | D39: 19 | E39: Sale | F39: 1/M | G39: MB | H39: 8293.83 | I39: =SUMIFS(SKD_data!$J$2:$J$584,Quality[Month],Summary_SKD!$N$2,Quality[measurment],Summary_SKD!E39,Quality[Unit],Summary_SKD!G39,Quality[[Sub ]],Summary_SKD!C39) -> 654.38259 | J39: =SUMIFS(SKD_data!$K$2:$K$584,Quality[Month],Summary_SKD!$N$2,Quality[measurment],Summary_SKD!E39,Quality[Unit],Summary_SKD!G39,Quality[[Sub ]],Summary_SKD!C39) -> 711 | K39: =IF(J39<I39,"X","O") -> O | L39: =SUMIFS(SKD_data!$L$2:$L$584,Quality[Month],Summary_SKD!$N$2,Quality[measurment],Summary_SKD!E39,Quality[Unit],Summary_SKD!G39,Quality[[Sub ]],Summary_SKD!C39) -> 7606.5082 | M39: =SUMIFS(SKD_data!$M$2:$M$584,Quality[Month],Summary_SKD!$N$2,Quality[measurment],Summary_SKD!E39,Quality[Unit],Summary_SKD!G39,Quality[[Sub ]],Summary_SKD!C39) -> 8076.2591 | N39: =IF(M39<L39,"X","O") -> O | O39: =IF(K39="X","l","") | P39: =IF(N39="X","¡","") | Z39: =IF(N39="O",1,0) -> 1 | AA39: =IF(K39="O",1,0) -> 1
C40: Profit | D40: 20 | E40: Amount | F40: 1/M | G40: MB | H40: 675.95 | I40: =SUMIFS(SKD_data!$J$2:$J$584,Quality[Month],Summary_SKD!$N$2,Quality[measurment],Summary_SKD!E40,Quality[Unit],Summary_SKD!G40,Quality[[Sub ]],Summary_SKD!C40) -> 61.201754 | J40: =SUMIFS(SKD_data!$K$2:$K$584,Quality[Month],Summary_SKD!$N$2,Quality[measurment],Summary_SKD!E40,Quality[Unit],Summary_SKD!G40,Quality[[Sub ]],Summary_SKD!C40) -> 66 | K40: =IF(J40>I40,"O","X") -> O | L40: =SUMIFS(SKD_data!$L$2:$L$584,Quality[Month],Summary_SKD!$N$2,Quality[measurment],Summary_SKD!E40,Quality[Unit],Summary_SKD!G40,Quality[[Sub ]],Summary_SKD!C40) -> 616.34532 | M40: =SUMIFS(SKD_data!$M$2:$M$584,Quality[Month],Summary_SKD!$N$2,Quality[measurment],Summary_SKD!E40,Quality[Unit],Summary_SKD!G40,Quality[[Sub ]],Summary_SKD!C40) -> 935.30399 | N40: =IF(M40>L40,"O","X") -> O | O40: =IF(K40="X","l","") | P40: =IF(N40="X","¡","") | Z40: =IF(N40="O",1,0) -> 1 | AA40: =IF(K40="O",1,0) -> 1
C41: Profit | E41: Ratio | F41: 1/M | G41: % | H41: 0.0815 | I41: =SUMIFS(SKD_data!$J$2:$J$584,Quality[Month],Summary_SKD!$N$2,Quality[measurment],Summary_SKD!E41,Quality[Unit],Summary_SKD!G41,Quality[[Sub ]],Summary_SKD!C41) -> 0.093525951 | J41: =SUMIFS(SKD_data!$K$2:$K$584,Quality[Month],Summary_SKD!$N$2,Quality[measurment],Summary_SKD!E41,Quality[Unit],Summary_SKD!G41,Quality[[Sub ]],Summary_SKD!C41) -> 0.092 | K41: =IF(J41>I41,"O","X") -> X | L41: =SUMIFS(SKD_data!$L$2:$L$584,Quality[Month],Summary_SKD!$N$2,Quality[measurment],Summary_SKD!E41,Quality[Unit],Summary_SKD!G41,Quality[[Sub ]],Summary_SKD!C41) -> 0.08102868 | M41: =SUMIFS(SKD_data!$M$2:$M$584,Quality[Month],Summary_SKD!$N$2,Quality[measurment],Summary_SKD!E41,Quality[Unit],Summary_SKD!G41,Quality[[Sub ]],Summary_SKD!C41) -> 0.11580906 | N41: =IF(M41>L41,"O","X") -> O | O41: =IF(K41="X","l","") -> l | P41: =IF(N41="X","¡","")
C42: BEP | D42: 21 | E42: - | F42: 1/M | G42: % | H42: 0.61 | L42: =SUMIFS(SKD_data!$L$2:$L$584,Quality[Month],Summary_SKD!$N$2,Quality[measurment],Summary_SKD!E42,Quality[Unit],Summary_SKD!G42,Quality[[Sub ]],Summary_SKD!C42) -> 0.59087324 | M42: =SUMIFS(SKD_data!$M$2:$M$584,Quality[Month],Summary_SKD!$N$2,Quality[measurment],Summary_SKD!E42,Quality[Unit],Summary_SKD!G42,Quality[[Sub ]],Summary_SKD!C42) -> 0.51563772 | N42: =IF(M42>L42,"X","O") -> O | O42: =IF(K42="X","l","") | P42: =IF(N42="X","¡","") | Z42: =IF(J42="O",1,0) -> 0
C43: Fixed cost C/D | D43: 22 | E43: - | F43: 1/M | G43: % | H43: 0.127 | L43: =SUMIFS(SKD_data!$L$2:$L$584,Quality[Month],Summary_SKD!$N$2,Quality[measurment],Summary_SKD!E43,Quality[Unit],Summary_SKD!G43,Quality[[Sub ]],Summary_SKD!C43) -> 0.11923504 | M43: =SUMIFS(SKD_data!$M$2:$M$584,Quality[Month],Summary_SKD!$N$2,Quality[measurment],Summary_SKD!E43,Quality[Unit],Summary_SKD!G43,Quality[[Sub ]],Summary_SKD!C43) -> 0.116 | N43: =IF(M43>L43,"X","O") -> O | O43: =IF(K43="X","l","") | P43: =IF(N43="X","¡","") | Z43: =IF(J43="O",1,0) -> 0
C44: Productivity | D44: 23 | E44: Direct (%) | F44: 1/M | G44: % | H44: 1 | I44: =SUMIFS(SKD_data!$J$2:$J$584,Quality[Month],Summary_SKD!$N$2,Quality[measurment],Summary_SKD!E44,Quality[Unit],Summary_SKD!G44,Quality[[Sub ]],Summary_SKD!C44) -> 1 | J44: =SUMIFS(SKD_data!$K$2:$K$584,Quality[Month],Summary_SKD!$N$2,Quality[measurment],Summary_SKD!E44,Quality[Unit],Summary_SKD!G44,Quality[[Sub ]],Summary_SKD!C44) -> 0.96 | K44: =IF(J44>I44,"X","O") -> O | L44: =SUMIFS(SKD_data!$L$2:$L$584,Quality[Month],Summary_SKD!$N$2,Quality[measurment],Summary_SKD!E44,Quality[Unit],Summary_SKD!G44,Quality[[Sub ]],Summary_SKD!C44) -> 1 | M44: =SUMIFS(SKD_data!$M$2:$M$584,Quality[Month],Summary_SKD!$N$2,Quality[measurment],Summary_SKD!E44,Quality[Unit],Summary_SKD!G44,Quality[[Sub ]],Summary_SKD!C44) -> 0.96313414 | N44: =IF(M44>L44,"X","O") -> O | O44: =IF(K44="X","l","") | P44: =IF(N44="X","¡","") | Z44: =IF(N44="O",1,0) -> 1 | AA44: =IF(K44="O",1,0) -> 1
C45: Productivity | E45: Direct (Ninku) | F45: 1/M | G45: Ninku | H45: 10164 | I45: =SUMIFS(SKD_data!$J$2:$J$584,Quality[Month],Summary_SKD!$N$2,Quality[measurment],Summary_SKD!E45,Quality[Unit],Summary_SKD!G45,Quality[[Sub ]],Summary_SKD!C45) -> 1007 | J45: =SUMIFS(SKD_data!$K$2:$K$584,Quality[Month],Summary_SKD!$N$2,Quality[measurment],Summary_SKD!E45,Quality[Unit],Summary_SKD!G45,Quality[[Sub ]],Summary_SKD!C45) -> 978 | K45: =IF(J45>I45,"X","O") -> O | L45: =SUMIFS(SKD_data!$L$2:$L$584,Quality[Month],Summary_SKD!$N$2,Quality[measurment],Summary_SKD!E45,Quality[Unit],Summary_SKD!G45,Quality[[Sub ]],Summary_SKD!C45) -> 10066.038 | M45: =SUMIFS(SKD_data!$M$2:$M$584,Quality[Month],Summary_SKD!$N$2,Quality[measurment],Summary_SKD!E45,Quality[Unit],Summary_SKD!G45,Quality[[Sub ]],Summary_SKD!C45) -> 9888.0884 | N45: =IF(M45>L45,"X","O") -> O | O45: =IF(K45="X","l","") | P45: =IF(N45="X","¡","")
C46: Productivity | D46: 24 | E46: Indirect (%) | F46: 1/M | G46: % | H46: 1 | I46: =SUMIFS(SKD_data!$J$2:$J$584,Quality[Month],Summary_SKD!$N$2,Quality[measurment],Summary_SKD!E46,Quality[Unit],Summary_SKD!G46,Quality[[Sub ]],Summary_SKD!C46) -> 1 | J46: =SUMIFS(SKD_data!$K$2:$K$584,Quality[Month],Summary_SKD!$N$2,Quality[measurment],Summary_SKD!E46,Quality[Unit],Summary_SKD!G46,Quality[[Sub ]],Summary_SKD!C46) -> 0.9 | K46: =IF(J46>I46,"X","O") -> O | L46: =SUMIFS(SKD_data!$L$2:$L$584,Quality[Month],Summary_SKD!$N$2,Quality[measurment],Summary_SKD!E46,Quality[Unit],Summary_SKD!G46,Quality[[Sub ]],Summary_SKD!C46) -> 1 | M46: =SUMIFS(SKD_data!$M$2:$M$584,Quality[Month],Summary_SKD!$N$2,Quality[measurment],Summary_SKD!E46,Quality[Unit],Summary_SKD!G46,Quality[[Sub ]],Summary_SKD!C46) -> 0.93001959 | N46: =IF(M46>L46,"X","O") -> O | O46: =IF(K46="X","l","") | P46: =IF(N46="X","¡","") | Z46: =IF(N46="O",1,0) -> 1 | AA46: =IF(K46="O",1,0) -> 1
C47: Productivity | E47: Indirect (Ninku) | F47: 1/M | G47: Ninku | H47: 936 | I47: =SUMIFS(SKD_data!$J$2:$J$584,Quality[Month],Summary_SKD!$N$2,Quality[measurment],Summary_SKD!E47,Quality[Unit],Summary_SKD!G47,Quality[[Sub ]],Summary_SKD!C47) -> 81 | J47: =SUMIFS(SKD_data!$K$2:$K$584,Quality[Month],Summary_SKD!$N$2,Quality[measurment],Summary_SKD!E47,Quality[Unit],Summary_SKD!G47,Quality[[Sub ]],Summary_SKD!C47) -> 73 | K47: =IF(J47>I47,"X","O") -> O | L47: =SUMIFS(SKD_data!$L$2:$L$584,Quality[Month],Summary_SKD!$N$2,Quality[measurment],Summary_SKD!E47,Quality[Unit],Summary_SKD!G47,Quality[[Sub ]],Summary_SKD!C47) -> 796.89 | M47: =SUMIFS(SKD_data!$M$2:$M$584,Quality[Month],Summary_SKD!$N$2,Quality[measurment],Summary_SKD!E47,Quality[Unit],Summary_SKD!G47,Quality[[Sub ]],Summary_SKD!C47) -> 765.22 | N47: =IF(M47>L47,"X","O") -> O | O47: =IF(K47="X","l","") | P47: =IF(N47="X","¡","") | Z47: =IF(N47="O",1,0) -> 1 | AA47: =IF(K47="O",1,0) -> 1
C48: Labour cost | D48: 25 | E48: Direct | F48: 1/M | G48: MB | H48: 413.7 | I48: =SUMIFS(SKD_data!$J$2:$J$584,Quality[Month],Summary_SKD!$N$2,Quality[measurment],Summary_SKD!E48,Quality[Unit],Summary_SKD!G48,Quality[[Sub ]],Summary_SKD!C48) -> 41 | J48: =SUMIFS(SKD_data!$K$2:$K$584,Quality[Month],Summary_SKD!$N$2,Quality[measurment],Summary_SKD!E48,Quality[Unit],Summary_SKD!G48,Quality[[Sub ]],Summary_SKD!C48) -> 37 | K48: =IF(J48>I48,"X","O") -> O | L48: =SUMIFS(SKD_data!$L$2:$L$584,Quality[Month],Summary_SKD!$N$2,Quality[measurment],Summary_SKD!E48,Quality[Unit],Summary_SKD!G48,Quality[[Sub ]],Summary_SKD!C48) -> 523.34 | M48: =SUMIFS(SKD_data!$M$2:$M$584,Quality[Month],Summary_SKD!$N$2,Quality[measurment],Summary_SKD!E48,Quality[Unit],Summary_SKD!G48,Quality[[Sub ]],Summary_SKD!C48) -> 514.94 | N48: =IF(M48>L48,"X","O") -> O | O48: =IF(K48="X","l","") | P48: =IF(N48="X","¡","") | R48: SiF tranfer Expat MP | Z48: =IF(N48="O",1,0) -> 1 | AA48: =IF(K48="O",1,0) -> 1
C49: Labour cost | E49: Indirect | F49: 1/M | G49: MB | H49: 126 | I49: =SUMIFS(SKD_data!$J$2:$J$584,Quality[Month],Summary_SKD!$N$2,Quality[measurment],Summary_SKD!E49,Quality[Unit],Summary_SKD!G49,Quality[[Sub ]],Summary_SKD!C49) -> 5 | J49: =SUMIFS(SKD_data!$K$2:$K$584,Quality[Month],Summary_SKD!$N$2,Quality[measurment],Summary_SKD!E49,Quality[Unit],Summary_SKD!G49,Quality[[Sub ]],Summary_SKD!C49) -> 5 | K49: =IF(J49>I47,"X","O") -> O | L49: =SUMIFS(SKD_data!$L$2:$L$584,Quality[Month],Summary_SKD!$N$2,Quality[measurment],Summary_SKD!E49,Quality[Unit],Summary_SKD!G49,Quality[[Sub ]],Summary_SKD!C49) -> 66.1 | M49: =SUMIFS(SKD_data!$M$2:$M$584,Quality[Month],Summary_SKD!$N$2,Quality[measurment],Summary_SKD!E49,Quality[Unit],Summary_SKD!G49,Quality[[Sub ]],Summary_SKD!C49) -> 62.655 | N49: =IF(M49>L49,"X","O") -> O | O49: =IF(K49="X","l","") | P49: =IF(N49="X","¡","")

Sheet Safety
J18: 45778
B19: Reason | C19: Recover activity | D19: Forecas result (Total) | E19: forecase recovery Month | G19: Reason | H19: Recover activity | I19: Forecas result (Total) | J19: forecase recovery Month
B20: =SDM_Data!O93 -> 1.Man : Authorized person Not follow regulation 2.System : Not have regulation to specific the Type of truck in each operation. | C20: 1.Level up Awareness & review role & response of authorized person (Owner activity, Owner area & Security guard) 2.Establish the regulation (Type of truck – Operation – Area) by centralized control and reduce fragmented control | D20: =SDM_Data!Q93 -> 4 | E20: =SDM_Data!R93 -> Mar.26

Sheet Q_Claim
N17: 45778
A18: Reason | B18: Recover activity | C18: Forecas result (Total) | D18: forecase recovery Month | F18: Reason | G18: Recover activity | H18: Forecas result (Total) | I18: forecase recovery Month | K18: Reason | L18: Recover activity | M18: Forecas result (Total) | N18: forecase recovery Month
A19: =SDM_Data!O214 -> 1. STM HP5S Engine cannot start (F/M Glue) Cause: Glue from jig ball air leak test at cylinder grinding process | B19: =SDM_Data!P214 -> C/M: 1) Change new jig design for prevent glue split. [Eff. Date : 10 Feb’26] 2) Add split glue removal procedure for ball jig. [Eff. Date : 4 Feb’26] Overall : Improve initial response and upstream Kaizen in FY26. | C19: =SDM_Data!Q214 -> Achieve target. Forecast total = 4 cases (FY25 SDM target = 4 cases) | D19: =SDM_Data!R214 -> Within FY26 | F19: =SDM_Data!O215 -> 1. STM HP5S Engine cannot start (F/M Glue) Cause: Glue from jig ball air leak test at cylinder grinding process | G19: =SDM_Data!P215 -> Same above. | H19: =SDM_Data!Q215 -> Not achieve target. Forecast total = 11 cases (FY25 SDM target = 9 cases) | I19: =SDM_Data!R215 -> Within FY26 | K19: =SDM_Data!O192 -> 0 | L19: =SDM_Data!P192 -> 0 | M19: =SDM_Data!Q192 -> 0 | N19: =SDM_Data!R192 -> 0
A38: Reason | B38: Recover activity | C38: Forecas result (Total) | D38: End Effect month | F38: Reason | G38: Recover activity | H38: Forecas result (Total) | I38: Start Effect month | K38: Reason | L38: Recover activity | M38: Forecas result (Total) | N38: End Effect month
A39: 1. DMHU Plug rail Coating peeling Cause: Under invesitgate with supplier & DIAT | B39: =SDM_Data!P216 -> C/M: (Temporary) 200% inspection part at supplier before delivery Overall : Improve initial response and upstream Kaizen in FY26. | C39: =SDM_Data!Q216 -> Not achieve target. Forecast total = 17 cases (FY25 target = 6 cases) | D39: =SDM_Data!R216 -> Within FY26 | F39: =SDM_Data!O218 -> 1. Rail Cap pipe fuel return Broken Cause: Under invesitgation 2. G3S Inlet connector missing ball Cause: Under investigation | G39: =SDM_Data!P218 -> C/M: Under invesitgation C/M: (Temporary) 100% Pin gauge check Go-NoGo at STC before delivery to SDM. | H39: =SDM_Data!Q218 -> Forecast total = 3 cases (FY25 target = 5 cases) | I39: =SDM_Data!R218 -> - | K39: =SDM_Data!O217 -> 1. DMHU Plug rail Coating peeling Cause: Under invesitgate with supplier & DIAT 2. G3S Inlet connector missing ball Cause: Under investigation | L39: =SDM_Data!P217 -> C/M: (Temporary) 200% inspection part at supplier before delivery C/M: (Temporary) 100% Pin gauge check Go-NoGo at STC before delivery to SDM. | M39: =SDM_Data!Q217 -> Not achieve target. Forcast total = 16 cases (FY25 target = 6 cases) | N39: =SDM_Data!R217 -> Within FY26
A58: Reason | B58: Recover activity | C58: Forecas result (Total) | D58: End Effect month | F58: Reason | G58: Recover activity | H58: Forecas result (Total) | I58: Start Effect month
A59: - | B59: - | C59: - | D59: - | F59: - | G59: - | H59: - | I59: -

Sheet Q-Loss
I17: 45901
A18: Reason | B18: Recover activity | C18: Forecas result (Total) | D18: End Effect month | F18: Reason | G18: Recover activity | H18: Forecas result (Total) | I18: Start Effect month
A19: =SDM_Data!O219 -> Monthly Over +0.02% Acc. AP/ Result ▲0.03% Cost of spoilage P/J on plan Remain KADAI : GDP [Plan 3.35MB/Act. 4.59MB/Diff+1.24MB] Problem P/L NG 1,146pcs [Plan 0.24%/Act 0.73%/Diff +0.49%] 1) Occure material DNTH cutting 601 run-out NG forecast end of Mar'26 (Forecast Mar'26 Over +1.2MB) 2) Occure in SDM process Relief seat grd. CPK 1.33 improvement M/C & Jig accuracy | B19: =SDM_Data!P219 -> GDP problem P/L NG situation action plan (Material & Machine) 1.(PE3/BPE) DNTH combine process cutting PCR issue start cutting line 602 (1st lot control to SDM Mar'26) and extend cutting line 601,603,604 Plan end of Mar'26 (On process) 2.PE2&PD Process capability M/C Relief seat grinding CPK >1.33 (On process) 3.PE2&PD next plan reamain KADAI condition grinding (Completed) -PD temporary action re-grinding process relief seat lapping 2 time and control depth seat surface & PE Change new type dresser | C19: =SDM_Data!Q219 -> Forecast Acc. Save ▲0.030% (Apr'25 -Mar'26) | D19: =SDM_Data!R219 -> 0 | F19: =SDM_Data!O220 -> Monthly Over +0.6MB Acc. AP/ Result ▲4.99MB | G19: =SDM_Data!P220 -> - | H19: =SDM_Data!Q220 -> Forecast Acc. Save ▲8.6MB (Apr'25 -Mar'26) | I19: =SDM_Data!R220 -> 0
A37: Reason | B37: Recover activity | C37: Forecas result (Total) | D37: End Effect month | F37: Reason | G37: Recover activity | H37: Forecas result (Total) | I37: Start Effect month | K37: Reason | L37: Recover activity | M37: Forecas result (Total) | N37: Start Effect month
A38: =SKD_data!O55 -> 1.[One Times] SCV Kakou delay scrap NG (Keep Body Valve yellow stain for analysis root cause) 2.[Cont.] DF2 NG alarm over judge M/C - NG alarm sealing leak , part cap Fuel fiter NG No.0100 NG 1.8% | B38: =SKD_data!P55 -> SCV NG Body valve yellow stain Action Change method for cleaning DI water and pump. DF2 NG alarm over jude M/C Action Maker change new inset mold Current MG 0% | C38: =SKD_data!Q55 -> 0.0048 | D38: =SKD_data!R55 -> - | F38: =SKD_data!O56 -> 1.[One Times] SCV Kakou delay scrap NG (Keep Body Valve yellow stain for analysis root cause) (+147 KB) 2.[Cont.] DF2 NG alarm over judge M/C - NG alarm sealing leak , part cap Fuel fiter NG No.0100 | G38: =SKD_data!P56 -> 0 | H38: =SKD_data!Q56 -> 4.3 | I38: =SKD_data!R56 -> - | K38: =SDM_Data!O221 -> Problem close increasing from last month = 16 items. New issue in Feb'26 = 15 items. Remaining issue cannot action until root cause C/M. Kadai : Almost unique problem of SDM/SKD Approach : Expands engineering ability for improvement by re-process & design | L38: =SDM_Data!P221 -> Priority and set action plan for overall quality loss (Q-loss & COS) in company in FY26. And strengthen ability of plan and actual control. (As explained in quality pillar) | M38: =SDM_Data!Q221 -> Not achieve target. Forecast = 178.5 MB | N38: =SDM_Data!R221 -> Within FY26
K39: Quality loss

Sheet Delivery
I17: 45778
A18: Reason | B18: Recover activity | C18: Forecas result (Total) | D18: End Effect month | F18: Reason | G18: Recover activity | H18: Forecas result (Total) | I18: Start Effect month
A19: =SDM_Data!O285 -> 0 | B19: =SDM_Data!P285 -> 0 | C19: =SDM_Data!Q285 -> 0 | D19: =SDM_Data!R285 -> 0 | F19: =SDM_Data!O286 -> GDP Assy line 2 (2.5 Day) Cover damper & seat upper laser welding mc - Ball screw of work work press ⇒ Loss time diagnosis due to trial & error ⇒ Create FTA Quality+BM UC pipe (0.5 Day) Air leak test mc - Air leakage in inspection system ⇒ Loss time diagnosis due to alarm message is not related with pheomenon ⇒ Create FTA Quality+BM PCV (2.5 Day) Intake valve OD GR ⇒ Quality/Process problem DF Plastic (1.0 Day) ⇒ Raw Material NG from TAKAHATA DF ADC (0.5 Day) New High pressure leak test mc ⇒ Process/Machine design problem (After SOP 1 month) | G19: =SDM_Data!P286 -> 0 | H19: =SDM_Data!Q286 -> 0 | I19: =SDM_Data!R286 -> 0
A38: Reason | B38: Recover activity | C38: Forecas result (Total) | D38: End Effect month | F38: Reason | G38: Recover activity | H38: Forecas result (Total) | I38: Start Effect month | K38: Reason | L38: Recover activity | M38: Forecas result (Total) | N38: Start Effect month
A39: - | B39: - | C39: - | D39: - | F39: - | G39: - | H39: - | I39: - | K39: =SDM_Data!O289 -> TH-Cambodia cross border situation | M39: - | N39: -

Sheet Compliane
I17: 45778
A18: Reason | B18: Recover activity | C18: Forecas result (Total) | D18: End Effect month | F18: Reason | G18: Recover activity | H18: Forecas result (Total) | I18: Start Effect month | K18: Reason | L18: Recover activity | M18: Forecas result (Total) | N18: Start Effect month
A19: - | B19: - | C19: - | D19: - | F19: - | G19: - | H19: - | I19: - | K19: =SDM_Data!O861&CHAR(10)&SDM_Data!O863&CHAR(10)&CHAR(10)&SKD_data!O398&CHAR(10)&SKD_data!O400 -> Expense >12M SDM-MT&FAC : 65 cases / 4.597 MB.:Job Stock Spare part,Oil) SDM-SPD&PD : 30 case / 3.149 Mb.: Job.Kaizen MC. & Cutting Tool SDM-PC : 14 cases / 0.354 MB.:Job Rent for Forklift SDM-Admin : 14 case / 1.057 MB.:Job Repair Investment >18M SDM-PE : 70 case / 42.549 MB.:Job Modify MC SDM-SPD&PE : 15 case / 7.374 Mb.: Job Kaizen MC. SKD expense >12 M SKD-PD : 4 cases / 0.328 MB.:Job Cutting tool SKD-MT&FAC : 4 case / 1.359 MB.:Job PM Machine SKD Investment >18 SKD-DMIN : 22 case / 26.215 MB.:Job Mold-die SKD-PR : 8 case / 4.193 MB.:Job Kaizen MC. | L19: =SDM_Data!P861&CHAR(10)&SDM_Data!P863 | M19: =SDM_Data!Q861&CHAR(10)&SDM_Data!Q863 | N19: =SDM_Data!R861&CHAR(10)&SDM_Data!R863
A38: Reason | B38: Recover activity | C38: Forecas result (Total) | D38: End Effect month | F38: Reason | G38: Recover activity | H38: Forecas result (Total) | I38: Start Effect month | K38: Reason | L38: Recover activity | M38: Forecas result (Total) | N38: Start Effect month
A39: =SDM_Data!O853&CHAR(10)&SDM_Data!O854&CHAR(10)&SDM_Data!O855&CHAR(10)&SDM_Data!O856 -> CIP (No using date) : PE 76.5 MB. SE 8.78MB PD 4.93 MB. INN 3.03 MB FAC 1.9 MB. MT 1.44 MB. CIP (Document not complete) FAC 5.29MB, PE 86.24MB, PD 4.49 MB. | B39: =SDM_Data!P853&CHAR(10)&SDM_Data!P854&CHAR(10)&SDM_Data!P855&CHAR(10)&SDM_Data!P856 | C39: =SDM_Data!Q853&CHAR(10)&SDM_Data!Q854&CHAR(10)&SDM_Data!Q855&CHAR(10)&SDM_Data!Q856 | D39: =SDM_Data!R853&CHAR(10)&SDM_Data!R854&CHAR(10)&SDM_Data!R855&CHAR(10)&SDM_Data!R856 | F39: =SKD_data!O390&CHAR(10)&SKD_data!O391&CHAR(10)&SKD_data!O392&CHAR(10)&SKD_data!O393 -> CIP (No using date) No record INV on system PE : 12 case, 6.86 MB. PU : 12 case, 18.49 MB. PD : 3 case, 3.57 MB. MT : 1 case, 0.04 MB. CIP (Document not complete) Under process approval & No submit analysis PE : 7 case, 4.6 MB. PU : 3 case, 2.09 MB. PD : 9 case, 8.01 MB. | G39: =SKD_data!P390&CHAR(10)&SKD_data!P391&CHAR(10)&SKD_data!P392&CHAR(10)&SKD_data!P393 | H39: =SKD_data!Q390&CHAR(10)&SKD_data!Q391&CHAR(10)&SKD_data!Q392&CHAR(10)&SKD_data!Q393 | I39: =SKD_data!R390&CHAR(10)&SKD_data!R391&CHAR(10)&SKD_data!R392&CHAR(10)&SKD_data!R393 | K39: =SDM_Data!O845 -> 0 | L39: =SDM_Data!P845 -> 0 | M39: =SDM_Data!Q845 -> 0 | N39: =SDM_Data!R845 -> 0
I58: 45778
A59: Reason | B59: Recover activity | C59: Forecas result (Total) | D59: End Effect month | F59: Reason | G59: Recover activity | H59: Forecas result (Total) | I59: Start Effect month | K59: Reason | L59: Recover activity | M59: Forecas result (Total) | N59: End Effect month
A60: =SDM_Data!O857&CHAR(10)&SDM_Data!O859 -> Plan Jan'26 = 4case Complet until Jan'26 = 15 case Complete until Jan'26 = 1 case(plan Mar'26) Remark: Target FY26 = 4case Transfer in Jun'26= 2 case 0.41 MB. Addition transfer in Jun'26 = 2case 6.94 MB. Completed in Jan'26 = plan 1 case Target FY26 Transfer in May'26= 6case (7.68 MB) Transfer in Apr'26= 1case (0.43 MB) | B60: =SDM_Data!P857&CHAR(10)&SDM_Data!P859 | C60: =SDM_Data!Q857&CHAR(10)&SDM_Data!Q859 | D60: =SDM_Data!R857&CHAR(10)&SDM_Data!R859 | F60: =SKD_data!O394&CHAR(10)&SKD_data!O395 -> (CIP >12 M) Complete 2 item 1.7MB trf in Jan.26 Over revise plan : PE : 1 Case 0.94MB (Waiting memo for cancel PO and record to expense) Transfer in FY26 PE : 1case 1.7MB (WASHING SOL 1W (G2G3) MC1 & MC2) Complete 2item 1.7MB trf in Jan.26 | G60: =SKD_data!P394&CHAR(10)&SKD_data!P395 | H60: =SKD_data!Q394&CHAR(10)&SKD_data!Q395 | I60: =SKD_data!R394&CHAR(10)&SKD_data!R395 | K60: - | L60: - | M60: - | N60: -
I80: 45778
A81: Reason | B81: Recover activity | C81: Forecas result (Total) | D81: End Effect month | F81: Reason | G81: Recover activity | H81: Forecas result (Total) | I81: Start Effect month | K81: Reason | L81: Recover activity | M81: Forecas result (Total) | N81: Start Effect month
A82: =SDM_Data!O859&CHAR(10)&SDM_Data!O860 -> Completed in Jan'26 = plan 1 case Target FY26 Transfer in May'26= 6case (7.68 MB) Transfer in Apr'26= 1case (0.43 MB) | B82: =SDM_Data!P859&CHAR(10)&SDM_Data!P860 | C82: =SDM_Data!Q859&CHAR(10)&SDM_Data!Q860 | D82: =SDM_Data!R859&CHAR(10)&SDM_Data!R860 | F82: =SKD_data!O364 -> (CIP > 18 M) Add Jan.26: - Over revise plan : - Transfer in FY26 - PU 17Case 21MB (Mold) - PE 1Case 1MB (AUTO LOADER 4SLOT PROCESING AT AMATURE S/A) | G82: =SKD_data!P364 -> 0 | H82: =SKD_data!Q364 -> 0 | I82: =SKD_data!R364 -> 0 | K82: =SDM_Data!O797 -> 0 | L82: =SDM_Data!P797 -> 0 | M82: =SDM_Data!Q797 -> 0 | N82: =SDM_Data!R797 -> 0
A100: Reason | B100: Recover activity | C100: Forecas result (Total) | D100: End Effect month | F100: Reason | G100: Recover activity | H100: Forecas result (Total) | I100: Start Effect month | K100: Reason | L100: Recover activity | M100: Forecas result (Total) | N100: Start Effect month
A101: - | B101: - | C101: - | D101: - | F101: - | G101: - | H101: - | I101: - | K101: =SDM_Data!O820 -> 0 | L101: =SDM_Data!P820 -> 0 | M101: =SDM_Data!Q820 -> 0 | N101: =SDM_Data!R820 -> 0
A314: Purchasing

Sheet Environment
N17: 45778
A18: Reason | B18: Recover activity | C18: Forecas result (Total) | D18: End Effect month | F18: Reason | G18: Recover activity | H18: Forecas result (Total) | I18: Start Effect month | K18: Reason | L18: Recover activity | M18: Forecas result (Total) | N18: Start Effect month
A19: =[1]Environment!P$58 -> - | B19: =[1]Environment!Q$58 -> - | C19: =[1]Environment!R$58 -> - | D19: =[1]Environment!S$58 -> - | F19: =SDM_Data!O1178 -> 0 | G19: =SDM_Data!P1178 -> 0 | H19: =SDM_Data!Q1178 -> 0 | I19: =SDM_Data!R1178 -> 0 | K19: =[1]Environment!P$59 -> - | L19: =[1]Environment!Q$59 -> - | M19: =[1]Environment!R$59 -> - | N19: =[1]Environment!S$59 -> -
A38: Reason | B38: Recover activity | C38: Forecas result (Total) | D38: End Effect month | F38: Reason | G38: Recover activity | H38: Forecas result (Total) | I38: End Effect month | K38: Reason | L38: Recover activity | M38: Forecas result (Total) | N38: Start Effect month
A39: =[1]Environment!P$62 -> - | B39: =[1]Environment!Q$62 -> - | C39: =[1]Environment!R$62 -> - | D39: =[1]Environment!S$62 -> - | F39: - | G39: - | H39: - | I39: - | K39: =SDM_Data!O1114 -> Accumulate Apr-Jul CO2 Emission over +766 t-CO2 from planned, The reason are (1) Co-generation stop (2) No energy day not achieve (3) Daily usage increase from production volume up and irrecgular issue | L39: =SDM_Data!P1114 -> Loss from Co-generation BM -Improve performance after repair, Addition time running Loss from No Energy day -Scope JIT supply -Reduce loss, air leak, standby m/c and Stop air condition after 17.00 of office area | M39: =SDM_Data!Q1114 -> Can recovery about 772 t-CO2 | N39: =SDM_Data!R1114 -> Dec'25
A58: Reason | B58: Recover activity | C58: Forecas result (Total) | D58: Start Effect month | F58: Reason | G58: Recover activity | H58: Forecas result (Total) | I58: End Effect month | K58: Reason | L58: Recover activity | M58: Forecas result (Total) | N58: Start Effect month
A59: =SDM_Data!O1102 -> - | B59: =SDM_Data!P1102 -> - | C59: =SDM_Data!Q1102 -> - | D59: =SDM_Data!R1102 -> - | F59: - | G59: - | H59: - | I59: - | K59: - | L59: - | M59: - | N59: -
A60: Energy

Sheet Attractive
A18: Reason | B18: Recover activity | C18: Target | D18: forecase recovery Month | F18: Reason | G18: Recover activity | H18: Target | I18: forecase recovery Month
A19: =SDM_Data!O1072 -> Safety DX Project delay from waiting PO approval and workflow analysis MT waiting start GO-Live Periodic system in FY26 (New data) | B19: =SDM_Data!P1072 -> - In FY26 attractive team will changing the scope of project which increase efficiency of SQDC (Cross Dept.) instead of working hour reduction and value-added - Auto Oil&Chemical usage report | C19: =SDM_Data!Q1072 -> 0 | D19: =SDM_Data!R1072 -> 0 | F19: =SDM_Data!O1071 -> Total 401.33 /1122.77 Hr./month 1. PPA 360/360 Hr. 2. Tool change 41/295 Hr. (62 times/week *4 week * 10min/60min = 41.33Hr/month) App complete but still can't canceled paper (Can count only double job load at 5ME app) 3. P chart 0/467.77 Hr. (Delay from P-chart comment, Change platform from M365-->Web app) | G19: =SDM_Data!P1071 -> 1.Tool change : Action weekly follow up w/ PD for speed up paper cancel 2. P-Chart : New paralell develop web app to use instead M365 due to app speed response issue | H19: =SDM_Data!Q1071 -> 0 | I19: =SDM_Data!R1071 -> Tool change - Cancel paper April'26 P-Chart - New web app Aug'26

Sheet Sheet1
A1: Safety
A3: Pump/M | B3: (All) | M3: Pump/A | N3: (All) | Y3: INJ/M | Z3: (All) | AK3: INJ/A | AL3: (All) | AW3: Vavle | AX3: (All) | BI3: SOL | BJ3: (All) | BU3: UC/M | BV3: (All) | CG3: UC/A | CH3: (All) | CS3: GDP | CT3: (All) | DE3: SIFS/DF | DF3: (All) | DQ3: TIE | DR3: (All) | EC3: WH | ED3: (All) | EO3: MT | EP3: (All) | FA3: QA&QC | FB3: (All) | FM3: ADM | FN3: (All) | FY3: PE | FZ3: (All) | GK3: PC | GL3: (All) | GW3: SPD | GX3: (All) | HI3: SE | HJ3: (All)
A5: Sum of Pump/M | B5: Column Labels | M5: Sum of Pump/A | N5: Column Labels | Y5: Sum of INJ/M | Z5: Column Labels | AK5: Sum of INJ/A | AL5: Column Labels | AW5: Sum of Vavle | AX5: Column Labels | BI5: Sum of SOL | BJ5: Column Labels | BU5: Sum of UC/M | BV5: Column Labels | CG5: Sum of UC/A | CH5: Column Labels | CS5: Sum of GDP | CT5: Column Labels | DE5: Sum of SIFS/DF | DF5: Column Labels | DQ5: Sum of TIE | DR5: Column Labels | EC5: Sum of WH | ED5: Column Labels | EO5: Sum of MT | EP5: Column Labels | FA5: Sum of QA&QC | FB5: Column Labels | FM5: Sum of ADM | FN5: Column Labels | FY5: Sum of PE | FZ5: Column Labels | GK5: Sum of PC | GL5: Column Labels | GW5: Sum of SPD | GX5: Column Labels | HI5: Sum of SE | HJ5: Column Labels
A6: Row Labels | B6: 1-Grade accident | C6: 8-High risk audit | D6: Fatal | E6: Hit | F6: Hit something | G6: Illegal & dangerous driving | H6: Injury | I6: Near miss | J6: Reoccurrence | M6: Row Labels | N6: 1-Grade accident | O6: 8-High risk audit | P6: Fatal | Q6: Hit | R6: Hit something | S6: Illegal & dangerous driving | T6: Injury | U6: Near miss | V6: Reoccurrence | Y6: Row Labels | Z6: 1-Grade accident | AA6: 8-High risk audit | AB6: Fatal | AC6: Hit | AD6: Hit something | AE6: Illegal & dangerous driving | AF6: Injury | AG6: Near miss | AH6: Reoccurrence | AK6: Row Labels | AL6: 1-Grade accident | AM6: 8-High risk audit | AN6: Fatal | AO6: Hit | AP6: Hit something | AQ6: Illegal & dangerous driving | AR6: Injury | AS6: Near miss | AT6: Reoccurrence | AW6: Row Labels | AX6: 1-Grade accident | AY6: 8-High risk audit | AZ6: Fatal | BA6: Hit | BB6: Hit something | BC6: Illegal & dangerous driving | BD6: Injury | BE6: Near miss | BF6: Reoccurrence | BI6: Row Labels | BJ6: 1-Grade accident | BK6: 8-High risk audit | BL6: Fatal | BM6: Hit | BN6: Hit something | BO6: Illegal & dangerous driving | BP6: Injury | BQ6: Near miss | BR6: Reoccurrence | BS6: Grand Total | BU6: Row Labels | BV6: 1-Grade accident | BW6: 8-High risk audit | BX6: Fatal | BY6: Hit | BZ6: Hit something | CA6: Illegal & dangerous driving | CB6: Injury | CC6: Near miss | CD6: Reoccurrence | CE6: Grand Total | CG6: Row Labels | CH6: 1-Grade accident | CI6: 8-High risk audit | CJ6: Fatal | CK6: Hit | CL6: Hit something | CM6: Illegal & dangerous driving | CN6: Injury | CO6: Near miss | CP6: Reoccurrence | CQ6: Grand Total | CS6: Row Labels | CT6: 1-Grade accident | CU6: 8-High risk audit | CV6: Fatal | CW6: Hit | CX6: Hit something | CY6: Illegal & dangerous driving | CZ6: Injury | DA6: Near miss | DB6: Reoccurrence | DC6: Grand Total | DE6: Row Labels | DF6: 1-Grade accident | DG6: 8-High risk audit | DH6: Fatal | DI6: Hit | DJ6: Hit something | DK6: Illegal & dangerous driving | DL6: Injury | DM6: Near miss | DN6: Reoccurrence | DO6: Grand Total | DQ6: Row Labels | DR6: 1-Grade accident | DS6: 8-High risk audit | DT6: Fatal | DU6: Hit | DV6: Hit something | DW6: Illegal & dangerous driving | DX6: Injury | DY6: Near miss | DZ6: Reoccurrence | EA6: Grand Total | EC6: Row Labels | ED6: 1-Grade accident | EE6: 8-High risk audit | EF6: Fatal | EG6: Hit | EH6: Hit something | EI6: Illegal & dangerous driving | EJ6: Injury | EK6: Near miss | EL6: Reoccurrence | EM6: Grand Total | EO6: Row Labels | EP6: 1-Grade accident | EQ6: 8-High risk audit | ER6: Fatal | ES6: Hit | ET6: Hit something | EU6: Illegal & dangerous driving | EV6: Injury | EW6: Near miss | EX6: Reoccurrence | EY6: Grand Total | FA6: Row Labels | FB6: 1-Grade accident | FC6: 8-High risk audit | FD6: Fatal | FE6: Hit | FF6: Hit something | FG6: Illegal & dangerous driving | FH6: Injury | FI6: Near miss | FJ6: Reoccurrence | FK6: Grand Total | FM6: Row Labels | FN6: 1-Grade accident | FO6: 8-High risk audit | FP6: Fatal | FQ6: Hit | FR6: Hit something | FS6: Illegal & dangerous driving | FT6: Injury | FU6: Near miss | FV6: Reoccurrence | FW6: Grand Total | FY6: Row Labels | FZ6: 1-Grade accident | GA6: 8-High risk audit | GB6: Fatal | GC6: Hit | GD6: Hit something | GE6: Illegal & dangerous driving | GF6: Injury | GG6: Near miss | GH6: Reoccurrence | GI6: Grand Total | GK6: Row Labels | GL6: 1-Grade accident | GM6: 8-High risk audit | GN6: Fatal | GO6: Hit | GP6: Hit something | GQ6: Illegal & dangerous driving | GR6: Injury | GS6: Near miss | GT6: Reoccurrence | GU6: Grand Total | GW6: Row Labels | GX6: 1-Grade accident | GY6: 8-High risk audit | GZ6: Fatal | HA6: Hit | HB6: Hit something | HC6: Illegal & dangerous driving | HD6: Injury | HE6: Near miss | HF6: Reoccurrence | HG6: Grand Total | HI6: Row Labels | HJ6: 1-Grade accident | HK6: 8-High risk audit | HL6: Fatal | HM6: Hit | HN6: Hit something | HO6: Illegal & dangerous driving | HP6: Injury | HQ6: Near miss | HR6: Reoccurrence | HS6: Grand Total
A7: Apr | B7: 0 | D7: 0 | E7: 0 | F7: 0 | G7: 0 | H7: 0 | I7: 0 | J7: 0 | M7: Apr | N7: 0 | P7: 0 | Q7: 0 | R7: 0 | S7: 0 | T7: 0 | U7: 0 | V7: 0 | Y7: Apr | Z7: 0 | AB7: 0 | AC7: 0 | AD7: 0 | AE7: 0 | AF7: 0 | AG7: 0 | AH7: 0 | AK7: Apr | AL7: 0 | AN7: 0 | AO7: 0 | AP7: 0 | AQ7: 0 | AR7: 0 | AS7: 0 | AT7: 0 | AW7: Apr | AX7: 0 | AZ7: 0 | BA7: 0 | BB7: 0 | BC7: 0 | BD7: 0 | BE7: 0 | BF7: 0 | BI7: Apr | BJ7: 0 | BL7: 0 | BM7: 0 | BN7: 0 | BO7: 0 | BP7: 0 | BQ7: 0 | BR7: 0 | BS7: 0 | BU7: Apr | BV7: 0 | BX7: 0 | BY7: 0 | BZ7: 0 | CA7: 0 | CB7: 0 | CC7: 0 | CD7: 0 | CE7: 0 | CG7: Apr | CH7: 0 | CJ7: 0 | CK7: 0 | CL7: 0 | CM7: 0 | CN7: 0 | CO7: 0 | CP7: 0 | CQ7: 0 | CS7: Apr | CT7: 0 | CV7: 0 | CW7: 0 | CX7: 0 | CY7: 0 | CZ7: 0 | DA7: 0 | DB7: 0 | DC7: 0 | DE7: Apr | DF7: 0 | DH7: 0 | DI7: 0 | DJ7: 0 | DK7: 0 | DL7: 0 | DM7: 0 | DN7: 0 | DO7: 0 | DQ7: Apr | DR7: 0 | DT7: 0 | DU7: 0 | DV7: 0 | DW7: 0 | DX7: 0 | DY7: 0 | DZ7: 0 | EA7: 0 | EC7: Apr | ED7: 0 | EF7: 0 | EG7: 0 | EH7: 0 | EI7: 0 | EJ7: 0 | EK7: 0 | EL7: 0 | EM7: 0 | EO7: Apr | EP7: 0 | ER7: 0 | ES7: 0 | ET7: 0 | EU7: 0 | EV7: 0 | EW7: 0 | EX7: 0 | EY7: 0 | FA7: Apr | FB7: 0 | FD7: 0 | FE7: 0 | FF7: 0 | FG7: 0 | FH7: 0 | FI7: 0 | FJ7: 0 | FK7: 0 | FM7: Apr | FN7: 0 | FP7: 0 | FQ7: 0 | FR7: 0 | FS7: 0 | FT7: 0 | FU7: 0 | FV7: 0 | FW7: 0 | FY7: Apr | FZ7: 0 | GB7: 0 | GC7: 0 | GD7: 0 | GE7: 0 | GF7: 0 | GG7: 0 | GH7: 0 | GI7: 0 | GK7: Apr | GL7: 0 | GN7: 0 | GO7: 0 | GP7: 0 | GQ7: 0 | GR7: 0 | GS7: 0 | GT7: 0 | GU7: 0 | GW7: Apr | GX7: 0 | GZ7: 0 | HA7: 0 | HB7: 0 | HC7: 0 | HD7: 0 | HE7: 0 | HF7: 0 | HG7: 0 | HI7: Apr | HJ7: 0 | HL7: 0 | HM7: 0 | HN7: 0 | HO7: 0 | HP7: 0 | HQ7: 0 | HR7: 0 | HS7: 0
A8: May | B8: 0 | D8: 0 | E8: 0 | F8: 0 | G8: 0 | H8: 0 | I8: 0 | J8: 0 | M8: May | N8: 0 | P8: 0 | Q8: 0 | R8: 0 | S8: 0 | T8: 0 | U8: 0 | V8: 0 | Y8: May | Z8: 0 | AB8: 0 | AC8: 0 | AD8: 0 | AE8: 0 | AF8: 0 | AG8: 0 | AH8: 0 | AK8: May | AL8: 0 | AN8: 0 | AO8: 0 | AP8: 0 | AQ8: 0 | AR8: 0 | AS8: 0 | AT8: 0 | AW8: May | AX8: 0 | AZ8: 0 | BA8: 0 | BB8: 0 | BC8: 0 | BD8: 0 | BE8: 0 | BF8: 0 | BI8: May | BJ8: 0 | BL8: 0 | BM8: 0 | BN8: 0 | BO8: 0 | BP8: 0 | BQ8: 0 | BR8: 0 | BS8: 0 | BU8: May | BV8: 0 | BX8: 0 | BY8: 0 | BZ8: 0 | CA8: 0 | CB8: 0 | CC8: 0 | CD8: 1 | CE8: 1 | CG8: May | CH8: 0 | CJ8: 0 | CK8: 0 | CL8: 0 | CM8: 0 | CN8: 0 | CO8: 0 | CP8: 0 | CQ8: 0 | CS8: May | CT8: 0 | CV8: 0 | CW8: 0 | CX8: 0 | CY8: 0 | CZ8: 0 | DA8: 0 | DB8: 0 | DC8: 0 | DE8: May | DF8: 0 | DH8: 0 | DI8: 0 | DJ8: 1 | DK8: 0 | DL8: 0 | DM8: 0 | DN8: 0 | DO8: 1 | DQ8: May | DR8: 0 | DT8: 0 | DU8: 0 | DV8: 0 | DW8: 0 | DX8: 0 | DY8: 0 | DZ8: 0 | EA8: 0 | EC8: May | ED8: 0 | EF8: 0 | EG8: 0 | EH8: 0 | EI8: 0 | EJ8: 0 | EK8: 0 | EL8: 0 | EM8: 0 | EO8: May | EP8: 0 | ER8: 0 | ES8: 0 | ET8: 0 | EU8: 0 | EV8: 0 | EW8: 0 | EX8: 0 | EY8: 0 | FA8: May | FB8: 0 | FD8: 0 | FE8: 0 | FF8: 0 | FG8: 0 | FH8: 0 | FI8: 0 | FJ8: 0 | FK8: 0 | FM8: May | FN8: 0 | FP8: 0 | FQ8: 0 | FR8: 0 | FS8: 0 | FT8: 0 | FU8: 0 | FV8: 0 | FW8: 0 | FY8: May | FZ8: 0 | GB8: 0 | GC8: 0 | GD8: 0 | GE8: 0 | GF8: 0 | GG8: 0 | GH8: 0 | GI8: 0 | GK8: May | GL8: 0 | GN8: 0 | GO8: 0 | GP8: 0 | GQ8: 0 | GR8: 0 | GS8: 0 | GT8: 0 | GU8: 0 | GW8: May | GX8: 0 | GZ8: 0 | HA8: 0 | HB8: 0 | HC8: 0 | HD8: 0 | HE8: 0 | HF8: 0 | HG8: 0 | HI8: May | HJ8: 0 | HL8: 0 | HM8: 0 | HN8: 0 | HO8: 0 | HP8: 0 | HQ8: 0 | HR8: 0 | HS8: 0
A9: Jun | B9: 0 | D9: 0 | E9: 0 | F9: 0 | G9: 0 | H9: 0 | I9: 0 | J9: 0 | M9: Jun | N9: 0 | P9: 0 | Q9: 0 | R9: 0 | S9: 0 | T9: 0 | U9: 0 | V9: 0 | Y9: Jun | Z9: 0 | AB9: 0 | AC9: 0 | AD9: 0 | AE9: 0 | AF9: 0 | AG9: 0 | AH9: 0 | AK9: Jun | AL9: 0 | AN9: 0 | AO9: 0 | AP9: 0 | AQ9: 0 | AR9: 0 | AS9: 0 | AT9: 0 | AW9: Jun | AX9: 0 | AZ9: 0 | BA9: 0 | BB9: 0 | BC9: 0 | BD9: 0 | BE9: 0 | BF9: 0 | BI9: Jun | BJ9: 0 | BL9: 0 | BM9: 0 | BN9: 0 | BO9: 0 | BP9: 0 | BQ9: 0 | BR9: 0 | BS9: 0 | BU9: Jun | BV9: 0 | BX9: 0 | BY9: 0 | BZ9: 0 | CA9: 0 | CB9: 0 | CC9: 0 | CD9: 0 | CE9: 0 | CG9: Jun | CH9: 0 | CJ9: 0 | CK9: 0 | CL9: 0 | CM9: 0 | CN9: 0 | CO9: 0 | CP9: 0 | CQ9: 0 | CS9: Jun | CT9: 0 | CV9: 0 | CW9: 0 | CX9: 0 | CY9: 0 | CZ9: 0 | DA9: 0 | DB9: 0 | DC9: 0 | DE9: Jun | DF9: 0 | DH9: 0 | DI9: 0 | DJ9: 0 | DK9: 0 | DL9: 0 | DM9: 0 | DN9: 0 | DO9: 0 | DQ9: Jun | DR9: 0 | DT9: 0 | DU9: 0 | DV9: 0 | DW9: 0 | DX9: 0 | DY9: 0 | DZ9: 0 | EA9: 0 | EC9: Jun | ED9: 0 | EF9: 0 | EG9: 0 | EH9: 0 | EI9: 0 | EJ9: 0 | EK9: 0 | EL9: 0 | EM9: 0 | EO9: Jun | EP9: 0 | ER9: 0 | ES9: 0 | ET9: 0 | EU9: 0 | EV9: 0 | EW9: 0 | EX9: 0 | EY9: 0 | FA9: Jun | FB9: 0 | FD9: 0 | FE9: 0 | FF9: 0 | FG9: 0 | FH9: 0 | FI9: 0 | FJ9: 0 | FK9: 0 | FM9: Jun | FN9: 0 | FP9: 0 | FQ9: 0 | FR9: 0 | FS9: 0 | FT9: 0 | FU9: 0 | FV9: 0 | FW9: 0 | FY9: Jun | FZ9: 0 | GB9: 0 | GC9: 0 | GD9: 0 | GE9: 0 | GF9: 0 | GG9: 0 | GH9: 0 | GI9: 0 | GK9: Jun | GL9: 0 | GN9: 0 | GO9: 0 | GP9: 0 | GQ9: 0 | GR9: 0 | GS9: 0 | GT9: 0 | GU9: 0 | GW9: Jun | GX9: 0 | GZ9: 0 | HA9: 0 | HB9: 0 | HC9: 0 | HD9: 0 | HE9: 0 | HF9: 0 | HG9: 0 | HI9: Jun | HJ9: 0 | HL9: 0 | HM9: 0 | HN9: 0 | HO9: 0 | HP9: 0 | HQ9: 0 | HR9: 0 | HS9: 0
A10: Jul | B10: 0 | D10: 0 | E10: 0 | F10: 0 | G10: 0 | H10: 0 | I10: 0 | J10: 0 | M10: Jul | N10: 0 | P10: 0 | Q10: 0 | R10: 0 | S10: 0 | T10: 0 | U10: 0 | V10: 0 | Y10: Jul | Z10: 0 | AB10: 0 | AC10: 0 | AD10: 0 | AE10: 0 | AF10: 0 | AG10: 0 | AH10: 0 | AK10: Jul | AL10: 0 | AN10: 0 | AO10: 0 | AP10: 0 | AQ10: 0 | AR10: 0 | AS10: 0 | AT10: 0 | AW10: Jul | AX10: 0 | AZ10: 0 | BA10: 0 | BB10: 0 | BC10: 0 | BD10: 0 | BE10: 0 | BF10: 0 | BI10: Jul | BJ10: 0 | BL10: 0 | BM10: 0 | BN10: 0 | BO10: 0 | BP10: 0 | BQ10: 0 | BR10: 0 | BS10: 0 | BU10: Jul | BV10: 0 | BX10: 0 | BY10: 0 | BZ10: 0 | CA10: 0 | CB10: 0 | CC10: 0 | CD10: 0 | CE10: 0 | CG10: Jul | CH10: 0 | CJ10: 0 | CK10: 0 | CL10: 0 | CM10: 0 | CN10: 0 | CO10: 0 | CP10: 0 | CQ10: 0 | CS10: Jul | CT10: 0 | CV10: 0 | CW10: 0 | CX10: 0 | CY10: 0 | CZ10: 0 | DA10: 0 | DB10: 0 | DC10: 0 | DE10: Jul | DF10: 0 | DH10: 0 | DI10: 0 | DJ10: 0 | DK10: 0 | DL10: 0 | DM10: 0 | DN10: 0 | DO10: 0 | DQ10: Jul | DR10: 0 | DT10: 0 | DU10: 0 | DV10: 0 | DW10: 0 | DX10: 1 | DY10: 0 | DZ10: 0 | EA10: 1 | EC10: Jul | ED10: 0 | EF10: 0 | EG10: 0 | EH10: 0 | EI10: 0 | EJ10: 0 | EK10: 0 | EL10: 1 | EM10: 1 | EO10: Jul | EP10: 0 | ER10: 0 | ES10: 0 | ET10: 0 | EU10: 0 | EV10: 0 | EW10: 0 | EX10: 0 | EY10: 0 | FA10: Jul | FB10: 0 | FD10: 0 | FE10: 0 | FF10: 0 | FG10: 0 | FH10: 0 | FI10: 0 | FJ10: 0 | FK10: 0 | FM10: Jul | FN10: 0 | FP10: 0 | FQ10: 0 | FR10: 0 | FS10: 0 | FT10: 0 | FU10: 0 | FV10: 0 | FW10: 0 | FY10: Jul | FZ10: 0 | GB10: 0 | GC10: 0 | GD10: 0 | GE10: 0 | GF10: 0 | GG10: 0 | GH10: 0 | GI10: 0 | GK10: Jul | GL10: 0 | GN10: 0 | GO10: 0 | GP10: 0 | GQ10: 0 | GR10: 0 | GS10: 0 | GT10: 0 | GU10: 0 | GW10: Jul | GX10: 0 | GZ10: 0 | HA10: 0 | HB10: 0 | HC10: 0 | HD10: 0 | HE10: 0 | HF10: 0 | HG10: 0 | HI10: Jul | HJ10: 0 | HL10: 0 | HM10: 0 | HN10: 0 | HO10: 0 | HP10: 0 | HQ10: 0 | HR10: 0 | HS10: 0
A11: Aug | B11: 0 | D11: 0 | E11: 0 | F11: 0 | G11: 0 | H11: 0 | I11: 0 | J11: 0 | M11: Aug | N11: 0 | P11: 0 | Q11: 0 | R11: 0 | S11: 0 | T11: 0 | U11: 0 | V11: 0 | Y11: Aug | Z11: 0 | AB11: 0 | AC11: 0 | AD11: 0 | AE11: 0 | AF11: 0 | AG11: 0 | AH11: 0 | AK11: Aug | AL11: 0 | AN11: 0 | AO11: 0 | AP11: 0 | AQ11: 0 | AR11: 0 | AS11: 0 | AT11: 0 | AW11: Aug | AX11: 0 | AZ11: 0 | BA11: 0 | BB11: 0 | BC11: 0 | BD11: 0 | BE11: 0 | BF11: 0 | BI11: Aug | BJ11: 0 | BL11: 0 | BM11: 0 | BN11: 0 | BO11: 0 | BP11: 0 | BQ11: 0 | BR11: 0 | BS11: 0 | BU11: Aug | BV11: 0 | BX11: 0 | BY11: 0 | BZ11: 0 | CA11: 0 | CB11: 0 | CC11: 0 | CD11: 0 | CE11: 0 | CG11: Aug | CH11: 0 | CJ11: 0 | CK11: 0 | CL11: 0 | CM11: 0 | CN11: 0 | CO11: 0 | CP11: 0 | CQ11: 0 | CS11: Aug | CT11: 0 | CV11: 0 | CW11: 0 | CX11: 0 | CY11: 0 | CZ11: 0 | DA11: 0 | DB11: 1 | DC11: 1 | DE11: Aug | DF11: 0 | DH11: 0 | DI11: 0 | DJ11: 0 | DK11: 0 | DL11: 0 | DM11: 0 | DN11: 0 | DO11: 0 | DQ11: Aug | DR11: 0 | DT11: 0 | DU11: 0 | DV11: 0 | DW11: 0 | DX11: 0 | DY11: 0 | DZ11: 0 | EA11: 0 | EC11: Aug | ED11: 0 | EF11: 0 | EG11: 0 | EH11: 0 | EI11: 0 | EJ11: 0 | EK11: 0 | EL11: 0 | EM11: 0 | EO11: Aug | EP11: 0 | ER11: 0 | ES11: 0 | ET11: 0 | EU11: 0 | EV11: 0 | EW11: 0 | EX11: 0 | EY11: 0 | FA11: Aug | FB11: 0 | FD11: 0 | FE11: 0 | FF11: 0 | FG11: 0 | FH11: 0 | FI11: 0 | FJ11: 0 | FK11: 0 | FM11: Aug | FN11: 0 | FP11: 0 | FQ11: 0 | FR11: 0 | FS11: 0 | FT11: 0 | FU11: 0 | FV11: 0 | FW11: 0 | FY11: Aug | FZ11: 0 | GB11: 0 | GC11: 0 | GD11: 0 | GE11: 0 | GF11: 0 | GG11: 0 | GH11: 0 | GI11: 0 | GK11: Aug | GL11: 0 | GN11: 0 | GO11: 0 | GP11: 0 | GQ11: 0 | GR11: 0 | GS11: 0 | GT11: 0 | GU11: 0 | GW11: Aug | GX11: 0 | GZ11: 0 | HA11: 0 | HB11: 0 | HC11: 0 | HD11: 0 | HE11: 0 | HF11: 0 | HG11: 0 | HI11: Aug | HJ11: 0 | HL11: 0 | HM11: 0 | HN11: 0 | HO11: 0 | HP11: 0 | HQ11: 0 | HR11: 0 | HS11: 0
A12: Sep | B12: 0 | D12: 0 | E12: 0 | F12: 0 | G12: 0 | H12: 0 | I12: 0 | J12: 0 | M12: Sep | N12: 0 | P12: 0 | Q12: 0 | R12: 0 | S12: 0 | T12: 0 | U12: 0 | V12: 0 | Y12: Sep | Z12: 0 | AB12: 0 | AC12: 0 | AD12: 0 | AE12: 0 | AF12: 0 | AG12: 0 | AH12: 0 | AK12: Sep | AL12: 0 | AN12: 0 | AO12: 0 | AP12: 0 | AQ12: 0 | AR12: 0 | AS12: 0 | AT12: 0 | AW12: Sep | AX12: 0 | AZ12: 0 | BA12: 0 | BB12: 0 | BC12: 0 | BD12: 0 | BE12: 0 | BF12: 0 | BI12: Sep | BJ12: 0 | BL12: 0 | BM12: 0 | BN12: 0 | BO12: 0 | BP12: 0 | BQ12: 0 | BR12: 0 | BS12: 0 | BU12: Sep | BV12: 0 | BX12: 0 | BY12: 0 | BZ12: 0 | CA12: 0 | CB12: 0 | CC12: 1 | CD12: 0 | CE12: 1 | CG12: Sep | CH12: 0 | CJ12: 0 | CK12: 0 | CL12: 0 | CM12: 0 | CN12: 0 | CO12: 0 | CP12: 0 | CQ12: 0 | CS12: Sep | CT12: 0 | CV12: 0 | CW12: 0 | CX12: 0 | CY12: 0 | CZ12: 0 | DA12: 0 | DB12: 0 | DC12: 0 | DE12: Sep | DF12: 0 | DH12: 0 | DI12: 0 | DJ12: 0 | DK12: 0 | DL12: 0 | DM12: 0 | DN12: 0 | DO12: 0 | DQ12: Sep | DR12: 0 | DT12: 0 | DU12: 0 | DV12: 0 | DW12: 0 | DX12: 0 | DY12: 0 | DZ12: 0 | EA12: 0 | EC12: Sep | ED12: 0 | EF12: 0 | EG12: 0 | EH12: 0 | EI12: 0 | EJ12: 0 | EK12: 0 | EL12: 0 | EM12: 0 | EO12: Sep | EP12: 0 | ER12: 0 | ES12: 0 | ET12: 0 | EU12: 0 | EV12: 0 | EW12: 0 | EX12: 0 | EY12: 0 | FA12: Sep | FB12: 0 | FD12: 0 | FE12: 0 | FF12: 0 | FG12: 0 | FH12: 0 | FI12: 0 | FJ12: 0 | FK12: 0 | FM12: Sep | FN12: 0 | FP12: 0 | FQ12: 0 | FR12: 0 | FS12: 0 | FT12: 0 | FU12: 0 | FV12: 0 | FW12: 0 | FY12: Sep | FZ12: 0 | GB12: 0 | GC12: 0 | GD12: 0 | GE12: 0 | GF12: 0 | GG12: 0 | GH12: 0 | GI12: 0 | GK12: Sep | GL12: 0 | GN12: 0 | GO12: 0 | GP12: 0 | GQ12: 0 | GR12: 0 | GS12: 0 | GT12: 0 | GU12: 0 | GW12: Sep | GX12: 0 | GZ12: 0 | HA12: 0 | HB12: 0 | HC12: 0 | HD12: 0 | HE12: 0 | HF12: 0 | HG12: 0 | HI12: Sep | HJ12: 0 | HL12: 0 | HM12: 0 | HN12: 0 | HO12: 0 | HP12: 0 | HQ12: 0 | HR12: 0 | HS12: 0
A13: Oct | B13: 0 | C13: 0 | D13: 0 | E13: 0 | F13: 0 | G13: 0 | H13: 0 | I13: 0 | J13: 0 | M13: Oct | N13: 0 | O13: 0 | P13: 0 | Q13: 0 | R13: 0 | S13: 0 | T13: 0 | U13: 0 | V13: 0 | Y13: Oct | Z13: 0 | AA13: 0 | AB13: 0 | AC13: 0 | AD13: 0 | AE13: 0 | AF13: 0 | AG13: 0 | AH13: 0 | AK13: Oct | AL13: 0 | AM13: 0 | AN13: 0 | AO13: 0 | AP13: 0 | AQ13: 0 | AR13: 0 | AS13: 0 | AT13: 0 | AW13: Oct | AX13: 0 | AY13: 2 | AZ13: 0 | BA13: 0 | BB13: 0 | BC13: 0 | BD13: 0 | BE13: 0 | BF13: 0 | BI13: Oct | BJ13: 0 | BK13: 0 | BL13: 0 | BM13: 0 | BN13: 0 | BO13: 0 | BP13: 0 | BQ13: 0 | BR13: 0 | BS13: 0 | BU13: Oct | BV13: 0 | BW13: 1 | BX13: 0 | BY13: 0 | BZ13: 0 | CA13: 0 | CB13: 0 | CC13: 0 | CD13: 0 | CE13: 1 | CG13: Oct | CH13: 0 | CI13: 0 | CJ13: 0 | CK13: 0 | CL13: 0 | CM13: 0 | CN13: 0 | CO13: 0 | CP13: 0 | CQ13: 0 | CS13: Oct | CT13: 0 | CU13: 0 | CV13: 0 | CW13: 0 | CX13: 0 | CY13: 0 | CZ13: 0 | DA13: 0 | DB13: 0 | DC13: 0 | DE13: Oct | DF13: 0 | DG13: 0 | DH13: 0 | DI13: 0 | DJ13: 0 | DK13: 0 | DL13: 0 | DM13: 0 | DN13: 0 | DO13: 0 | DQ13: Oct | DR13: 0 | DS13: 0 | DT13: 0 | DU13: 0 | DV13: 0 | DW13: 0 | DX13: 0 | DY13: 0 | DZ13: 0 | EA13: 0 | EC13: Oct | ED13: 0 | EE13: 0 | EF13: 0 | EG13: 0 | EH13: 0 | EI13: 0 | EJ13: 0 | EK13: 0 | EL13: 0 | EM13: 0 | EO13: Oct | EP13: 0 | EQ13: 2 | ER13: 0 | ES13: 0 | ET13: 0 | EU13: 0 | EV13: 0 | EW13: 0 | EX13: 0 | EY13: 2 | FA13: Oct | FB13: 0 | FC13: 0 | FD13: 0 | FE13: 0 | FF13: 0 | FG13: 0 | FH13: 0 | FI13: 0 | FJ13: 0 | FK13: 0 | FM13: Oct | FN13: 0 | FO13: 0 | FP13: 0 | FQ13: 0 | FR13: 0 | FS13: 1 | FT13: 0 | FU13: 0 | FV13: 0 | FW13: 1 | FY13: Oct | FZ13: 0 | GA13: 0 | GB13: 0 | GC13: 0 | GD13: 0 | GE13: 0 | GF13: 0 | GG13: 0 | GH13: 0 | GI13: 0 | GK13: Oct | GL13: 0 | GM13: 0 | GN13: 0 | GO13: 0 | GP13: 0 | GQ13: 0 | GR13: 0 | GS13: 0 | GT13: 0 | GU13: 0 | GW13: Oct | GX13: 0 | GY13: 0 | GZ13: 0 | HA13: 0 | HB13: 0 | HC13: 0 | HD13: 0 | HE13: 0 | HF13: 0 | HG13: 0 | HI13: Oct | HJ13: 0 | HK13: 0 | HL13: 0 | HM13: 0 | HN13: 0 | HO13: 0 | HP13: 0 | HQ13: 0 | HR13: 0 | HS13: 0
A14: Nov | B14: 0 | D14: 0 | E14: 0 | F14: 0 | G14: 0 | H14: 0 | I14: 1 | J14: 0 | M14: Nov | N14: 0 | P14: 0 | Q14: 0 | R14: 0 | S14: 0 | T14: 0 | U14: 0 | V14: 0 | Y14: Nov | Z14: 0 | AB14: 0 | AC14: 0 | AD14: 1 | AE14: 0 | AF14: 0 | AG14: 0 | AH14: 0 | AK14: Nov | AL14: 0 | AN14: 0 | AO14: 0 | AP14: 0 | AQ14: 0 | AR14: 0 | AS14: 0 | AT14: 0 | AW14: Nov | AX14: 0 | AZ14: 0 | BA14: 0 | BB14: 0 | BC14: 0 | BD14: 0 | BE14: 0 | BF14: 0 | BI14: Nov | BJ14: 0 | BL14: 0 | BM14: 0 | BN14: 0 | BO14: 0 | BP14: 0 | BQ14: 0 | BR14: 0 | BS14: 0 | BU14: Nov | BV14: 0 | BX14: 0 | BY14: 0 | BZ14: 0 | CA14: 0 | CB14: 0 | CC14: 0 | CD14: 0 | CE14: 0 | CG14: Nov | CH14: 0 | CJ14: 0 | CK14: 0 | CL14: 0 | CM14: 0 | CN14: 0 | CO14: 0 | CP14: 0 | CQ14: 0 | CS14: Nov | CT14: 0 | CV14: 0 | CW14: 0 | CX14: 0 | CY14: 0 | CZ14: 0 | DA14: 0 | DB14: 0 | DC14: 0 | DE14: Nov | DF14: 0 | DH14: 0 | DI14: 0 | DJ14: 0 | DK14: 0 | DL14: 0 | DM14: 0 | DN14: 0 | DO14: 0 | DQ14: Nov | DR14: 0 | DT14: 0 | DU14: 0 | DV14: 0 | DW14: 0 | DX14: 0 | DY14: 0 | DZ14: 0 | EA14: 0 | EC14: Nov | ED14: 0 | EF14: 1 | EG14: 0 | EH14: 0 | EI14: 0 | EJ14: 0 | EK14: 0 | EL14: 0 | EM14: 1 | EO14: Nov | EP14: 0 | ER14: 0 | ES14: 0 | ET14: 0 | EU14: 0 | EV14: 0 | EW14: 1 | EX14: 0 | EY14: 1 | FA14: Nov | FB14: 0 | FD14: 0 | FE14: 0 | FF14: 0 | FG14: 0 | FH14: 0 | FI14: 0 | FJ14: 0 | FK14: 0 | FM14: Nov | FN14: 0 | FP14: 0 | FQ14: 0 | FR14: 0 | FS14: 0 | FT14: 0 | FU14: 0 | FV14: 0 | FW14: 0 | FY14: Nov | FZ14: 0 | GB14: 0 | GC14: 0 | GD14: 0 | GE14: 0 | GF14: 0 | GG14: 0 | GH14: 0 | GI14: 0 | GK14: Nov | GL14: 0 | GN14: 0 | GO14: 0 | GP14: 0 | GQ14: 0 | GR14: 0 | GS14: 0 | GT14: 0 | GU14: 0 | GW14: Nov | GX14: 0 | GZ14: 0 | HA14: 0 | HB14: 0 | HC14: 0 | HD14: 0 | HE14: 0 | HF14: 0 | HG14: 0 | HI14: Nov | HJ14: 0 | HL14: 0 | HM14: 0 | HN14: 0 | HO14: 0 | HP14: 0 | HQ14: 0 | HR14: 0 | HS14: 0
A15: Dec | B15: 0 | D15: 0 | E15: 0 | F15: 0 | G15: 0 | H15: 0 | I15: 0 | J15: 0 | M15: Dec | N15: 0 | P15: 0 | Q15: 0 | R15: 0 | S15: 0 | T15: 0 | U15: 0 | V15: 0 | Y15: Dec | Z15: 0 | AB15: 0 | AC15: 0 | AD15: 0 | AE15: 0 | AF15: 0 | AG15: 0 | AH15: 0 | AK15: Dec | AL15: 0 | AN15: 0 | AO15: 0 | AP15: 0 | AQ15: 0 | AR15: 0 | AS15: 0 | AT15: 0 | AW15: Dec | AX15: 0 | AZ15: 0 | BA15: 0 | BB15: 0 | BC15: 0 | BD15: 1 | BE15: 0 | BF15: 0 | BI15: Dec | BJ15: 0 | BL15: 0 | BM15: 0 | BN15: 0 | BO15: 0 | BP15: 0 | BQ15: 0 | BR15: 0 | BS15: 0 | BU15: Dec | BV15: 0 | BX15: 0 | BY15: 0 | BZ15: 0 | CA15: 0 | CB15: 0 | CC15: 0 | CD15: 0 | CE15: 0 | CG15: Dec | CH15: 0 | CJ15: 0 | CK15: 0 | CL15: 0 | CM15: 0 | CN15: 0 | CO15: 0 | CP15: 0 | CQ15: 0 | CS15: Dec | CT15: 0 | CV15: 0 | CW15: 0 | CX15: 0 | CY15: 0 | CZ15: 0 | DA15: 0 | DB15: 0 | DC15: 0 | DE15: Dec | DF15: 0 | DH15: 0 | DI15: 0 | DJ15: 0 | DK15: 0 | DL15: 0 | DM15: 0 | DN15: 0 | DO15: 0 | DQ15: Dec | DR15: 0 | DT15: 0 | DU15: 0 | DV15: 0 | DW15: 0 | DX15: 0 | DY15: 0 | DZ15: 0 | EA15: 0 | EC15: Dec | ED15: 0 | EF15: 0 | EG15: 0 | EH15: 0 | EI15: 0 | EJ15: 0 | EK15: 0 | EL15: 0 | EM15: 0 | EO15: Dec | EP15: 0 | ER15: 0 | ES15: 0 | ET15: 0 | EU15: 0 | EV15: 0 | EW15: 0 | EX15: 0 | EY15: 0 | FA15: Dec | FB15: 0 | FD15: 0 | FE15: 0 | FF15: 0 | FG15: 0 | FH15: 0 | FI15: 0 | FJ15: 0 | FK15: 0 | FM15: Dec | FN15: 0 | FP15: 0 | FQ15: 0 | FR15: 0 | FS15: 0 | FT15: 0 | FU15: 0 | FV15: 0 | FW15: 0 | FY15: Dec | FZ15: 0 | GB15: 0 | GC15: 0 | GD15: 0 | GE15: 0 | GF15: 0 | GG15: 0 | GH15: 0 | GI15: 0 | GK15: Dec | GL15: 0 | GN15: 0 | GO15: 0 | GP15: 0 | GQ15: 0 | GR15: 0 | GS15: 0 | GT15: 0 | GU15: 0 | GW15: Dec | GX15: 0 | GZ15: 0 | HA15: 0 | HB15: 0 | HC15: 0 | HD15: 0 | HE15: 0 | HF15: 0 | HG15: 0 | HI15: Dec | HJ15: 0 | HL15: 0 | HM15: 0 | HN15: 0 | HO15: 0 | HP15: 0 | HQ15: 0 | HR15: 0 | HS15: 0
A16: Jan | B16: 0 | D16: 0 | E16: 0 | F16: 0 | G16: 0 | H16: 0 | I16: 0 | J16: 0 | M16: Jan | N16: 0 | P16: 0 | Q16: 0 | R16: 0 | S16: 0 | T16: 0 | U16: 0 | V16: 0 | Y16: Jan | Z16: 0 | AB16: 0 | AC16: 0 | AD16: 0 | AE16: 0 | AF16: 0 | AG16: 0 | AH16: 0 | AK16: Jan | AL16: 0 | AN16: 0 | AO16: 0 | AP16: 0 | AQ16: 0 | AR16: 0 | AS16: 0 | AT16: 0 | AW16: Jan | AX16: 0 | AZ16: 0 | BA16: 0 | BB16: 0 | BC16: 0 | BD16: 0 | BE16: 0 | BF16: 0 | BI16: Jan | BJ16: 0 | BL16: 0 | BM16: 0 | BN16: 0 | BO16: 0 | BP16: 0 | BQ16: 0 | BR16: 0 | BS16: 0 | BU16: Jan | BV16: 0 | BX16: 0 | BY16: 0 | BZ16: 0 | CA16: 0 | CB16: 0 | CC16: 0 | CD16: 0 | CE16: 0 | CG16: Jan | CH16: 0 | CJ16: 0 | CK16: 0 | CL16: 0 | CM16: 0 | CN16: 0 | CO16: 0 | CP16: 0 | CQ16: 0 | CS16: Jan | CT16: 0 | CV16: 0 | CW16: 0 | CX16: 0 | CY16: 0 | CZ16: 0 | DA16: 0 | DB16: 0 | DC16: 0 | DE16: Jan | DF16: 0 | DH16: 0 | DI16: 0 | DJ16: 0 | DK16: 0 | DL16: 0 | DM16: 0 | DN16: 0 | DO16: 0 | DQ16: Jan | DR16: 0 | DT16: 0 | DU16: 0 | DV16: 0 | DW16: 0 | DX16: 0 | DY16: 0 | DZ16: 0 | EA16: 0 | EC16: Jan | ED16: 0 | EF16: 0 | EG16: 0 | EH16: 0 | EI16: 0 | EJ16: 0 | EK16: 0 | EL16: 0 | EM16: 0 | EO16: Jan | EP16: 0 | ER16: 0 | ES16: 0 | ET16: 0 | EU16: 0 | EV16: 0 | EW16: 0 | EX16: 0 | EY16: 0 | FA16: Jan | FB16: 0 | FD16: 0 | FE16: 0 | FF16: 0 | FG16: 0 | FH16: 0 | FI16: 0 | FJ16: 0 | FK16: 0 | FM16: Jan | FN16: 0 | FP16: 0 | FQ16: 1 | FR16: 0 | FS16: 0 | FT16: 0 | FU16: 0 | FV16: 0 | FW16: 1 | FY16: Jan | FZ16: 0 | GB16: 0 | GC16: 0 | GD16: 0 | GE16: 0 | GF16: 0 | GG16: 0 | GH16: 0 | GI16: 0 | GK16: Jan | GL16: 0 | GN16: 0 | GO16: 0 | GP16: 0 | GQ16: 0 | GR16: 0 | GS16: 0 | GT16: 0 | GU16: 0 | GW16: Jan | GX16: 0 | GZ16: 0 | HA16: 0 | HB16: 0 | HC16: 0 | HD16: 0 | HE16: 0 | HF16: 0 | HG16: 0 | HI16: Jan | HJ16: 0 | HL16: 0 | HM16: 0 | HN16: 0 | HO16: 0 | HP16: 0 | HQ16: 0 | HR16: 0 | HS16: 0
A17: Feb | B17: 0 | D17: 0 | E17: 0 | F17: 0 | G17: 0 | H17: 0 | I17: 0 | J17: 0 | M17: Feb | N17: 0 | P17: 0 | Q17: 0 | R17: 0 | S17: 0 | T17: 0 | U17: 0 | V17: 0 | Y17: Feb | Z17: 0 | AB17: 0 | AC17: 0 | AD17: 0 | AE17: 0 | AF17: 0 | AG17: 0 | AH17: 0 | AK17: Feb | AL17: 0 | AN17: 0 | AO17: 0 | AP17: 0 | AQ17: 0 | AR17: 0 | AS17: 0 | AT17: 0 | AW17: Feb | AX17: 0 | AZ17: 0 | BA17: 0 | BB17: 0 | BC17: 0 | BD17: 0 | BE17: 0 | BF17: 0 | BI17: Feb | BJ17: 0 | BL17: 0 | BM17: 0 | BN17: 0 | BO17: 0 | BP17: 0 | BQ17: 0 | BR17: 0 | BS17: 0 | BU17: Feb | BV17: 0 | BX17: 0 | BY17: 0 | BZ17: 0 | CA17: 0 | CB17: 0 | CC17: 0 | CD17: 0 | CE17: 0 | CG17: Feb | CH17: 0 | CJ17: 0 | CK17: 0 | CL17: 0 | CM17: 0 | CN17: 0 | CO17: 0 | CP17: 0 | CQ17: 0 | CS17: Feb | CT17: 0 | CV17: 0 | CW17: 0 | CX17: 0 | CY17: 0 | CZ17: 0 | DA17: 0 | DB17: 0 | DC17: 0 | DE17: Feb | DF17: 0 | DH17: 0 | DI17: 0 | DJ17: 0 | DK17: 0 | DL17: 0 | DM17: 0 | DN17: 0 | DO17: 0 | DQ17: Feb | DR17: 0 | DT17: 0 | DU17: 0 | DV17: 0 | DW17: 0 | DX17: 0 | DY17: 0 | DZ17: 0 | EA17: 0 | EC17: Feb | ED17: 0 | EF17: 0 | EG17: 0 | EH17: 0 | EI17: 0 | EJ17: 0 | EK17: 0 | EL17: 0 | EM17: 0 | EO17: Feb | EP17: 0 | ER17: 0 | ES17: 0 | ET17: 0 | EU17: 0 | EV17: 0 | EW17: 0 | EX17: 1 | EY17: 1 | FA17: Feb | FB17: 0 | FD17: 0 | FE17: 0 | FF17: 0 | FG17: 0 | FH17: 0 | FI17: 0 | FJ17: 0 | FK17: 0 | FM17: Feb | FN17: 0 | FP17: 0 | FQ17: 0 | FR17: 0 | FS17: 0 | FT17: 0 | FU17: 0 | FV17: 0 | FW17: 0 | FY17: Feb | FZ17: 0 | GB17: 0 | GC17: 0 | GD17: 0 | GE17: 0 | GF17: 0 | GG17: 0 | GH17: 0 | GI17: 0 | GK17: Feb | GL17: 0 | GN17: 0 | GO17: 0 | GP17: 0 | GQ17: 0 | GR17: 0 | GS17: 0 | GT17: 0 | GU17: 0 | GW17: Feb | GX17: 0 | GZ17: 0 | HA17: 0 | HB17: 0 | HC17: 0 | HD17: 0 | HE17: 0 | HF17: 0 | HG17: 0 | HI17: Feb | HJ17: 0 | HL17: 0 | HM17: 0 | HN17: 0 | HO17: 0 | HP17: 0 | HQ17: 0 | HR17: 0 | HS17: 0
A18: Mar | M18: Mar | Y18: Mar | AK18: Mar | AW18: Mar | BI18: Mar | BU18: Mar | CG18: Mar | CS18: Mar | DE18: Mar | DQ18: Mar | EC18: Mar | EO18: Mar | FA18: Mar | FM18: Mar | FY18: Mar | GK18: Mar | GW18: Mar | HI18: Mar
BI19: Grand Total | BJ19: 0 | BK19: 0 | BL19: 0 | BM19: 0 | BN19: 0 | BO19: 0 | BP19: 0 | BQ19: 0 | BR19: 0 | BS19: 0 | BU19: Grand Total | BV19: 0 | BW19: 1 | BX19: 0 | BY19: 0 | BZ19: 0 | CA19: 0 | CB19: 0 | CC19: 1 | CD19: 1 | CE19: 3 | CG19: Grand Total | CH19: 0 | CI19: 0 | CJ19: 0 | CK19: 0 | CL19: 0 | CM19: 0 | CN19: 0 | CO19: 0 | CP19: 0 | CQ19: 0 | CS19: Grand Total | CT19: 0 | CU19: 0 | CV19: 0 | CW19: 0 | CX19: 0 | CY19: 0 | CZ19: 0 | DA19: 0 | DB19: 1 | DC19: 1 | DE19: Grand Total | DF19: 0 | DG19: 0 | DH19: 0 | DI19: 0 | DJ19: 1 | DK19: 0 | DL19: 0 | DM19: 0 | DN19: 0 | DO19: 1 | DQ19: Grand Total | DR19: 0 | DS19: 0 | DT19: 0 | DU19: 0 | DV19: 0 | DW19: 0 | DX19: 1 | DY19: 0 | DZ19: 0 | EA19: 1 | EC19: Grand Total | ED19: 0 | EE19: 0 | EF19: 1 | EG19: 0 | EH19: 0 | EI19: 0 | EJ19: 0 | EK19: 0 | EL19: 1 | EM19: 2 | EO19: Grand Total | EP19: 0 | EQ19: 2 | ER19: 0 | ES19: 0 | ET19: 0 | EU19: 0 | EV19: 0 | EW19: 1 | EX19: 1 | EY19: 4 | FA19: Grand Total | FB19: 0 | FC19: 0 | FD19: 0 | FE19: 0 | FF19: 0 | FG19: 0 | FH19: 0 | FI19: 0 | FJ19: 0 | FK19: 0 | FM19: Grand Total | FN19: 0 | FO19: 0 | FP19: 0 | FQ19: 1 | FR19: 0 | FS19: 1 | FT19: 0 | FU19: 0 | FV19: 0 | FW19: 2 | FY19: Grand Total | FZ19: 0 | GA19: 0 | GB19: 0 | GC19: 0 | GD19: 0 | GE19: 0 | GF19: 0 | GG19: 0 | GH19: 0 | GI19: 0 | GK19: Grand Total | GL19: 0 | GM19: 0 | GN19: 0 | GO19: 0 | GP19: 0 | GQ19: 0 | GR19: 0 | GS19: 0 | GT19: 0 | GU19: 0 | GW19: Grand Total | GX19: 0 | GY19: 0 | GZ19: 0 | HA19: 0 | HB19: 0 | HC19: 0 | HD19: 0 | HE19: 0 | HF19: 0 | HG19: 0 | HI19: Grand Total | HJ19: 0 | HK19: 0 | HL19: 0 | HM19: 0 | HN19: 0 | HO19: 0 | HP19: 0 | HQ19: 0 | HR19: 0 | HS19: 0
A22: Quality
A26: Quality
A28: Sub | B28: Claim | M28: Sub | N28: Claim | Y28: Sub | Z28: Claim | AK28: Sub | AL28: Claim | AW28: Sub | AX28: Claim | BI28: Sub | BJ28: Claim | BU28: Sub | BV28: Claim | CG28: Sub | CH28: Claim | CS28: Sub | CT28: Claim | DE28: Sub | DF28: Claim
A30: Pump/M | B30: Column Labels | M30: Pump/A | N30: Column Labels | Y30: INJ/M | Z30: Column Labels | AK30: INJ/A | AL30: Column Labels | AW30: Vavle | AX30: Column Labels | BI30: SOL | BJ30: Column Labels | BU30: UC/M | BV30: Column Labels | CG30: UC/A | CH30: Column Labels | CS30: GDP | CT30: Column Labels | DE30: SIFS/DF | DF30: Column Labels
B31: Case | N31: Case | Z31: Case | AL31: Case | AX31: Case | BJ31: Case | BV31: Case | CH31: Case | CT31: Case | DF31: Case
A32: Row Labels | B32: 0-km claim (All DN response) | C32: 0-km claim (Official) | D32: Critical claim | E32: Internal NCR | F32: OGC claim | G32: Supplier NCR | H32: Market claim | M32: Row Labels | N32: 0-km claim (All DN response) | O32: 0-km claim (Official) | P32: Critical claim | Q32: Internal NCR | R32: OGC claim | S32: Supplier NCR | T32: Market claim | Y32: Row Labels | Z32: 0-km claim (All DN response) | AA32: 0-km claim (Official) | AB32: Critical claim | AC32: Internal NCR | AD32: OGC claim | AE32: Supplier NCR | AF32: Market claim | AK32: Row Labels | AL32: 0-km claim (All DN response) | AM32: 0-km claim (Official) | AN32: Critical claim | AO32: Internal NCR | AP32: OGC claim | AQ32: Supplier NCR | AR32: Market claim | AW32: Row Labels | AX32: 0-km claim (All DN response) | AY32: 0-km claim (Official) | AZ32: Critical claim | BA32: Internal NCR | BB32: OGC claim | BC32: Supplier NCR | BD32: Market claim | BI32: Row Labels | BJ32: 0-km claim (All DN response) | BK32: 0-km claim (Official) | BL32: Critical claim | BM32: Internal NCR | BN32: OGC claim | BO32: Supplier NCR | BP32: Market claim | BU32: Row Labels | BV32: 0-km claim (All DN response) | BW32: 0-km claim (Official) | BX32: Critical claim | BY32: Internal NCR | BZ32: OGC claim | CA32: Supplier NCR | CB32: Market claim | CG32: Row Labels | CH32: 0-km claim (All DN response) | CI32: 0-km claim (Official) | CJ32: Critical claim | CK32: Internal NCR | CL32: OGC claim | CM32: Supplier NCR | CN32: Market claim | CS32: Row Labels | CT32: 0-km claim (All DN response) | CU32: 0-km claim (Official) | CV32: Critical claim | CW32: Internal NCR | CX32: OGC claim | CY32: Supplier NCR | CZ32: Market claim | DE32: Row Labels | DF32: 0-km claim (All DN response) | DG32: 0-km claim (Official) | DH32: Critical claim | DI32: Internal NCR | DJ32: OGC claim | DK32: Supplier NCR | DL32: Market claim
A33: Apr | B33: 0 | C33: 0 | D33: 0 | E33: 0 | F33: 1 | G33: 1 | H33: 0 | M33: Apr | N33: 0 | O33: 0 | P33: 0 | Q33: 0 | R33: 0 | S33: 0 | T33: 0 | Y33: Apr | Z33: 0 | AA33: 0 | AB33: 0 | AC33: 0 | AD33: 0 | AE33: 0 | AF33: 0 | AK33: Apr | AL33: 0 | AM33: 0 | AN33: 0 | AO33: 0 | AP33: 0 | AQ33: 0 | AR33: 0 | AW33: Apr | AX33: 0 | AY33: 0 | AZ33: 0 | BA33: 0 | BB33: 0 | BC33: 0 | BD33: 0 | BI33: Apr | BJ33: 0 | BK33: 0 | BL33: 0 | BM33: 0 | BN33: 0 | BO33: 0 | BP33: 0 | BU33: Apr | BV33: 0 | BW33: 0 | BX33: 0 | BY33: 0 | BZ33: 0 | CA33: 0 | CB33: 0 | CG33: Apr | CH33: 0 | CI33: 0 | CJ33: 0 | CK33: 0 | CL33: 0 | CM33: 0 | CN33: 0 | CS33: Apr | CT33: 0 | CU33: 0 | CV33: 0 | CW33: 0 | CX33: 0 | CY33: 0 | CZ33: 0 | DE33: Apr | DF33: 0 | DG33: 0 | DH33: 0 | DI33: 0 | DJ33: 0 | DK33: 0 | DL33: 0
A34: May | B34: 0 | C34: 0 | D34: 0 | E34: 0 | F34: 0 | G34: 0 | H34: 0 | M34: May | N34: 0 | O34: 0 | P34: 0 | Q34: 0 | R34: 0 | S34: 0 | T34: 1 | Y34: May | Z34: 0 | AA34: 0 | AB34: 0 | AC34: 0 | AD34: 0 | AE34: 0 | AF34: 0 | AK34: May | AL34: 0 | AM34: 0 | AN34: 0 | AO34: 0 | AP34: 0 | AQ34: 0 | AR34: 0 | AW34: May | AX34: 0 | AY34: 0 | AZ34: 0 | BA34: 0 | BB34: 0 | BC34: 0 | BD34: 0 | BI34: May | BJ34: 0 | BK34: 0 | BL34: 0 | BM34: 0 | BN34: 0 | BO34: 0 | BP34: 0 | BU34: May | BV34: 0 | BW34: 0 | BX34: 0 | BY34: 0 | BZ34: 0 | CA34: 0 | CB34: 0 | CG34: May | CH34: 0 | CI34: 0 | CJ34: 0 | CK34: 0 | CL34: 0 | CM34: 0 | CN34: 0 | CS34: May | CT34: 0 | CU34: 0 | CV34: 0 | CW34: 0 | CX34: 0 | CY34: 0 | CZ34: 0 | DE34: May | DF34: 0 | DG34: 0 | DH34: 0 | DI34: 0 | DJ34: 0 | DK34: 0 | DL34: 0
A35: Jun | B35: 0 | C35: 0 | D35: 0 | E35: 0 | F35: 0 | G35: 0 | H35: 0 | M35: Jun | N35: 0 | O35: 0 | P35: 0 | Q35: 0 | R35: 0 | S35: 0 | T35: 4 | Y35: Jun | Z35: 0 | AA35: 0 | AB35: 0 | AC35: 0 | AD35: 0 | AE35: 0 | AF35: 0 | AK35: Jun | AL35: 0 | AM35: 0 | AN35: 0 | AO35: 0 | AP35: 0 | AQ35: 0 | AR35: 0 | AW35: Jun | AX35: 0 | AY35: 0 | AZ35: 0 | BA35: 0 | BB35: 0 | BC35: 0 | BD35: 0 | BI35: Jun | BJ35: 0 | BK35: 0 | BL35: 0 | BM35: 0 | BN35: 0 | BO35: 0 | BP35: 0 | BU35: Jun | BV35: 0 | BW35: 0 | BX35: 0 | BY35: 0 | BZ35: 2 | CA35: 1 | CB35: 0 | CG35: Jun | CH35: 0 | CI35: 0 | CJ35: 0 | CK35: 0 | CL35: 0 | CM35: 0 | CN35: 0 | CS35: Jun | CT35: 0 | CU35: 0 | CV35: 0 | CW35: 0 | CX35: 0 | CY35: 0 | CZ35: 0 | DE35: Jun | DF35: 0 | DG35: 0 | DH35: 0 | DI35: 0 | DJ35: 0 | DK35: 0 | DL35: 0
A36: Jul | B36: 0 | C36: 0 | D36: 0 | E36: 0 | F36: 0 | G36: 0 | H36: 0 | M36: Jul | N36: 0 | O36: 0 | P36: 0 | Q36: 0 | R36: 0 | S36: 0 | T36: 0 | Y36: Jul | Z36: 0 | AA36: 0 | AB36: 0 | AC36: 0 | AD36: 0 | AE36: 0 | AF36: 0 | AK36: Jul | AL36: 1 | AM36: 1 | AN36: 0 | AO36: 0 | AP36: 0 | AQ36: 0 | AR36: 0 | AW36: Jul | AX36: 0 | AY36: 0 | AZ36: 0 | BA36: 0 | BB36: 0 | BC36: 0 | BD36: 0 | BI36: Jul | BJ36: 0 | BK36: 0 | BL36: 0 | BM36: 0 | BN36: 0 | BO36: 0 | BP36: 0 | BU36: Jul | BV36: 0 | BW36: 0 | BX36: 0 | BY36: 0 | BZ36: 0 | CA36: 0 | CB36: 0 | CG36: Jul | CH36: 0 | CI36: 0 | CJ36: 0 | CK36: 0 | CL36: 0 | CM36: 0 | CN36: 0 | CS36: Jul | CT36: 0 | CU36: 0 | CV36: 0 | CW36: 0 | CX36: 0 | CY36: 0 | CZ36: 0 | DE36: Jul | DF36: 0 | DG36: 0 | DH36: 0 | DI36: 0 | DJ36: 0 | DK36: 0 | DL36: 0
A37: Aug | B37: 0 | C37: 0 | D37: 0 | E37: 0 | F37: 0 | G37: 0 | H37: 0 | M37: Aug | N37: 1 | O37: 0 | P37: 0 | Q37: 0 | R37: 0 | S37: 0 | T37: 1 | Y37: Aug | Z37: 0 | AA37: 0 | AB37: 0 | AC37: 0 | AD37: 0 | AE37: 0 | AF37: 0 | AK37: Aug | AL37: 1 | AM37: 1 | AN37: 0 | AO37: 0 | AP37: 0 | AQ37: 1 | AR37: 0 | AW37: Aug | AX37: 0 | AY37: 0 | AZ37: 0 | BA37: 0 | BB37: 0 | BC37: 0 | BD37: 0 | BI37: Aug | BJ37: 0 | BK37: 0 | BL37: 0 | BM37: 0 | BN37: 0 | BO37: 0 | BP37: 0 | BU37: Aug | BV37: 0 | BW37: 0 | BX37: 0 | BY37: 0 | BZ37: 1 | CA37: 1 | CB37: 0 | CG37: Aug | CH37: 0 | CI37: 0 | CJ37: 0 | CK37: 0 | CL37: 0 | CM37: 0 | CN37: 0 | CS37: Aug | CT37: 0 | CU37: 0 | CV37: 0 | CW37: 0 | CX37: 0 | CY37: 1 | CZ37: 0 | DE37: Aug | DF37: 0 | DG37: 0 | DH37: 0 | DI37: 0 | DJ37: 0 | DK37: 1 | DL37: 0
A38: Sep | B38: 0 | C38: 0 | D38: 0 | E38: 0 | F38: 1 | G38: 0 | H38: 0 | M38: Sep | N38: 0 | O38: 0 | P38: 0 | Q38: 0 | R38: 0 | S38: 0 | T38: 0 | Y38: Sep | Z38: 0 | AA38: 0 | AB38: 0 | AC38: 0 | AD38: 0 | AE38: 0 | AF38: 0 | AK38: Sep | AL38: 0 | AM38: 0 | AN38: 0 | AO38: 0 | AP38: 0 | AQ38: 0 | AR38: 0 | AW38: Sep | AX38: 0 | AY38: 0 | AZ38: 0 | BA38: 0 | BB38: 0 | BC38: 0 | BD38: 0 | BI38: Sep | BJ38: 0 | BK38: 0 | BL38: 0 | BM38: 0 | BN38: 0 | BO38: 0 | BP38: 0 | BU38: Sep | BV38: 0 | BW38: 0 | BX38: 0 | BY38: 0 | BZ38: 1 | CA38: 0 | CB38: 0 | CG38: Sep | CH38: 0 | CI38: 0 | CJ38: 0 | CK38: 0 | CL38: 0 | CM38: 0 | CN38: 0 | CS38: Sep | CT38: 0 | CU38: 0 | CV38: 0 | CW38: 0 | CX38: 0 | CY38: 0 | CZ38: 0 | DE38: Sep | DF38: 0 | DG38: 0 | DH38: 0 | DI38: 0 | DJ38: 0 | DK38: 0 | DL38: 0
A39: Oct | B39: 0 | C39: 0 | D39: 0 | E39: 0 | F39: 0 | G39: 0 | H39: 0 | M39: Oct | N39: 0 | O39: 0 | P39: 0 | Q39: 0 | R39: 0 | S39: 0 | T39: 0 | Y39: Oct | Z39: 0 | AA39: 0 | AB39: 0 | AC39: 0 | AD39: 1 | AE39: 0 | AF39: 0 | AK39: Oct | AL39: 1 | AM39: 0 | AN39: 0 | AO39: 0 | AP39: 0 | AQ39: 0 | AR39: 0 | AW39: Oct | AX39: 0 | AY39: 0 | AZ39: 0 | BA39: 0 | BB39: 0 | BC39: 0 | BD39: 0 | BI39: Oct | BJ39: 0 | BK39: 0 | BL39: 0 | BM39: 0 | BN39: 0 | BO39: 0 | BP39: 0 | BU39: Oct | BV39: 0 | BW39: 0 | BX39: 0 | BY39: 0 | BZ39: 0 | CA39: 0 | CB39: 0 | CG39: Oct | CH39: 0 | CI39: 0 | CJ39: 0 | CK39: 0 | CL39: 0 | CM39: 0 | CN39: 0 | CS39: Oct | CT39: 0 | CU39: 0 | CV39: 0 | CW39: 0 | CX39: 0 | CY39: 0 | CZ39: 0 | DE39: Oct | DF39: 0 | DG39: 0 | DH39: 0 | DI39: 0 | DJ39: 0 | DK39: 0 | DL39: 0
A40: Nov | B40: 0 | C40: 0 | D40: 0 | E40: 0 | F40: 0 | G40: 0 | H40: 0 | M40: Nov | N40: 0 | O40: 0 | P40: 0 | Q40: 0 | R40: 0 | S40: 0 | T40: 0 | Y40: Nov | Z40: 0 | AA40: 0 | AB40: 0 | AC40: 0 | AD40: 0 | AE40: 2 | AF40: 0 | AK40: Nov | AL40: 2 | AM40: 1 | AN40: 0 | AO40: 0 | AP40: 0 | AQ40: 0 | AR40: 0 | AW40: Nov | AX40: 0 | AY40: 0 | AZ40: 0 | BA40: 0 | BB40: 0 | BC40: 0 | BD40: 0 | BI40: Nov | BJ40: 0 | BK40: 0 | BL40: 0 | BM40: 0 | BN40: 1 | BO40: 0 | BP40: 0 | BU40: Nov | BV40: 0 | BW40: 0 | BX40: 0 | BY40: 0 | BZ40: 1 | CA40: 0 | CB40: 0 | CG40: Nov | CH40: 0 | CI40: 0 | CJ40: 0 | CK40: 0 | CL40: 0 | CM40: 0 | CN40: 0 | CS40: Nov | CT40: 0 | CU40: 0 | CV40: 0 | CW40: 0 | CX40: 0 | CY40: 0 | CZ40: 0 | DE40: Nov | DF40: 0 | DG40: 0 | DH40: 0 | DI40: 0 | DJ40: 0 | DK40: 0 | DL40: 0
A41: Dec | B41: 0 | C41: 0 | D41: 0 | E41: 0 | F41: 0 | G41: 0 | H41: 0 | M41: Dec | N41: 0 | O41: 0 | P41: 0 | Q41: 0 | R41: 1 | S41: 1 | T41: 0 | Y41: Dec | Z41: 0 | AA41: 0 | AB41: 0 | AC41: 0 | AD41: 0 | AE41: 1 | AF41: 0 | AK41: Dec | AL41: 0 | AM41: 0 | AN41: 0 | AO41: 0 | AP41: 0 | AQ41: 0 | AR41: 0 | AW41: Dec | AX41: 0 | AY41: 0 | AZ41: 0 | BA41: 0 | BB41: 0 | BC41: 0 | BD41: 0 | BI41: Dec | BJ41: 0 | BK41: 0 | BL41: 0 | BM41: 0 | BN41: 0 | BO41: 0 | BP41: 0 | BU41: Dec | BV41: 0 | BW41: 0 | BX41: 0 | BY41: 0 | BZ41: 1 | CA41: 0 | CB41: 0 | CG41: Dec | CH41: 0 | CI41: 0 | CJ41: 0 | CK41: 0 | CL41: 0 | CM41: 0 | CN41: 0 | CS41: Dec | CT41: 0 | CU41: 0 | CV41: 0 | CW41: 0 | CX41: 0 | CY41: 0 | CZ41: 0 | DE41: Dec | DF41: 0 | DG41: 0 | DH41: 0 | DI41: 0 | DJ41: 0 | DK41: 0 | DL41: 0
A42: Jan | B42: 0 | C42: 0 | D42: 0 | E42: 0 | F42: 1 | G42: 1 | H42: 0 | M42: Jan | N42: 1 | O42: 0 | P42: 0 | Q42: 0 | R42: 0 | S42: 0 | T42: 0 | Y42: Jan | Z42: 0 | AA42: 0 | AB42: 0 | AC42: 0 | AD42: 2 | AE42: 2 | AF42: 0 | AK42: Jan | AL42: 0 | AM42: 1 | AN42: 0 | AO42: 1 | AP42: 0 | AQ42: 0 | AR42: 0 | AW42: Jan | AX42: 0 | AY42: 0 | AZ42: 0 | BA42: 0 | BB42: 0 | BC42: 0 | BD42: 0 | BI42: Jan | BJ42: 0 | BK42: 0 | BL42: 0 | BM42: 0 | BN42: 1 | BO42: 0 | BP42: 0 | BU42: Jan | BV42: 0 | BW42: 0 | BX42: 0 | BY42: 0 | BZ42: 0 | CA42: 0 | CB42: 0 | CG42: Jan | CH42: 0 | CI42: 0 | CJ42: 0 | CK42: 0 | CL42: 1 | CM42: 0 | CN42: 0 | CS42: Jan | CT42: 1 | CU42: 0 | CV42: 0 | CW42: 0 | CX42: 0 | CY42: 0 | CZ42: 0 | DE42: Jan | DF42: 0 | DG42: 0 | DH42: 0 | DI42: 0 | DJ42: 0 | DK42: 0 | DL42: 0
A43: Feb | B43: 0 | C43: 0 | D43: 0 | E43: 0 | F43: 0 | G43: 0 | H43: 0 | M43: Feb | N43: 1 | O43: 1 | P43: 0 | Q43: 1 | R43: 1 | S43: 1 | T43: 0 | Y43: Feb | Z43: 0 | AA43: 0 | AB43: 0 | AC43: 0 | AD43: 0 | AE43: 0 | AF43: 0 | AK43: Feb | AL43: 0 | AM43: 0 | AN43: 0 | AO43: 1 | AP43: 0 | AQ43: 1 | AR43: 0 | AW43: Feb | AX43: 0 | AY43: 0 | AZ43: 0 | BA43: 0 | BB43: 0 | BC43: 0 | BD43: 0 | BI43: Feb | BJ43: 0 | BK43: 0 | BL43: 0 | BM43: 0 | BN43: 0 | BO43: 0 | BP43: 0 | BU43: Feb | BV43: 0 | BW43: 0 | BX43: 0 | BY43: 0 | BZ43: 0 | CA43: 0 | CB43: 0 | CG43: Feb | CH43: 0 | CI43: 0 | CJ43: 0 | CK43: 0 | CL43: 0 | CM43: 0 | CN43: 0 | CS43: Feb | CT43: 0 | CU43: 0 | CV43: 0 | CW43: 0 | CX43: 0 | CY43: 0 | CZ43: 0 | DE43: Feb | DF43: 0 | DG43: 0 | DH43: 0 | DI43: 0 | DJ43: 0 | DK43: 0 | DL43: 0
A44: Mar | B44: 0 | C44: 0 | D44: 0 | E44: 0 | F44: 0 | G44: 0 | H44: 0 | M44: Mar | N44: 0 | O44: 0 | P44: 0 | Q44: 0 | R44: 0 | S44: 0 | T44: 0 | Y44: Mar | Z44: 0 | AA44: 0 | AB44: 0 | AC44: 0 | AD44: 0 | AE44: 0 | AF44: 0 | AK44: Mar | AL44: 0 | AM44: 0 | AN44: 0 | AO44: 0 | AP44: 0 | AQ44: 0 | AR44: 0 | AW44: Mar | AX44: 0 | AY44: 0 | AZ44: 0 | BA44: 0 | BB44: 0 | BC44: 0 | BD44: 0 | BI44: Mar | BJ44: 0 | BK44: 0 | BL44: 0 | BM44: 0 | BN44: 0 | BO44: 0 | BP44: 0 | BU44: Mar | BV44: 0 | BW44: 0 | BX44: 0 | BY44: 0 | BZ44: 0 | CA44: 0 | CB44: 0 | CG44: Mar | CH44: 0 | CI44: 0 | CJ44: 0 | CK44: 0 | CL44: 0 | CM44: 0 | CN44: 0 | CS44: Mar | CT44: 0 | CU44: 0 | CV44: 0 | CW44: 0 | CX44: 0 | CY44: 0 | CZ44: 0 | DE44: Mar | DF44: 0 | DG44: 0 | DH44: 0 | DI44: 0 | DJ44: 0 | DK44: 0 | DL44: 0
B49: Column Labels | N49: Column Labels | Z49: Column Labels | AL49: Column Labels | AX49: Column Labels | BJ49: Column Labels | BV49: Column Labels | CH49: Column Labels | CT49: Column Labels | DI49: Column Labels
B50: MB | N50: MB | Z50: MB | AL50: MB | AX50: MB | BJ50: MB | BV50: MB | CH50: MB | CT50: MB | DI50: MB
B51: Cost of spoilage | N51: Cost of spoilage | Z51: Cost of spoilage | AL51: Cost of spoilage | AX51: Cost of spoilage | BJ51: Cost of spoilage | BV51: Cost of spoilage | CH51: Cost of spoilage | CT51: Cost of spoilage | DI51: Cost of spoilage
A52: Row Labels | B52: -T_Pump/M | C52: Pump/M | M52: Row Labels | N52: Sum of T_Pump/A | O52: -Pump/A | Y52: Row Labels | Z52: -T_INJ/M | AA52: -INJ/M | AK52: Row Labels | AL52: -T_INJ/A | AM52: -INJ/A | AW52: Row Labels | AX52: - T_Vavle | AY52: -Vavle | BI52: Row Labels | BJ52: -T_SOL | BK52: -SOL | BU52: Row Labels | BV52: -T_UC/M | BW52: -UC/M | CG52: Row Labels | CH52: -T_UC/A | CI52: - UC/A | CS52: Row Labels | CT52: -T_GDP | CU52: -GDP | DH52: Row Labels | DI52: -T_SIFS/DF | DJ52: -SIFS/DF
A53: Apr | B53: 0.26915112 | C53: 0.19 | M53: Apr | N53: 2.1540277 | O53: 1.62 | Y53: Apr | Z53: 1.9798676 | AA53: 1.74 | AK53: Apr | AL53: 4.5910012 | AM53: 3.83 | AW53: Apr | AX53: 1.1211463 | AY53: 0.99 | BI53: Apr | BJ53: 2.0543752 | BK53: 1.77 | BU53: Apr | BV53: 1.9557577 | BW53: 1.91 | CG53: Apr | CH53: 0.85347012 | CI53: 0.58 | CS53: Apr | CT53: 1.9000327 | CU53: 1.44 | DH53: Apr | DI53: 0.16406098 | DJ53: 0.11
A54: May | B54: 0.26030076 | C54: 0.29 | M54: May | N54: 2.2269609 | O54: 1.69 | Y54: May | Z54: 2.0690648 | AA54: 2.36 | AK54: May | AL54: 4.54694 | AM54: 4.75 | AW54: May | AX54: 1.1723113 | AY54: 1.15 | BI54: May | BJ54: 2.1368057 | BK54: 2.58 | BU54: May | BV54: 1.3100624 | BW54: 1.8 | CG54: May | CH54: 0.87727388 | CI54: 0.72 | CS54: May | CT54: 2.0725175 | CU54: 2.02 | DH54: May | DI54: 0.15835369 | DJ54: 0.11
A55: Jun | B55: 0.28281841 | C55: 0.64877209 | M55: Jun | N55: 2.2278902 | O55: 1.8874631 | Y55: Jun | Z55: 2.0912217 | AA55: 2.3743258 | AK55: Jun | AL55: 4.7503456 | AM55: 4.6965641 | AW55: Jun | AX55: 1.2599926 | AY55: 1.519972 | BI55: Jun | BJ55: 2.2493809 | BK55: 2.439633 | BU55: Jun | BV55: 1.4890538 | BW55: 1.7951673 | CG55: Jun | CH55: 0.93944452 | CI55: 0.6406852 | CS55: Jun | CT55: 2.1541837 | CU55: 2.1170631 | DH55: Jun | DI55: 0.19336997 | DJ55: 0.154317
A56: Jul | B56: 0.24786875 | C56: 0.17760193 | M56: Jul | N56: 2.1703098 | O56: 1.9250392 | Y56: Jul | Z56: 2.0799643 | AA56: 2.2078515 | AK56: Jul | AL56: 4.5112613 | AM56: 4.312509 | AW56: Jul | AX56: 1.2120857 | AY56: 1.028643 | BI56: Jul | BJ56: 2.0620994 | BK56: 2.93841 | BU56: Jul | BV56: 1.4719735 | BW56: 1.5303763 | CG56: Jul | CH56: 0.96570584 | CI56: 0.74793824 | CS56: Jul | CT56: 2.0206608 | CU56: 2.1623883 | DH56: Jul | DI56: 0.14220931 | DJ56: 0.13953
A57: Aug | B57: 0.28524565 | C57: 0.21343181 | M57: Aug | N57: 2.2935274 | O57: 1.6393891 | Y57: Aug | Z57: 2.0966419 | AA57: 2.2312255 | AK57: Aug | AL57: 4.857574 | AM57: 5.40721 | AW57: Aug | AX57: 1.2623393 | AY57: 1.175156 | BI57: Aug | BJ57: 2.1949603 | BK57: 3.220153 | BU57: Aug | BV57: 1.4812051 | BW57: 1.7533772 | CG57: Aug | CH57: 1.0006611 | CI57: 1.7533772 | CS57: Aug | CT57: 2.012642 | CU57: 3.9941965 | DH57: Aug | DI57: 0.18681132 | DJ57: 0.228292
A58: Sep | B58: 0.27620883 | C58: 0.23302392 | M58: Sep | N58: 2.210397 | O58: 1.1672612 | Y58: Sep | Z58: 2.0964345 | AA58: 2.52 | AK58: Sep | AL58: 4.8159528 | AM58: 5.06 | AW58: Sep | AX58: 1.2768186 | AY58: 1.32 | BI58: Sep | BJ58: 2.1979622 | BK58: 2.77 | BU58: Sep | BV58: 1.424042 | BW58: 2.776 | CG58: Sep | CH58: 0.92569076 | CI58: 0.799 | CS58: Sep | CT58: 1.9820569 | CU58: 3.48 | DH58: Sep | DI58: 0.17184939 | DJ58: 0.155
A59: Oct | B59: 0.27845188 | C59: 0.21680767 | M59: Oct | N59: 2.2367157 | O59: 1.2876895 | Y59: Oct | Z59: 2.0842312 | AA59: 2.0434032 | AK59: Oct | AL59: 4.8005798 | AM59: 4.0685952 | AW59: Oct | AX59: 1.2291118 | AY59: 1.2786867 | BI59: Oct | BJ59: 2.111104 | BK59: 2.1936924 | BU59: Oct | BV59: 1.4746437 | BW59: 2.0922545 | CG59: Oct | CH59: 0.90943924 | CI59: 0.56943959 | CS59: Oct | CT59: 1.9868566 | CU59: 4.2151349 | DH59: Oct | DI59: 0.17911751 | DJ59: 0.17529443
A60: Nov | B60: 0.26420376 | C60: 0.22687753 | M60: Nov | N60: 2.2047033 | O60: 1.5339443 | Y60: Nov | Z60: 2.0426154 | AA60: 2.258194 | AK60: Nov | AL60: 4.5505178 | AM60: 4.2696829 | AW60: Nov | AX60: 1.1477678 | AY60: 0 | BI60: Nov | BJ60: 1.9142458 | BK60: 0 | BU60: Nov | BV60: 1.514728 | BW60: 2.228012 | CG60: Nov | CH60: 0.99286228 | CI60: 0.46284432 | CS60: Nov | CT60: 2.0286181 | CU60: 2.3541939 | DH60: Nov | DI60: 0.15871631 | DJ60: 0
A61: Dec | B61: 0.27449528 | C61: 0.331 | M61: Dec | N61: 2.2270878 | O61: 1.494 | Y61: Dec | Z61: 2.071142 | AA61: 1.988 | AK61: Dec | AL61: 4.7154584 | AM61: 3.989 | AW61: Dec | AX61: 1.1705216 | AY61: 1.11 | BI61: Dec | BJ61: 1.9175276 | BK61: 1.67 | BU61: Dec | BV61: 1.4162911 | BW61: 1.684 | CG61: Dec | CH61: 0.97424432 | CI61: 0.515 | CS61: Dec | CT61: 1.7958162 | CU61: 1.74 | DH61: Dec | DI61: 0.16722995 | DJ61: 0.27
A62: Jan | B62: 0.27264734 | C62: 0.296 | M62: Jan | N62: 2.247182 | O62: 1.75 | Y62: Jan | Z62: 2.114255 | AA62: 2.47 | AK62: Jan | AL62: 4.5961882 | AM62: 4.8 | AW62: Jan | AX62: 1.1457904 | AY62: 1.11 | BI62: Jan | BJ62: 1.8809481 | BK62: 2.18 | BU62: Jan | BV62: 1.3765777 | BW62: 1.912 | CG62: Jan | CH62: 0.99625784 | CI62: 0.777 | CS62: Jan | CT62: 1.7522052 | CU62: 2.784 | DH62: Jan | DI62: 0.17150253 | DJ62: 0.25
A63: Feb | B63: 0.27600043 | C63: 0.31639037 | M63: Feb | N63: 2.2986537 | O63: 1.6143153 | Y63: Feb | Z63: 2.1389042 | AA63: 2.3346576 | AK63: Feb | AL63: 4.6307153 | AM63: 5.3196105 | AW63: Feb | AX63: 1.1197695 | AY63: 0 | BI63: Feb | BJ63: 1.8345063 | BK63: 0 | BU63: Feb | BV63: 1.388301 | BW63: 2.5515468 | CG63: Feb | CH63: 0.6871922 | CI63: 0.59857492 | CS63: Feb | CT63: 1.7408439 | CU63: 4.0787032 | DH63: Feb | DI63: 0.17604314 | DJ63: 0
A64: Mar | B64: 0.27905515 | C64: 0 | M64: Mar | N64: 2.2448065 | O64: 0 | Y64: Mar | Z64: 2.1337327 | AA64: 0 | AK64: Mar | AL64: 4.8468241 | AM64: 0 | AW64: Mar | AX64: 1.2245115 | AY64: 0 | BI64: Mar | BJ64: 1.9282009 | BK64: 0 | BU64: Mar | BV64: 1.3664382 | BW64: 0 | CG64: Mar | CH64: 0.66201896 | CI64: 0 | CS64: Mar | CT64: 1.780594 | CU64: 0 | DH64: Mar | DI64: 0.1769891 | DJ64: 0
A66: Delivery
A68: -Pump/M | B68: Column Labels | J68: -Pump/A | K68: Column Labels | S68: - INJ/M | T68: Column Labels | AB68: -INJ/A | AC68: Column Labels | AK68: -Vavle | AL68: Column Labels | AT68: -SOL | AU68: Column Labels | BC68: -UC/M | BD68: Column Labels | BL68: -UC/A | BM68: Column Labels | BU68: - GDP | BV68: Column Labels | CD68: -SIFS/DF | CE68: Column Labels
B69: Long BM >3 hr | C69: Premium/Unplanned freight | D69: Unplanned holiday working | K69: Long BM >3 hr | L69: Premium/Unplanned freight | M69: Unplanned holiday working | T69: Long BM >3 hr | U69: Premium/Unplanned freight | V69: Unplanned holiday working | W69: Grand Total | AC69: Long BM >3 hr | AD69: Premium/Unplanned freight | AE69: Unplanned holiday working | AL69: Long BM >3 hr | AM69: Premium/Unplanned freight | AN69: Unplanned holiday working | AO69: Grand Total | AU69: Long BM >3 hr | AV69: Premium/Unplanned freight | AW69: Unplanned holiday working | AX69: Grand Total | BD69: Long BM >3 hr | BE69: Premium/Unplanned freight | BF69: Unplanned holiday working | BG69: Grand Total | BM69: Long BM >3 hr | BN69: Premium/Unplanned freight | BO69: Unplanned holiday working | BP69: Grand Total | BV69: Long BM >3 hr | BW69: Premium/Unplanned freight | BX69: Unplanned holiday working | BY69: Grand Total | CE69: Long BM >3 hr | CF69: Premium/Unplanned freight | CG69: Unplanned holiday working | CH69: Grand Total
A70: Row Labels | B70: Case | C70: MB | D70: Day | J70: Row Labels | K70: Case | L70: MB | M70: Day | S70: Row Labels | T70: Case | U70: MB | V70: Day | AB70: Row Labels | AC70: Case | AD70: MB | AE70: Day | AK70: Row Labels | AL70: Case | AM70: MB | AN70: Day | AT70: Row Labels | AU70: Case | AV70: MB | AW70: Day | BC70: Row Labels | BD70: Case | BE70: MB | BF70: Day | BL70: Row Labels | BM70: Case | BN70: MB | BO70: Day | BU70: Row Labels | BV70: Case | BW70: MB | BX70: Day | CD70: Row Labels | CE70: Case | CF70: MB | CG70: Day
A71: Apr | B71: 0 | C71: 0 | D71: 0 | J71: Apr | K71: 0 | L71: 0.52 | M71: 0 | S71: Apr | T71: 0 | U71: 0 | V71: 0 | W71: 0 | AB71: Apr | AC71: 5 | AD71: 0 | AE71: 0 | AK71: Apr | AL71: 0 | AM71: 0 | AN71: 0 | AO71: 0 | AT71: Apr | AU71: 1 | AV71: 0 | AW71: 0 | AX71: 1 | BC71: Apr | BD71: 2 | BE71: 0 | BF71: 1 | BG71: 3 | BL71: Apr | BM71: 0 | BN71: 0 | BO71: 0 | BP71: 0 | BU71: Apr | BV71: 1 | BW71: 0 | BX71: 0 | BY71: 1 | CD71: Apr | CE71: 1 | CF71: 0 | CG71: 0 | CH71: 1
A72: May | B72: 0 | C72: 0 | D72: 0 | J72: May | K72: 1 | L72: 0 | M72: 1 | S72: May | T72: 0 | U72: 0 | V72: 0 | W72: 0 | AB72: May | AC72: 4 | AD72: 0 | AE72: 0 | AK72: May | AL72: 3 | AM72: 0 | AN72: 0 | AO72: 3 | AT72: May | AU72: 1 | AV72: 0 | AW72: 1 | AX72: 2 | BC72: May | BD72: 2 | BE72: 0 | BF72: 0 | BG72: 2 | BL72: May | BM72: 3 | BN72: 0 | BO72: 1 | BP72: 4 | BU72: May | BV72: 1 | BW72: 0 | BX72: 0 | BY72: 1 | CD72: May | CE72: 0 | CF72: 0 | CG72: 1 | CH72: 1
A73: Jun | B73: 0 | C73: 0 | D73: 0 | J73: Jun | K73: 2 | L73: 0 | M73: 0 | S73: Jun | T73: 0 | U73: 0 | V73: 0 | W73: 0 | AB73: Jun | AC73: 1 | AD73: 0 | AE73: 0 | AK73: Jun | AL73: 1 | AM73: 0 | AN73: 0 | AO73: 1 | AT73: Jun | AU73: 5 | AV73: 0 | AW73: 0 | AX73: 5 | BC73: Jun | BD73: 4 | BE73: 0.18 | BF73: 1 | BG73: 5.18 | BL73: Jun | BM73: 2 | BN73: 0 | BO73: 0 | BP73: 2 | BU73: Jun | BV73: 4 | BW73: 0.25 | BX73: 0 | BY73: 4.25 | CD73: Jun | CE73: 0 | CF73: 0 | CG73: 1 | CH73: 1
A74: Jul | B74: 0 | C74: 0 | D74: 0 | J74: Jul | K74: 0 | L74: 0 | M74: 0 | S74: Jul | T74: 0 | U74: 0 | V74: 0 | W74: 0 | AB74: Jul | AC74: 0 | AD74: 0 | AE74: 0 | AK74: Jul | AL74: 0 | AM74: 0 | AN74: 0 | AO74: 0 | AT74: Jul | AU74: 3 | AV74: 0 | AW74: 0 | AX74: 3 | BC74: Jul | BD74: 2 | BE74: 0 | BF74: 1 | BG74: 3 | BL74: Jul | BM74: 2 | BN74: 0 | BO74: 1 | BP74: 3 | BU74: Jul | BV74: 1 | BW74: 0 | BX74: 0 | BY74: 1 | CD74: Jul | CE74: 0 | CF74: 0.63 | CG74: 0 | CH74: 0.63
A75: Aug | B75: 0 | C75: 0 | D75: 0 | J75: Aug | K75: 0 | L75: 0 | M75: 0 | S75: Aug | T75: 0 | U75: 0 | V75: 0 | W75: 0 | AB75: Aug | AC75: 0 | AD75: 0 | AE75: 0 | AK75: Aug | AL75: 1 | AM75: 0 | AN75: 0 | AO75: 1 | AT75: Aug | AU75: 5 | AV75: 0 | AW75: 1 | AX75: 6 | BC75: Aug | BD75: 8 | BE75: 0.14 | BF75: 1 | BG75: 9.14 | BL75: Aug | BM75: 1 | BN75: 0 | BO75: 1 | BP75: 2 | BU75: Aug | BV75: 3 | BW75: 0 | BX75: 0 | BY75: 3 | CD75: Aug | CE75: 0 | CF75: 0.37 | CG75: 0 | CH75: 0.37
A76: Sep | B76: 0 | D76: 0 | J76: Sep | K76: 0 | M76: 0 | S76: Sep | T76: 0 | V76: 0 | W76: 0 | AB76: Sep | AC76: 1 | AE76: 0 | AK76: Sep | AL76: 1 | AN76: 1 | AO76: 2 | AT76: Sep | AU76: 3 | AW76: 0 | AX76: 3 | BC76: Sep | BD76: 6 | BF76: 1 | BG76: 7 | BL76: Sep | BM76: 0 | BO76: 0 | BP76: 0 | BU76: Sep | BV76: 2 | BX76: 1 | BY76: 3 | CD76: Sep | CE76: 0 | CF76: 0.16 | CG76: 0 | CH76: 0.16
A77: Oct | B77: 0 | D77: 0 | J77: Oct | K77: 0 | M77: 0 | S77: Oct | T77: 0 | U77: 0 | V77: 0 | W77: 0 | AB77: Oct | AC77: 1 | AE77: 0 | AK77: Oct | AL77: 3 | AN77: 0 | AO77: 3 | AT77: Oct | AU77: 5 | AW77: 0 | AX77: 5 | BC77: Oct | BD77: 0 | BE77: 0.02 | BF77: 0 | BG77: 0.02 | BL77: Oct | BM77: 0 | BO77: 0 | BP77: 0 | BU77: Oct | BV77: 1 | BX77: 1 | BY77: 2 | CD77: Oct | CE77: 1 | CF77: 0.07 | CG77: 1 | CH77: 2.07
A78: Nov | B78: 0 | D78: 0 | J78: Nov | K78: 2 | M78: 0 | S78: Nov | T78: 0 | V78: 0 | W78: 0 | AB78: Nov | AC78: 3 | AE78: 0 | AK78: Nov | AL78: 0 | AN78: 0 | AO78: 0 | AT78: Nov | AU78: 0 | AW78: 1 | AX78: 1 | BC78: Nov | BD78: 3 | BF78: 0 | BG78: 3 | BL78: Nov | BM78: 0 | BO78: 0 | BP78: 0 | BU78: Nov | BV78: 0 | BX78: 1 | BY78: 1 | CD78: Nov | CE78: 0 | CF78: 0.06 | CG78: 0 | CH78: 0.06
A79: Dec | B79: 0 | D79: 0 | J79: Dec | K79: 2 | M79: 0 | S79: Dec | T79: 0 | V79: 0 | W79: 0 | AB79: Dec | AC79: 0 | AE79: 0 | AK79: Dec | AL79: 0 | AN79: 0 | AO79: 0 | AT79: Dec | AU79: 1 | AW79: 0 | AX79: 1 | BC79: Dec | BD79: 1 | BF79: 0 | BG79: 1 | BL79: Dec | BM79: 0 | BO79: 0 | BP79: 0 | BU79: Dec | BV79: 0 | BX79: 0 | BY79: 0 | CD79: Dec | CE79: 0 | CF79: 0.19 | CG79: 0 | CH79: 0.19
A80: Jan | B80: 0 | C80: 0 | D80: 0 | J80: Jan | K80: 0 | L80: 0 | M80: 0 | S80: Jan | T80: 0 | U80: 0 | V80: 0 | W80: 0 | AB80: Jan | AC80: 0 | AD80: 0 | AE80: 0 | AK80: Jan | AL80: 0 | AM80: 0 | AN80: 1 | AO80: 1 | AT80: Jan | AU80: 4 | AV80: 0 | AW80: 0 | AX80: 4 | BC80: Jan | BD80: 3 | BE80: 0 | BF80: 0 | BG80: 3 | BL80: Jan | BM80: 1 | BN80: 0 | BO80: 0 | BP80: 1 | BU80: Jan | BV80: 0 | BW80: 0 | BX80: 0 | BY80: 0 | CD80: Jan | CE80: 1 | CF80: 0.05 | CG80: 0 | CH80: 1.05
A81: Feb | C81: 0 | J81: Feb | L81: 0 | S81: Feb | U81: 0 | W81: 0 | AB81: Feb | AD81: 0 | AK81: Feb | AM81: 0 | AO81: 0 | AT81: Feb | AV81: 0 | AX81: 0 | BC81: Feb | BE81: 0 | BG81: 0 | BL81: Feb | BN81: 0 | BP81: 0 | BU81: Feb | BW81: 0 | BY81: 0 | CD81: Feb | CF81: 0.05 | CH81: 0.05
A82: Mar | J82: Mar | S82: Mar | AB82: Mar | AK82: Mar | AT82: Mar | BC82: Mar | BL82: Mar | BU82: Mar | CD82: Mar
S83: Grand Total | T83: 0 | U83: 0 | V83: 0 | W83: 0 | AK83: Grand Total | AL83: 9 | AM83: 0 | AN83: 2 | AO83: 11 | AT83: Grand Total | AU83: 28 | AV83: 0 | AW83: 3 | AX83: 31 | BC83: Grand Total | BD83: 31 | BE83: 0.34 | BF83: 5 | BG83: 36.34 | BL83: Grand Total | BM83: 9 | BN83: 0 | BO83: 3 | BP83: 12 | BU83: Grand Total | BV83: 13 | BW83: 0.25 | BX83: 3 | BY83: 16.25 | CD83: Grand Total | CE83: 3 | CF83: 1.58 | CG83: 3 | CH83: 7.58
A87: Compliance
F89: Sub | G89: Business compliance | K89: Sub | L89: Business compliance | P89: Sub | Q89: Business compliance | U89: Sub | V89: Business compliance | Z89: Sub | AA89: Business compliance | AE89: Sub | AF89: Business compliance | AJ89: Sub | AK89: Business compliance | AO89: Sub | AP89: Business compliance | AU89: Sub | AV89: Business compliance | AZ89: Sub | BA89: Business compliance | BE89: Sub | BF89: Business compliance | BK89: Sub | BL89: Business compliance | BQ89: Sub | BR89: Business compliance | BV89: Sub | BW89: Business compliance | CA89: Sub | CB89: Business compliance | CF89: Sub | CG89: Business compliance | CK89: Sub | CL89: Business compliance | CP89: Sub | CQ89: Business compliance | CU89: Sub | CV89: Business compliance | CZ89: Sub | DA89: Business compliance
F91: -Pump/A | G91: Column Labels | K91: -INJ/M | L91: Column Labels | P91: -INJ/A | Q91: Column Labels | U91: -Vavle | V91: Column Labels | Z91: - SOL | AA91: Column Labels | AE91: - UC/M | AF91: Column Labels | AJ91: -UC/A | AK91: Column Labels | AO91: -SOL | AP91: Column Labels | AU91: -GDP | AV91: Column Labels | BA91: Column Labels | BF91: Column Labels | BK91: - WH | BL91: Column Labels | BR91: Column Labels | BV91: -TIE | BW91: Column Labels | CA91: -QA&QC | CB91: Column Labels | CF91: -ADM | CG91: Column Labels | CK91: -PE | CL91: Column Labels | CP91: -PC | CQ91: Column Labels | CV91: Column Labels | CZ91: -SE | DA91: Column Labels
G92: Special purchasing | H92: Urgent purchasing | I92: Urgent purchasing clear within3 Month | L92: Special purchasing | M92: Urgent purchasing | N92: Urgent purchasing clear within3 Month | Q92: Special purchasing | R92: Urgent purchasing | S92: Urgent purchasing clear within3 Month | V92: Special purchasing | W92: Urgent purchasing | X92: Urgent purchasing clear within3 Month | AA92: Special purchasing | AB92: Urgent purchasing | AC92: Urgent purchasing clear within3 Month | AF92: Special purchasing | AG92: Urgent purchasing | AH92: Urgent purchasing clear within3 Month | AK92: Special purchasing | AL92: Urgent purchasing | AM92: Urgent purchasing clear within3 Month | AP92: Special purchasing | AQ92: Urgent purchasing | AR92: Urgent purchasing clear within3 Month | AV92: Special purchasing | AW92: Urgent purchasing | AX92: Urgent purchasing clear within3 Month | BA92: Special purchasing | BB92: Urgent purchasing | BC92: Urgent purchasing clear within3 Month | BF92: MB | BL92: Special purchasing | BM92: Urgent purchasing | BN92: Urgent purchasing clear within3 Month | BR92: Special purchasing | BS92: Urgent purchasing | BT92: Urgent purchasing clear within3 Month | BW92: Special purchasing | BX92: Urgent purchasing | BY92: Urgent purchasing clear within3 Month | CB92: Special purchasing | CC92: Urgent purchasing | CD92: Urgent purchasing clear within3 Month | CG92: Special purchasing | CH92: Urgent purchasing | CI92: Urgent purchasing clear within3 Month | CL92: Special purchasing | CM92: Urgent purchasing | CN92: Urgent purchasing clear within3 Month | CQ92: Special purchasing | CR92: Urgent purchasing | CS92: Urgent purchasing clear within3 Month | CV92: Special purchasing | CW92: Urgent purchasing | CX92: Urgent purchasing clear within3 Month | DA92: Special purchasing | DB92: Urgent purchasing | DC92: Urgent purchasing clear within3 Month
F93: Row Labels | K93: Row Labels | P93: Row Labels | U93: Row Labels | Z93: Row Labels | AE93: Row Labels | AJ93: Row Labels | AO93: Row Labels | AU93: Row Labels | AZ93: Row Labels | BE93: Row Labels | BF93: -TIE | BG93: Count of measurment | BK93: Row Labels | BQ93: Row Labels | BV93: Row Labels | CA93: Row Labels | CF93: Row Labels | CK93: Row Labels | CP93: Row Labels | CU93: Row Labels | CZ93: Row Labels
F94: Apr | G94: 0 | H94: 0 | I94: 0 | K94: Apr | L94: 0 | M94: 0 | N94: 0 | P94: Apr | Q94: 0 | R94: 0 | S94: 0 | U94: Apr | V94: 0 | W94: 0 | X94: 0 | Z94: Apr | AA94: 0 | AB94: 0 | AC94: 0 | AE94: Apr | AF94: 0 | AG94: 0.062 | AH94: 0 | AJ94: Apr | AK94: 0 | AL94: 0 | AM94: 0 | AO94: Apr | AP94: 0 | AQ94: 0 | AR94: 0 | AU94: Apr | AV94: 0 | AW94: 0 | AX94: 0 | AZ94: Apr | BE94: Apr | BF94: 0 | BG94: 3 | BK94: Apr | BL94: 0 | BM94: 0 | BN94: 0 | BQ94: Apr | BV94: Apr | BW94: 0 | BX94: 0 | BY94: 0 | CA94: Apr | CB94: 0 | CC94: 0 | CD94: 0 | CF94: Apr | CG94: 0 | CH94: 0 | CI94: 0 | CK94: Apr | CL94: 1.63 | CM94: 2.325 | CN94: 0 | CP94: Apr | CQ94: 0 | CR94: 0 | CS94: 0 | CU94: Apr | CZ94: Apr | DA94: 0.17 | DB94: 0 | DC94: 0
F95: May | G95: 0 | H95: 0 | I95: 0 | K95: May | L95: 0 | M95: 1.991 | N95: 0 | P95: May | Q95: 0 | R95: 0 | S95: 0 | U95: May | V95: 0 | W95: 0.3465 | X95: 0 | Z95: May | AA95: 0 | AB95: 0 | AC95: 0 | AE95: May | AF95: 0 | AG95: 0 | AH95: 0 | AJ95: May | AK95: 0 | AL95: 0 | AM95: 0 | AO95: May | AP95: 0 | AQ95: 0 | AR95: 0 | AU95: May | AV95: 0 | AW95: 0.025 | AX95: 0 | AZ95: May | BE95: May | BF95: 0 | BG95: 3 | BK95: May | BL95: 0 | BM95: 0 | BN95: 0 | BQ95: May | BV95: May | BW95: 0 | BX95: 0 | BY95: 0 | CA95: May | CB95: 0 | CC95: 0.2363 | CD95: 0 | CF95: May | CG95: 0 | CH95: 0 | CI95: 0 | CK95: May | CL95: 1.68 | CM95: 0.00378 | CN95: 0 | CP95: May | CQ95: 0 | CR95: 0 | CS95: 0 | CU95: May | CZ95: May | DA95: 0 | DB95: 0 | DC95: 0
F96: Jun | G96: 0 | H96: 0 | I96: 0 | K96: Jun | L96: 0 | M96: 0 | N96: 0 | P96: Jun | Q96: 0 | R96: 0 | S96: 0 | U96: Jun | V96: 0 | W96: 0.0844 | X96: 0 | Z96: Jun | AA96: 0 | AB96: 0 | AC96: 0 | AE96: Jun | AF96: 0 | AG96: 0 | AH96: 0 | AJ96: Jun | AK96: 0 | AL96: 0 | AM96: 0 | AO96: Jun | AP96: 0 | AQ96: 0 | AR96: 0 | AU96: Jun | AV96: 0 | AW96: 0.359 | AX96: 0 | AZ96: Jun | BE96: Jun | BF96: 0 | BG96: 3 | BK96: Jun | BL96: 0 | BM96: 0.097 | BN96: 0 | BQ96: Jun | BV96: Jun | BW96: 0 | BX96: 0 | BY96: 0 | CA96: Jun | CB96: 0.11 | CC96: 0 | CD96: 0 | CF96: Jun | CG96: 0 | CH96: 0 | CI96: 0 | CK96: Jun | CL96: 0.92 | CM96: 2.509 | CN96: 0.93 | CP96: Jun | CQ96: 0 | CR96: 0 | CS96: 0 | CU96: Jun | CZ96: Jun | DA96: 0 | DB96: 0 | DC96: 0
F97: Jul | G97: 0 | H97: 0 | I97: 0 | K97: Jul | L97: 0 | M97: 0 | N97: 0 | P97: Jul | Q97: 0 | R97: 0 | S97: 0 | U97: Jul | V97: 0 | W97: 0 | X97: 0 | Z97: Jul | AA97: 0 | AB97: 0 | AC97: 0 | AE97: Jul | AF97: 0 | AG97: 0 | AH97: 0 | AJ97: Jul | AK97: 0 | AL97: 0 | AM97: 0 | AO97: Jul | AP97: 0 | AQ97: 0 | AR97: 0 | AU97: Jul | AV97: 0 | AW97: 0 | AX97: 0 | AZ97: Jul | BE97: Jul | BF97: 0 | BG97: 3 | BK97: Jul | BL97: 0 | BM97: 0 | BN97: 0 | BQ97: Jul | BV97: Jul | BW97: 0 | BX97: 0 | BY97: 0 | CA97: Jul | CB97: 0 | CC97: 0.0124 | CD97: 0 | CF97: Jul | CG97: 0 | CH97: 0.0158 | CI97: 0 | CK97: Jul | CL97: 0 | CM97: 10.5284 | CN97: 0 | CP97: Jul | CQ97: 0 | CR97: 0 | CS97: 0 | CU97: Jul | CZ97: Jul | DA97: 0 | DB97: 0 | DC97: 0
F98: Aug | G98: 0 | H98: 0 | I98: 0 | K98: Aug | L98: 0 | M98: 0 | N98: 0 | P98: Aug | Q98: 0 | R98: 0 | S98: 0 | U98: Aug | V98: 0 | W98: 0 | X98: 0 | Z98: Aug | AA98: 0 | AB98: 0 | AC98: 0 | AE98: Aug | AF98: 0 | AG98: 0 | AH98: 0 | AJ98: Aug | AK98: 0 | AL98: 0 | AM98: 0 | AO98: Aug | AP98: 0 | AQ98: 0 | AR98: 0 | AU98: Aug | AV98: 0 | AW98: 0.0082 | AX98: 0 | AZ98: Aug | BE98: Aug | BF98: 0.31 | BG98: 3 | BK98: Aug | BL98: 0.31 | BM98: 0 | BN98: 0 | BQ98: Aug | BV98: Aug | BW98: 0.31 | BX98: 0 | BY98: 0 | CA98: Aug | CB98: 0 | CC98: 0 | CD98: 0 | CF98: Aug | CG98: 0 | CH98: 0 | CI98: 0 | CK98: Aug | CL98: 5.86 | CM98: 6.1307 | CN98: 0 | CP98: Aug | CQ98: 0 | CR98: 0 | CS98: 0 | CU98: Aug | CZ98: Aug | DA98: 0.34 | DB98: 0 | DC98: 0
F99: Sep | G99: 0 | H99: 0 | I99: 0 | K99: Sep | L99: 0 | M99: 0 | N99: 0 | P99: Sep | Q99: 0 | R99: 0 | S99: 0 | U99: Sep | V99: 0 | W99: 0.827 | X99: 0 | Z99: Sep | AA99: 0 | AB99: 0 | AC99: 0 | AE99: Sep | AF99: 0 | AG99: 0 | AH99: 0 | AJ99: Sep | AK99: 0 | AL99: 0 | AM99: 0 | AO99: Sep | AP99: 0 | AQ99: 0 | AR99: 0 | AU99: Sep | AV99: 0 | AW99: 0.037 | AX99: 0 | AZ99: Sep | BE99: Sep | BF99: 0 | BG99: 3 | BK99: Sep | BL99: 0 | BM99: 0 | BN99: 0 | BQ99: Sep | BV99: Sep | BW99: 0 | BX99: 0 | BY99: 0 | CA99: Sep | CB99: 0 | CC99: 0 | CD99: 0 | CF99: Sep | CG99: 0 | CH99: 0 | CI99: 0 | CK99: Sep | CL99: 0 | CM99: 5.4117 | CN99: 0 | CP99: Sep | CQ99: 0 | CR99: 0.805 | CS99: 0 | CU99: Sep | CZ99: Sep | DA99: 0 | DB99: 0 | DC99: 0
F100: Oct | G100: 0.65 | H100: 0 | I100: 0 | K100: Oct | L100: 0 | M100: 0 | N100: 0 | P100: Oct | Q100: 0.22 | R100: 0.09 | S100: 0 | U100: Oct | V100: 0 | W100: 0 | X100: 0 | Z100: Oct | AA100: 0 | AB100: 0 | AC100: 0 | AE100: Oct | AF100: 0 | AG100: 0 | AH100: 0 | AJ100: Oct | AK100: 0 | AL100: 0 | AM100: 0 | AO100: Oct | AP100: 0 | AQ100: 0 | AR100: 0 | AU100: Oct | AV100: 0 | AW100: 0.015 | AX100: 0 | AZ100: Oct | BE100: Oct | BF100: 0 | BG100: 3 | BK100: Oct | BL100: 0 | BM100: 0 | BN100: 0 | BQ100: Oct | BV100: Oct | BW100: 0 | BX100: 0 | BY100: 0 | CA100: Oct | CB100: 0.4 | CC100: 0.0871 | CD100: 0 | CF100: Oct | CG100: 0 | CH100: 0 | CI100: 0 | CK100: Oct | CL100: 19.686 | CM100: 5.4999 | CN100: 0 | CP100: Oct | CQ100: 0 | CR100: 0 | CS100: 0 | CU100: Oct | CZ100: Oct | DA100: 0 | DB100: 0 | DC100: 0
F101: Nov | G101: 0.32 | H101: 0 | I101: 0 | K101: Nov | L101: 0 | M101: 0.025 | N101: 0 | P101: Nov | Q101: 0 | R101: 0 | S101: 0 | U101: Nov | V101: 0 | W101: 0.287 | X101: 0 | Z101: Nov | AA101: 0 | AB101: 0.024 | AC101: 0 | AE101: Nov | AF101: 0 | AG101: 0 | AH101: 0 | AJ101: Nov | AK101: 0 | AL101: 0.136 | AM101: 0 | AO101: Nov | AP101: 0 | AQ101: 0.024 | AR101: 0 | AU101: Nov | AV101: 0 | AW101: 0.008 | AX101: 0 | AZ101: Nov | BE101: Nov | BF101: 0 | BG101: 3 | BK101: Nov | BL101: 0 | BM101: 0 | BN101: 0 | BQ101: Nov | BV101: Nov | BW101: 0 | BX101: 0 | BY101: 0 | CA101: Nov | CB101: 0 | CC101: 0 | CD101: 0 | CF101: Nov | CG101: 0 | CH101: 0 | CI101: 0 | CK101: Nov | CL101: 0.245 | CM101: 2.1299 | CN101: 0 | CP101: Nov | CQ101: 0 | CR101: 0 | CS101: 0 | CU101: Nov | CZ101: Nov | DA101: 0 | DB101: 0 | DC101: 0
F102: Dec | G102: 0 | H102: 0.0175 | I102: 0 | K102: Dec | L102: 0.8 | M102: 0 | N102: 0 | P102: Dec | Q102: 0 | R102: 0 | S102: 0 | U102: Dec | V102: 10.6 | W102: 0 | X102: 0 | Z102: Dec | AA102: 0 | AB102: 0 | AC102: 0 | AE102: Dec | AF102: 0 | AG102: 0 | AH102: 0 | AJ102: Dec | AK102: 0 | AL102: 0 | AM102: 0 | AO102: Dec | AP102: 0 | AQ102: 0 | AR102: 0 | AU102: Dec | AV102: 0 | AW102: 0.018525 | AX102: 0 | AZ102: Dec | BE102: Dec | BF102: 0 | BG102: 3 | BK102: Dec | BL102: 0 | BM102: 0 | BN102: 0 | BQ102: Dec | BV102: Dec | BW102: 0 | BX102: 0 | BY102: 0 | CA102: Dec | CB102: 0 | CC102: 0 | CD102: 0 | CF102: Dec | CG102: 0 | CH102: 0.0299 | CI102: 0 | CK102: Dec | CL102: 8.5 | CM102: 9.083051 | CN102: 0 | CP102: Dec | CQ102: 0 | CR102: 0.025 | CS102: 0 | CU102: Dec | CZ102: Dec | DA102: 0 | DB102: 0.285 | DC102: 0
F103: Jan | G103: 0 | H103: 0 | I103: 0 | K103: Jan | L103: 0 | M103: 0 | N103: 0 | P103: Jan | Q103: 0 | R103: 0.02649 | S103: 0 | U103: Jan | V103: 0 | W103: 0 | X103: 0 | Z103: Jan | AA103: 0 | AB103: 0 | AC103: 0 | AE103: Jan | AF103: 0 | AG103: 0 | AH103: 0 | AJ103: Jan | AK103: 0 | AL103: 0 | AM103: 0 | AO103: Jan | AP103: 0 | AQ103: 0 | AR103: 0 | AU103: Jan | AV103: 0 | AW103: 0 | AX103: 0 | AZ103: Jan | BE103: Jan | BF103: 0 | BG103: 3 | BK103: Jan | BL103: 0 | BM103: 0 | BN103: 0 | BQ103: Jan | BV103: Jan | BW103: 0 | BX103: 0 | BY103: 0 | CA103: Jan | CB103: 0 | CC103: 0.0041 | CD103: 0 | CF103: Jan | CG103: 0 | CH103: 0.015 | CI103: 0 | CK103: Jan | CL103: 0 | CM103: 2.886752 | CN103: 0 | CP103: Jan | CQ103: 0 | CR103: 0 | CS103: 0 | CU103: Jan | CZ103: Jan | DA103: 0 | DB103: 0 | DC103: 0
F104: Feb | G104: 0 | H104: 0.226 | I104: 0 | K104: Feb | L104: 0 | M104: 0 | N104: 0 | P104: Feb | Q104: 0 | R104: 0 | S104: 0 | U104: Feb | V104: 0.1 | W104: 0.6367 | X104: 0 | Z104: Feb | AA104: 0 | AB104: 0 | AC104: 0 | AE104: Feb | AF104: 0 | AG104: 0 | AH104: 0 | AJ104: Feb | AK104: 0 | AL104: 0 | AM104: 0 | AO104: Feb | AP104: 0 | AQ104: 0 | AR104: 0 | AU104: Feb | AV104: 0 | AW104: 0 | AX104: 0 | AZ104: Feb | BE104: Feb | BF104: 0 | BG104: 3 | BK104: Feb | BL104: 0 | BM104: 0 | BN104: 0 | BQ104: Feb | BV104: Feb | BW104: 0 | BX104: 0 | BY104: 0 | CA104: Feb | CB104: 0 | CC104: 0 | CD104: 0 | CF104: Feb | CG104: 0 | CH104: 0 | CI104: 0 | CK104: Feb | CL104: 7.9228 | CM104: 3.754 | CN104: 0 | CP104: Feb | CQ104: 0 | CR104: 0 | CS104: 0 | CU104: Feb | CZ104: Feb | DA104: 0 | DB104: 0 | DC104: 0
F105: Mar | G105: 0 | H105: 0 | I105: 0 | K105: Mar | L105: 0 | M105: 0 | N105: 0 | P105: Mar | Q105: 0 | R105: 0 | S105: 0 | U105: Mar | V105: 0 | W105: 0 | X105: 0 | Z105: Mar | AA105: 0 | AB105: 0 | AC105: 0 | AE105: Mar | AF105: 0 | AG105: 0 | AH105: 0 | AJ105: Mar | AK105: 0 | AL105: 0 | AM105: 0 | AO105: Mar | AP105: 0 | AQ105: 0 | AR105: 0 | AU105: Mar | AV105: 0 | AW105: 0 | AX105: 0 | AZ105: Mar | BE105: Mar | BF105: 0 | BG105: 3 | BK105: Mar | BL105: 0 | BM105: 0 | BN105: 0 | BQ105: Mar | BV105: Mar | BW105: 0 | BX105: 0 | BY105: 0 | CA105: Mar | CB105: 0 | CC105: 0 | CD105: 0 | CF105: Mar | CG105: 0 | CH105: 0 | CI105: 0 | CK105: Mar | CL105: 0 | CM105: 0 | CN105: 0 | CP105: Mar | CQ105: 0 | CR105: 0 | CS105: 0 | CU105: Mar | CZ105: Mar | DA105: 0 | DB105: 0 | DC105: 0
A108: Sub | B108: (All) | U108: Sub | V108: (All) | AO108: Sub | AP108: (All) | BI108: Sub | BJ108: (All) | CC108: Sub | CD108: (All) | CW108: Sub | CX108: (All) | DQ108: Sub | DR108: (All) | EK108: Sub | EL108: (All) | FE108: Sub | FF108: (All) | FY108: Sub | FZ108: (All) | GS108: Sub | GT108: (All) | HN108: Sub | HO108: (All) | IH108: Sub | II108: (All) | JB108: Sub | JC108: (All) | JV108: Sub | JW108: (All) | KP108: Sub | KQ108: (All) | LJ108: Sub | LK108: (All) | MD108: Sub | ME108: (All)
A110: -Pump/M | B110: Column Labels | U110: -Pump/A | V110: Column Labels | AO110: -INJ/M | AP110: Column Labels | BI110: -INJ/A | BJ110: Column Labels | CC110: -Vavle | CD110: Column Labels | CW110: -SOL | CX110: Column Labels | DQ110: -UC/M | DR110: Column Labels | EK110: -UC/A | EL110: Column Labels | FE110: -GDP | FF110: Column Labels | FZ110: Column Labels | GS110: -TIE | GT110: Column Labels | HN110: - WH | HO110: Column Labels | II110: Column Labels | JB110: -QA&QC | JC110: Column Labels | JV110: -ADM | JW110: Column Labels | KP110: - PE | KQ110: Column Labels | LK110: Column Labels | MD110: -SE | ME110: Column Labels
